Workbook
Name Bajo: 1
Name SegmentaciónDeDatos_Actividades: #N/A
Name SegmentaciónDeDatos_AÑO: #N/A
Name SegmentaciónDeDatos_Consecuencia: #N/A
Name SegmentaciónDeDatos_Eficacia: #N/A
Name SegmentaciónDeDatos_Nivel_cualitativo_de_riesgo: #N/A
Name SegmentaciónDeDatos_Nivel_del_riesgo: #N/A
Name SegmentaciónDeDatos_Subclasificación: #N/A
Name SegmentaciónDeDatos_Tipo_de_peligro: #N/A

Sheet HOME
C1: MATRIZ IDENTIFICACIÓN DE PELIGROS, EVALUACIÓN Y VALORACIÓN DE RIESGOS | F1: MATRIZ IDENTIFICACIÓN DE PELIGROS, EVALUACIÓN Y VALORACIÓN DE RIESGOS

Sheet RAM
C1: Matriz Evaluacion del Riesgo RAM | H1: CODIGO COL-HSEQ-FT-006 EMISIÓN 13-07-2015 VIGENCIA 21-10-2015 VERSIÓN 2 PÁGINA 1 de 1
C5: CONSECUENCIA DEL EVENTO | G5: PROBABILIDAD
B6: Nivel | C6: Personas | D6: Medio Ambiente | E6: Activos & Financiera | F6: Reputación Empresarial | G6: 1. Remoto Una vez durante la vida de las instalaciones, menor a 1 cada 20 años | H6: 2. Improbable Una vez cada 5 a 20 años. | I6: 3. Probable Una ocurrencia entre 1 y 5 años. | J6: 4. Frecuente Una o más ocurrencias por año.
B7: 1. Menor | C7: • Lesión menor • Enfermedad menor. • Primeros auxilios requeridos. • No evacuaciones. • Amenaza implícita del propietario del terreno/activista. | D7: • Daño ambiental menor y efectos confinados al arrendamiento. • Impacto confinado al arrendamiento. | E7: • Pérdida de producción insignificante. • Pérdida de producción y equipos menor de US$50,000 • Delito menor contra la propiedad. | F7: • Inquietudes localizadas, queja única del interesado y sin atención de los medios. • Sin impacto en la reputación de Parex. • Impacto mínimo en el público. | G7: 1 | H7: 2 | I7: 3 | J7: 4
B8: 2. Moderado | C8: • Lesión con auxilio médico. • Trabajo restringido. • Evacuación del sitio de trabajo. • Amenaza específica del propietario del terreno/activista. | D8: • Daño ambiental moderado. • Impactos localizados fuera del arrendamiento o fuera del sitio. • Limpieza inmediata. | E8: • Cierre de facilidades / equipos a corto plazo ( menos de una semana) • Pérdida de producción y equipos mayor de US$50,000 hasta US$500,000 • Delito mayor contra la propiedad. | F8: • Atención breve a medios locales, quejas múltiples de los interesados. • Impacto local a corto plazo sobre la reputación de Parex. • Acción legal y/o regulatoria resultante en respuesta administrativa. | G8: 2 | H8: 4 | I8: 6 | J8: 8
B9: 3. Serio | C9: • Lesión con pérdida de tiempo. • Lesiones múltiples. • Impacto sobre la salud a corto plazo (incl. daño emocional) • Evacuación de las instalaciones y del área más cercana. • Acción violenta del dueño del terreno / activista. | D9: • Daño ambiental severo reversible o a corto plazo. • Efectos dentro del campo/bloque de operaciones. • Impactos generalizados al terreno, al agua o al aire. | E9: • Instalaciones de una semana/cierre de equipos. • Pérdida de producción y equipos mayor de US$500,000 y menor de US$10 millones. • Pérdida sustancial por robo/vandalismo. | F9: • Atención prolongada del área local, de la comunidad o noticias provinciales. • Impacto adverso sobre la reputación de Parex a nivel provincial, caída a corto plazo en el precio de la acción de Parex • Acción legal y/o regulatoria resultante en multas o acciones punitivas. | G9: 3 | H9: 6 | I9: 9 | J9: 12
B10: 4. Crítico | C10: • Fatalidad •Impacto sobre la salud a largo plazo (incl.daño emocional) •Incapacidad permanente • Evacuación de las instalaciones y de la comunidad •Acción del propietario del terreno/activista involucrando armas.. | D10: • Daño ambiental severo irreversible o a largo-plazo. • Impactos generalizados al medio ambiente sensible y/o cuerpos de agua principales / vías fluviales o aire | E10: • Instalaciones de un mes/cierre de equipos • Pérdida de producción y equipos superior a US$10 millones • Ataque/atentado terrorista | F10: • Inquietudes generalizadas con extenso cubrimiento adverso de medios nacionales o internacionales. • Impacto importante a largo plazo sobre la reputación, mercado de las acciones y precio de las acciones. • Acción resultante en procesamiento judicial y/o regulatorio, o en la suspensión de las operaciones. | G10: 4 | H10: 8 | I10: 12 | J10: 16
A12: Paso 2 - Probabilidad estimada.
B13: Nivel | C13: Descripción. | E13: Probabilidad.
B14: 4 Frecuente | C14: Se espera que el evento ocurra en este proyecto. | E14: Una o más ocurrencias por año.
B15: 3 Probable | C15: Se espera que el evento ocurra en un proyecto de Parex en los próximos 1 a 5 años, pero no necesariamente en este proyecto | E15: Una ocurrencia entre 1 y 5 años.
B16: 2 Improbable. | C16: Evento de no probable ocurrerncia basado en actuales prácticas, pero que Parex puede experimentar a nivel de Compañía, en una de las instalaciones de Parex sobre la vida promedio de las instalaciones. | E16: Una vez cada 5 a 20 años.
B17: 1 Remoto | C17: Evento de no probable ocurrencia y que no se espera que Parex experimente dicho evento, pero la industria lo ha experimentado en el pasado. | E17: Una vez durante la vida de las instalaciones, menor a 1 cada 20 años
A19: Paso 3 - Determinar el Potencial del Riesgo.
A20: Consecuencia | B20: 4 Crítico | C20: 4 | D20: 8 | E20: 12 | F20: 16
B21: 3 Serio | C21: 3 | D21: 6 | E21: 9 | F21: 12
B22: 2 Moderado | C22: 2 | D22: 4 | E22: 6 | F22: 8
B23: 1 Menor | C23: 1 | D23: 2 | E23: 3 | F23: 4
C24: 1 Remoto | D24: 2 No probable | E24: 3 Probable | F24: 4 Frecuente
B25: Probabilidad
B27: EXTREMO | C27: Extremo – Actividades STOP. No se puede proceder con el trabajo hasta que el riesgo se reduzca a su más bajo nivel. (Se requiere la aprobación del Vice Presidente y/o COO)
B28: ALTO | C28: Se deben implementar medidas de control/mitigación del riesgo Altas-Extensivas. Se deben emprender esfuerzos para reducir el riesgo a un nivel MEDIO o BAJO. (Se requiere la aprobación del Gerente del Departamento).
B29: MEDIO | C29: Se deben implementar medidas de control/mitigación de los riesgos de nivel medio, para permitir que el trabajo prosiga. Se deben emprender esfuerzos para reducir el riesgo a un nivel BAJO. (Para valoración 4 se requiere la aprobación del Supervisor de Sitio, Company Man, interventor de facilidades, obras civiles, etc. Para valoración con nivel 6 se requiere la aprobación del Líder de Operación, Coordinadores, Superintendente.)
B30: BAJO | C30: Bajo– Algunas medidas de control/mitigación del riesgo pueden ser justificadas. Representa un nivel aceptable del riesgo. ( Se requiere la aprobación del Supervisor del Sitio, Company Man).

Sheet Parametros
A1: Biológico | B1: Físico | C1: Químico | D1: Psicosocial | E1: Biomecánicas | F1: Condiciones_de_seguridad | G1: Fenómenos_naturales | I1: Nivel del riesgo | J1: Tipo de peligro
A2: 1.1 Virus | B2: 2.1 Ruido | C2: 3.1 Polvos orgánicos e inorgánicos | D2: 4.1 Gestión organizacional | E2: 5.1 Postura | F2: 6.1 Mecánico | G2: 7.1 Sismo | I2: 1 | J2: 1. Biológico
A3: 1.2 Bacterias | B3: 2.2 Iluminación | C3: 3.2 Fibras | D3: 4.2 Características de la organización del trabajo | E3: 5.2 Esfuerzos | F3: 6.2 Eléctrico | G3: 7.2 Terremoto | I3: 2 | J3: 2. Físico
A4: 1.3 Hongos | B4: 2.3 Vibración | C4: 3.3 Líquidos, nieblas | D4: 4.3 Condiciones de la tarea | E4: 5.3 Movimientos repetitivos | F4: 6.3 Locativos | G4: 7.3 Vendaval | I4: 3 | J4: 3. Químico
A5: 1.4 Ricketslas | B5: 2.4 Temperaturas extremas | C5: 3.4 Líquidos, rocíos | D5: 4.4 Características del grupo social de trabajo | E5: 5.4 Manipulación manual de cargas | F5: 6.4 Tecnológico | G5: 7.4 Inundación | I5: 4 | J5: 4. Psicosocial
A6: 1.5 Parásitos | B6: 2.5 Presión | C6: 3.5 Gases y vapores | D6: 4.5 Interface persona | F6: 6.5 Accidentes de transito | G6: 7.5 Derrumbe | I6: 6 | J6: 5. Biomecánicas
A7: 1.6 Picaduras | B7: 2.6 Radiaciones ionizantes | C7: 3.6 Humos metálicos y NO metálicos | D7: 4.6 Jornada de trabajo | F7: 6.6 Públicos | G7: 7.6 Precipitaciones | I7: 8 | J7: 6. Condiciones de seguridad
A8: 1.7 Mordeduras | B8: 2.7 Radiaciones No ionizantes | C8: 3.7 Material particulado | D8: 4.7. Carga de Trabajo | F8: 6.7 Trabajo en alturas | I8: 9 | J8: 7. Fenómenos naturales
A9: 1.8 Fluidos o excrementos | D9: 4.8 Victimización y acoso (bullying) e intimidación | F9: 6.8 Espacios confinados | I9: 12
D10: 4.9 Liderazgo y la cultura de la organización | I10: 16 | J10: Consecuencias
J11: AT
J12: EL
J13: AT/EL
B14: https://static.vecteezy.com/system/resources/previews/029/920/044/non_2x/risk-icon-on-speedometer-high-risk-meter-stock-illustration-vector.jpg | J14: Bienes y Finanzas
B15: https://img.freepik.com/vector-premium/medidor-velocimetro-vectorial-flecha-salpicadero-indicadores-verdes-amarillos-naranjas-rojos-indicador-tacometro-niveles-riesgo-miedo-bitcoin-medio-alto-criptomoneda-indice-codicia_81863-5351.jpg | J15: Reputación de la empresa
B16: https://static.vecteezy.com/system/resources/previews/002/556/994/non_2x/high-risk-concept-on-speedometer-illustration-speedometer-icon-colorful-infographic-gauge-element-vector.jpg
J17: Cargos
J18: Asistente Administrativo(a) RSE Campo
A19: Calsificación | B19: Imagen | D19: Calsificación | E19: Imagen | J19: Contratistas
A20: Biológico | B20: #VALUE! | D20: Extremo | E20: #VALUE! | J20: Coordinador(a) Administrativo(a)
A21: Físico | B21: #VALUE! | D21: Alto | E21: #VALUE! | J21: Coordinador(a) de Seguridad Campo
A22: Químico | B22: #VALUE! | D22: Medio | E22: #VALUE! | J22: Gestor de RSE
A23: Psicosocial | B23: #VALUE! | D23: Bajo | E23: #VALUE! | J23: HSEQ
A24: Biomecánicas | B24: #VALUE! | J24: Ingeniero(a) de Obras Civiles
A25: Condiciones_de_seguridad | B25: #VALUE! | J25: Ingeniero(a) de Producción
A26: Fenómenos_naturales | B26: #VALUE! | J26: Ingeniero(a) Química
J27: Ingeniero(a) Senior de Perforación
J28: Profesional TIC Campo
J29: Supervisor de Bodega
J30: Supervisor de Construcción
J31: Supervisor de Mantenimiento en Campo
J32: Supervisor de Producción
J33: Supervisor de Producción General
J34: Supervisor General de Mantenimiento
J35: Todo el personal de la locación
J36: Comunidad
J37: Visitantes
J39: Estación
... J49: Boranda

Sheet L. DE MATRICES
C2: #VALUE! | D2: LISTADO DE ACTIVIDADES DEL BLOQUE
C8: ITEM | D8: Centro de trabajo | E8: Actividades | F8: Hipervinculo | G8: Celda | H8: MATRICES ACTIVIDADES
C9: 1 | D9: EXPLORACIÓN | E9: =IF(H9="","",H9) -> Transporte terrestre | F9: =IF(C9="","",HYPERLINK("#'2026'!"&G9,"Ir a la actividad"&H9)) -> Ir a la actividadTransporte terrestre | G9: {=ADDRESS(MATCH($H9,'año26'!F:F,0),COLUMN('año26'!F:F))} -> $F$11 | H9: {=_xlfn.UNIQUE(año26[Tárea])} -> Transporte terrestre
C10: =IF(H11="",IF(H10="","",C9+1),IF(H10="","",C9+1)) -> 2 | D10: EXPLORACIÓN | E10: =IF(H10="","",H10) -> Transporte Aéreo | F10: =IF(C10="","",HYPERLINK("#'2026'!"&G10,"Ir a la actividad"&H10)) -> Ir a la actividadTransporte Aéreo | G10: {=ADDRESS(MATCH($H10,'año26'!F:F,0),COLUMN('año26'!F:F))} -> $F$27 | H10: Transporte Aéreo
C11: =IF(H12="",IF(H11="","",C10+1),IF(H11="","",C10+1)) -> 3 | D11: EXPLORACIÓN | E11: =IF(H11="","",H11) -> Transporte Fluvial | F11: =IF(C11="","",HYPERLINK("#'2026'!"&G11,"Ir a la actividad"&H11)) -> Ir a la actividadTransporte Fluvial | G11: {=ADDRESS(MATCH($H11,'año26'!F:F,0),COLUMN('año26'!F:F))} -> $F$33 | H11: Transporte Fluvial
C12: =IF(H13="",IF(H12="","",C11+1),IF(H12="","",C11+1)) -> 4 | D12: EXPLORACIÓN | E12: =IF(H12="","",H12) -> Toma de muestras | F12: =IF(C12="","",HYPERLINK("#'2026'!"&G12,"Ir a la actividad"&H12)) -> Ir a la actividadToma de muestras | G12: {=ADDRESS(MATCH($H12,'año26'!F:F,0),COLUMN('año26'!F:F))} -> $F$44 | H12: Toma de muestras
C13: =IF(H14="",IF(H13="","",C12+1),IF(H13="","",C12+1)) -> 5 | D13: EXPLORACIÓN | E13: =IF(H13="","",H13) -> Estudios geológicos | F13: =IF(C13="","",HYPERLINK("#'2026'!"&G13,"Ir a la actividad"&H13)) -> Ir a la actividadEstudios geológicos | G13: {=ADDRESS(MATCH($H13,'año26'!F:F,0),COLUMN('año26'!F:F))} -> $F$65 | H13: Estudios geológicos
C14: =IF(H15="",IF(H14="","",C13+1),IF(H14="","",C13+1)) -> 6 | D14: EXPLORACIÓN | E14: =IF(H14="","",H14) -> WELL SITE - Geología de operaciones en pozo | F14: =IF(C14="","",HYPERLINK("#'2026'!"&G14,"Ir a la actividad"&H14)) -> Ir a la actividadWELL SITE - Geología de operaciones en pozo | G14: {=ADDRESS(MATCH($H14,'año26'!F:F,0),COLUMN('año26'!F:F))} -> $F$80 | H14: WELL SITE - Geología de operaciones en pozo
C15: =IF(H16="",IF(H15="","",C14+1),IF(H15="","",C14+1)) -> 7 | D15: EXPLORACIÓN | E15: =IF(H15="","",H15) -> Well Logging - Ensamblar y conectar equipos, herramientas y registros al vástago del taladro o cables para conducir las pruebas y ensayos requeridos. Medir y calibrar tuberías y herramientas | F15: =IF(C15="","",HYPERLINK("#'2026'!"&G15,"Ir a la actividad"&H15)) -> Ir a la actividadWell Logging - Ensamblar y conectar equipos, herramientas y registros al vástago del taladro o cables para conducir las pruebas y ensayos requeridos. Medir y calibrar tuberías y herramientas | G15: {=ADDRESS(MATCH($H15,'año26'!F:F,0),COLUMN('año26'!F:F))} -> $F$93 | H15: Well Logging - Ensamblar y conectar equipos, herramientas y registros al vástago del taladro o cables para conducir las pruebas y ensayos requeridos. Medir y calibrar tuberías y herramientas
C16: =IF(H17="",IF(H16="","",C15+1),IF(H16="","",C15+1)) -> 8 | D16: EXPLORACIÓN | E16: =IF(H16="","",H16) -> Mud Logging - Monitoreo de parámetros | F16: =IF(C16="","",HYPERLINK("#'2026'!"&G16,"Ir a la actividad"&H16)) -> Ir a la actividadMud Logging - Monitoreo de parámetros | G16: {=ADDRESS(MATCH($H16,'año26'!F:F,0),COLUMN('año26'!F:F))} -> $F$102 | H16: Mud Logging - Monitoreo de parámetros
C17: =IF(H18="",IF(H17="","",C16+1),IF(H17="","",C16+1)) -> 9 | D17: EXPLORACIÓN | E17: =IF(H17="","",H17) -> REGISTROS - ACTIVIDADES ADMINISTRATIVAS - Revisión y análisis de Informes | F17: =IF(C17="","",HYPERLINK("#'2026'!"&G17,"Ir a la actividad"&H17)) -> Ir a la actividadREGISTROS - ACTIVIDADES ADMINISTRATIVAS - Revisión y análisis de Informes | G17: {=ADDRESS(MATCH($H17,'año26'!F:F,0),COLUMN('año26'!F:F))} -> $F$124 | H17: REGISTROS - ACTIVIDADES ADMINISTRATIVAS - Revisión y análisis de Informes
C18: =IF(H19="",IF(H18="","",C17+1),IF(H18="","",C17+1)) -> 10 | D18: EXPLORACIÓN | E18: =IF(H18="","",H18) -> Todas las tareas del proceso productivo | F18: =IF(C18="","",HYPERLINK("#'2026'!"&G18,"Ir a la actividad"&H18)) -> Ir a la actividadTodas las tareas del proceso productivo | G18: {=ADDRESS(MATCH($H18,'año26'!F:F,0),COLUMN('año26'!F:F))} -> $F$136 | H18: Todas las tareas del proceso productivo
C19: =IF(H20="",IF(H19="","",C18+1),IF(H19="","",C18+1)) | D19: EXPLORACIÓN | E19: =IF(H19="","",H19) | F19: =IF(C19="","",HYPERLINK("#'2026'!"&G19,"Ir a la actividad"&H19)) | G19: {=ADDRESS(MATCH($H19,'año26'!F:F,0),COLUMN('año26'!F:F))} -> #N/A
C20: =IF(H21="",IF(H20="","",C19+1),IF(H20="","",C19+1)) | D20: EXPLORACIÓN | E20: =IF(H20="","",H20) | F20: =IF(C20="","",HYPERLINK("#'2026'!"&G20,"Ir a la actividad"&H20)) | G20: {=ADDRESS(MATCH($H20,'año26'!F:F,0),COLUMN('año26'!F:F))} -> #N/A
C21: =IF(H22="",IF(H21="","",C20+1),IF(H21="","",C20+1)) | D21: EXPLORACIÓN | E21: =IF(H21="","",H21) | F21: =IF(C21="","",HYPERLINK("#'2026'!"&G21,"Ir a la actividad"&H21)) | G21: {=ADDRESS(MATCH($H21,'año26'!F:F,0),COLUMN('año26'!F:F))} -> #N/A
C22: =IF(H23="",IF(H22="","",C21+1),IF(H22="","",C21+1)) | D22: EXPLORACIÓN | E22: =IF(H22="","",H22) | F22: =IF(C22="","",HYPERLINK("#'2026'!"&G22,"Ir a la actividad"&H22)) | G22: {=ADDRESS(MATCH($H22,'año26'!F:F,0),COLUMN('año26'!F:F))} -> #N/A
C23: =IF(H24="",IF(H23="","",C22+1),IF(H23="","",C22+1)) | D23: EXPLORACIÓN | E23: =IF(H23="","",H23) | F23: =IF(C23="","",HYPERLINK("#'2026'!"&G23,"Ir a la actividad"&H23)) | G23: {=ADDRESS(MATCH($H23,'año26'!F:F,0),COLUMN('año26'!F:F))} -> #N/A
C24: =IF(H25="",IF(H24="","",C23+1),IF(H24="","",C23+1)) | D24: EXPLORACIÓN | E24: =IF(H24="","",H24) | F24: =IF(C24="","",HYPERLINK("#'2026'!"&G24,"Ir a la actividad"&H24)) | G24: {=ADDRESS(MATCH($H24,'año26'!F:F,0),COLUMN('año26'!F:F))} -> #N/A
C25: =IF(H26="",IF(H25="","",C24+1),IF(H25="","",C24+1)) | D25: EXPLORACIÓN | E25: =IF(H25="","",H25) | F25: =IF(C25="","",HYPERLINK("#'2026'!"&G25,"Ir a la actividad"&H25)) | G25: {=ADDRESS(MATCH($H25,'año26'!F:F,0),COLUMN('año26'!F:F))} -> #N/A
C26: =IF(H27="",IF(H26="","",C25+1),IF(H26="","",C25+1)) | D26: EXPLORACIÓN | E26: =IF(H26="","",H26) | F26: =IF(C26="","",HYPERLINK("#'2026'!"&G26,"Ir a la actividad"&H26)) | G26: {=ADDRESS(MATCH($H26,'año26'!F:F,0),COLUMN('año26'!F:F))} -> #N/A
C27: =IF(H28="",IF(H27="","",C26+1),IF(H27="","",C26+1)) | D27: EXPLORACIÓN | E27: =IF(H27="","",H27) | F27: =IF(C27="","",HYPERLINK("#'2026'!"&G27,"Ir a la actividad"&H27)) | G27: {=ADDRESS(MATCH($H27,'año26'!F:F,0),COLUMN('año26'!F:F))} -> #N/A
C28: =IF(H29="",IF(H28="","",C27+1),IF(H28="","",C27+1)) | E28: =IF(H28="","",H28) | F28: =IF(C28="","",HYPERLINK("#'2026'!"&G28,"Ir a la actividad"&H28)) | G28: {=ADDRESS(MATCH($H28,'año26'!F:F,0),COLUMN('año26'!F:F))} -> #N/A
C29: =IF(H30="",IF(H29="","",C28+1),IF(H29="","",C28+1)) | E29: =IF(H29="","",H29) | F29: =IF(C29="","",HYPERLINK("#'2026'!"&G29,"Ir a la actividad"&H29)) | G29: {=ADDRESS(MATCH($H29,'año26'!F:F,0),COLUMN('año26'!F:F))} -> #N/A
C30: =IF(H31="",IF(H30="","",C29+1),IF(H30="","",C29+1)) | E30: =IF(H30="","",H30) | F30: =IF(C30="","",HYPERLINK("#'2026'!"&G30,"Ir a la actividad"&H30)) | G30: {=ADDRESS(MATCH($H30,'año26'!F:F,0),COLUMN('año26'!F:F))} -> #N/A
C31: =IF(H32="",IF(H31="","",C30+1),IF(H31="","",C30+1)) | E31: =IF(H31="","",H31) | F31: =IF(C31="","",HYPERLINK("#'2026'!"&G31,"Ir a la actividad"&H31)) | G31: {=ADDRESS(MATCH($H31,'año26'!F:F,0),COLUMN('año26'!F:F))} -> #N/A
C32: =IF(H33="",IF(H32="","",C31+1),IF(H32="","",C31+1)) | E32: =IF(H32="","",H32) | F32: =IF(C32="","",HYPERLINK("#'2026'!"&G32,"Ir a la actividad"&H32)) | G32: {=ADDRESS(MATCH($H32,'año26'!F:F,0),COLUMN('año26'!F:F))} -> #N/A
C33: =IF(H34="",IF(H33="","",C32+1),IF(H33="","",C32+1)) | E33: =IF(H33="","",H33) | F33: =IF(C33="","",HYPERLINK("#'2026'!"&G33,"Ir a la actividad"&H33)) | G33: {=ADDRESS(MATCH($H33,'año26'!F:F,0),COLUMN('año26'!F:F))} -> #N/A
C34: =IF(H35="",IF(H34="","",C33+1),IF(H34="","",C33+1)) | E34: =IF(H34="","",H34) | F34: =IF(C34="","",HYPERLINK("#'2026'!"&G34,"Ir a la actividad"&H34)) | G34: {=ADDRESS(MATCH($H34,'año26'!F:F,0),COLUMN('año26'!F:F))} -> #N/A
C35: =IF(H36="",IF(H35="","",C34+1),IF(H35="","",C34+1)) | E35: =IF(H35="","",H35) | F35: =IF(C35="","",HYPERLINK("#'2026'!"&G35,"Ir a la actividad"&H35)) | G35: {=ADDRESS(MATCH($H35,'año26'!F:F,0),COLUMN('año26'!F:F))} -> #N/A
C36: =IF(H37="",IF(H36="","",C35+1),IF(H36="","",C35+1)) | E36: =IF(H36="","",H36) | F36: =IF(C36="","",HYPERLINK("#'2026'!"&G36,"Ir a la actividad"&H36)) | G36: {=ADDRESS(MATCH($H36,'año26'!F:F,0),COLUMN('año26'!F:F))} -> #N/A
C37: =IF(H38="",IF(H37="","",C36+1),IF(H37="","",C36+1)) | E37: =IF(H37="","",H37) | F37: =IF(C37="","",HYPERLINK("#'2026'!"&G37,"Ir a la actividad"&H37)) | G37: {=ADDRESS(MATCH($H37,'año26'!F:F,0),COLUMN('año26'!F:F))} -> #N/A
C38: =IF(H39="",IF(H38="","",C37+1),IF(H38="","",C37+1)) | E38: =IF(H38="","",H38) | F38: =IF(C38="","",HYPERLINK("#'2026'!"&G38,"Ir a la actividad"&H38)) | G38: {=ADDRESS(MATCH($H38,'año26'!F:F,0),COLUMN('año26'!F:F))} -> #N/A
C39: =IF(H40="",IF(H39="","",C38+1),IF(H39="","",C38+1)) | E39: =IF(H39="","",H39) | F39: =IF(C39="","",HYPERLINK("#'2026'!"&G39,"Ir a la actividad"&H39)) | G39: {=ADDRESS(MATCH($H39,'año26'!F:F,0),COLUMN('año26'!F:F))} -> #N/A
... C196: =IF(H197="",IF(H196="","",C195+1),IF(H196="","",C195+1)) | E196: =IF(H196="","",H196) | F196: =IF(C196="","",HYPERLINK("#'2026'!"&G196,"Ir a la actividad"&H196)) | G196: {=ADDRESS(MATCH($H196,'año26'!F:F,0),COLUMN('año26'!F:F))} -> #N/A

Sheet 2024
H2: MATRIZ DE IDENTIFICACIÓN DE PELIGROS Y VALORACIÓN DE RIESGOS Y DETERMINACIÓN DE CONTROLES | AH2: CODIGO COL-HSEQ-FT-210 EMISIÓN 13-07-2015 VIGENCIA 31-05-2018 VERSIÓN 4 PÁGINA 1 de 1 | AW2: Factor de riesgo | AY2: Biológico | AZ2: Físico | BA2: Químico | BB2: Psicosocial | BC2: Biomecánicos | BD2: Condiciones de seguridad | BE2: Fenómenos naturales
B3: Proceso Evaluado: | F3: Perforación | AH3: EXTREMO | AI3: Vice-Presidentes y/o COO | AP3: Bajo | AQ3: CONSECUENCIA | AR3: 4 Crítico | AS3: 4 | AT3: 8 | AU3: 12 | AV3: 16
B4: Categoría del Riesgo: | F4: Personas, Medio ambiente, Activos y Activos & Riesgo Financiero | AH4: ALTO | AI4: Gerente de Departamento | AP4: Medio | AR4: 3 Serio | AS4: 3 | AT4: 6 | AU4: 9 | AV4: 12
B5: Alcance de la evaluación: | F5: Actualización matriz de Identificación de peligros, valoración de riesgos y determinacion de controles para las actividades de Perforación | AH5: MEDIO | AI5: Superintendente, Líder de operaciones, Etc. | AP5: Alto | AR5: 2 Moderado | AS5: 2 | AT5: 4 | AU5: 6 | AV5: 8
B6: Responsable de Actualización: | F6: Rafael Bermeo / Sebastian Moyano ( Ing Operaciones) / Nidia López Ospina (Gestiones integrales HSEQ) / Henry Tocaruncho (Gerente HS) | AH6: BAJO | AI6: Autoridad de área | AP6: Extremo | AR6: 1 Menor | AS6: 1 | AT6: 2 | AU6: 3 | AV6: 4
B7: Fecha de Actualización (DD/MM/AAAA): | F7: 29/05/2021; 15/06/2022; 26/06/2023, 26/06/2024 | AS7: 1 Remoto | AT7: 2 Improbable | AU7: 3 Probable | AV7: 4 Frecuente
AS8: PROBABILIDAD
B9: No. | C9: AÑO | D9: Estación | E9: Actividad | F9: Tárea | G9: Área / Equipo | H9: PELIGRO - Descripción | I9: PELIGRO -Tipo | J9: PELIGRO -Iconografia | K9: PELIGRO - Clasificación | L9: Consecuencias (AT/EL) | M9: TAREA - Rutinaria | N9: TAREA (Interna - ERutinariaterna) | O9: Numero de personas expuestas - Directos | P9: Numero de personas expuestas - Contratistas | Q9: Numero de personas expuestas - Visitantes, Clientes, autoridades | R9: Horas de exposición (En relación con las 24 horas al día) | S9: CARGOS O PARTES INTERESADAS APLICABLES | T9: CONTROLES EXISTENTES - Fuente | U9: CONTROLES EXISTENTES - Medio | V9: CONTROLES EXISTENTES - Individuo | W9: VALORACION DE RIESGO - C | X9: VALORACION DE RIESGO - Categoría | Y9: VALORACION DE RIESGO -p | Z9: Nivel de riesgo | AA9: ERutinariaistencia de requisitos legales | AB9: CONTROLES (TRATAMIENTO DEL RIESGO Y PLANES ATENUANTES) - ELIMINACIÓN | AC9: CONTROLES (TRATAMIENTO DEL RIESGO Y PLANES ATENUANTES) - SUSTITUCIÓN | AD9: CONTROLES (TRATAMIENTO DEL RIESGO Y PLANES ATENUANTES) - CONTROLES DE INGENIERIA | AE9: CONTROLES (TRATAMIENTO DEL RIESGO Y PLANES ATENUANTES) - CONTROLES ADMINISTRATIVOS / SEÑALIZACIÓN | AF9: CONTROLES (TRATAMIENTO DEL RIESGO Y PLANES ATENUANTES) - ELEMENTOS DE PROTECCIÓN PERSONAL | AG9: Compilado de controles | AH9: RESPONSABLE DE EJECUTAR LA ACCION | AI9: VALORACION DEL RIESGO RESULTANTE CON CONTROLES (Riesgo residual) - C | AJ9: VALORACION DEL RIESGO RESULTANTE CON CONTROLES (Riesgo residual) - Categoría | AK9: VALORACION DEL RIESGO RESULTANTE CON CONTROLES (Riesgo residual) - p | AL9: VALORACION DEL RIESGO RESULTANTE CON CONTROLES (Riesgo residual) - Nivel de riesgo | AM9: VALORACION DEL RIESGO RESULTANTE CON CONTROLES (Riesgo residual) - INTERPRETACIÓN DEL RIESGO | AN9: EFICACIA DE LAS MEDIDAS DE CONTROL Registro de accidentes, casi accidentes o enfermedades generados en el periodo evaluado. | AO9: Eficaz | AP9: Comprensión Riesgo | AQ9: Nivel del Riesgo
B10: 1 | C10: 2024 | D10: Campos Parex | E10: MOVILIZACIÓN Y DESMOVILIZACIÓN | F10: Inspección de vía y nueva locación: Recorridos a pie / Supervisión en campo/ inspecciones/ Interaccion con la comunidad / Desplazamiento en vehículos | G10: Ruta de Movilización y Nueva locación | H10: Atropellos o golpes con vehículos | I10: Condiciones_de_seguridad | J10: =_xlfn.XLOOKUP(año24[[#This Row],[PELIGRO -Tipo]], Tabla12[Calsificación], Tabla12[Imagen]) -> #VALUE! | K10: 6.5 Accidentes de transito | L10: AT | M10: Rutinaria | N10: Interna | O10: 2 | P10: 4 | Q10: 2 | R10: 8 | S10: Contratistas | T10: Sistemas de seguridad del Vehículo (cinturón de seguridad, airbags, apoya cabezas, llantas) Sistema de monitoreo de velocidad acorde a la legislación | U10: Inspecciones de seguridad Plan de movilizaciones Señalización Controlador vial | V10: * Plan estratégico de seguridad via-PEVS * Control de contratistas de servicios de transporte * Anexo HSEQ para contratistas * Plan de Emergencias | W10: 3 Serio | X10: Personas | Y10: 3 Probable | Z10: =INDEX($AS$3:$AV$6,MATCH($W10,$AR$3:$AR$6,FALSE),MATCH($Y10,AS$7:$AV$7,FALSE)) -> 9 | AA10: Si (Ver matriz de requisitos legales) | AB10: Ninguna | AC10: Ninguna | AD10: Sistemas de seguridad del Vehículo (cinturón de seguridad, airbags, apoya cabezas, llantas) | AE10: Continuar con los controles implemetados: *Seguimiento cumplimiento del PESV * Evaluación de desempeño de cotratistas | AF10: Ver matriz de EPP | AG10: ="Eliminación del riesgo:"&año24[[#This Row],[CONTROLES (TRATAMIENTO DEL RIESGO Y PLANES ATENUANTES) - ELIMINACIÓN]]&"Sustitución del riesgo; "&año24[[#This Row],[CONTROLES (TRATAMIENTO DEL RIESGO Y PLANES ATENUANTES) - SUSTITUCIÓN]]&"Controles de Ingenieria; "&año24[[#This Row],[CONTROLES (TRATAMIENTO DEL RIESGO Y PLANES ATENUANTES) - CONTROLES DE INGENIERIA]]&" Controles administrativos; "&año24[[#This Row],[CONTROLES (TRATAMIENTO DEL RIESGO Y PLANES ATENUANTES) - CONTROLES ADMINISTRATIVOS / SEÑALIZACIÓN]]&"Controles de EPP; "&año24[[#This Row],[CONTROLES (TRATAMIENTO DEL RIESGO Y PLANES ATENUANTES) - ELEMENTOS DE PROTECCIÓN PERSONAL]] -> Eliminación del riesgo:NingunaSustitución del riesgo; NingunaControles de Ingenieria; Sistemas de seguridad del Vehículo (cinturón de seguridad, airbags, apoya cabezas, llantas) Controles administrativos; Continuar con los controles implemetados: *Seguimiento cumplimiento del PESV * Evaluación de desempeño de cotratistas Controles de EPP; Ver matriz de EPP | AH10: HS Parex Contratista | AI10: 2 Moderado | AJ10: Personas | AK10: 2 Improbable | AL10: =INDEX($AS$3:$AV$6,MATCH($AI10,$AR$3:$AR$6,FALSE),MATCH($AK10,$AS$7:$AV$7,FALSE)) -> 4 | AM10: =IF(año24[[#This Row],[VALORACION DEL RIESGO RESULTANTE CON CONTROLES (Riesgo residual) - Nivel de riesgo]]<=3,"Bajo",IF(año24[[#This Row],[VALORACION DEL RIESGO RESULTANTE CON CONTROLES (Riesgo residual) - Nivel de riesgo]]<=6,"Medio",IF(año24[[#This Row],[VALORACION DEL RIESGO RESULTANTE CON CONTROLES (Riesgo residual) - Nivel de riesgo]]<=12,"Alto","Extremo"))) -> Medio | AO10: =IF(AL10<=4,"SI",IF(AL10>=5,"NO")) -> SI | AP10: ="El nivel del riesgo es"&" "&año24[[#This Row],[VALORACION DEL RIESGO RESULTANTE CON CONTROLES (Riesgo residual) - INTERPRETACIÓN DEL RIESGO]]&" siendo las principales consecuencias las siguientes; "&año24[[#This Row],[Consecuencias (AT/EL)]] -> El nivel del riesgo es Medio siendo las principales consecuencias las siguientes; AT | AQ10: =_xlfn.XLOOKUP(año24[[#This Row],[VALORACION DEL RIESGO RESULTANTE CON CONTROLES (Riesgo residual) - INTERPRETACIÓN DEL RIESGO]], Nivel[Calsificación], Nivel[Imagen]) -> #VALUE!
B11: 2 | C11: 2024 | D11: Campos Parex | E11: MOVILIZACIÓN Y DESMOVILIZACIÓN | F11: Inspección de vía y nueva locación: Recorridos a pie / Supervisión en campo/ inspecciones/ Interaccion con la comunidad / Desplazamiento en vehículos | G11: Ruta de Movilización y Nueva locación | H11: Lluvias, tormentas eléctricas | I11: Fenómenos_naturales | J11: =_xlfn.XLOOKUP(año24[[#This Row],[PELIGRO -Tipo]], Tabla12[Calsificación], Tabla12[Imagen]) -> #VALUE! | K11: 7.6 Precipitaciones | L11: AT | M11: Rutinaria | N11: Externa | O11: 2 | P11: 4 | Q11: 2 | R11: 1 | S11: Contratistas | T11: Ninguna | U11: Señalización Layout de la locación Sistema de alarma Detector de tormentas Pararrayos Brigada de emergencias | V11: Uso de EPP (Dotación de invierno) Charlas Informativas | W11: 3 Serio | X11: Personas | Y11: 2 Improbable | Z11: =INDEX($AS$3:$AV$6,MATCH($W11,$AR$3:$AR$6,FALSE),MATCH($Y11,AS$7:$AV$7,FALSE)) -> 6 | AA11: Si (Ver matriz de requisitos legales) | AB11: Ninguna | AC11: Ninguna | AD11: Puesta a tierra de equipos en la locación | AE11: Continuar con los controles implemetados: * Plan de emergencias *Unidad de Respuesta a Emergencias (URE) | AF11: Ver matriz de EPP | AG11: ="Eliminación del riesgo:"&año24[[#This Row],[CONTROLES (TRATAMIENTO DEL RIESGO Y PLANES ATENUANTES) - ELIMINACIÓN]]&"Sustitución del riesgo; "&año24[[#This Row],[CONTROLES (TRATAMIENTO DEL RIESGO Y PLANES ATENUANTES) - SUSTITUCIÓN]]&"Controles de Ingenieria; "&año24[[#This Row],[CONTROLES (TRATAMIENTO DEL RIESGO Y PLANES ATENUANTES) - CONTROLES DE INGENIERIA]]&" Controles administrativos; "&año24[[#This Row],[CONTROLES (TRATAMIENTO DEL RIESGO Y PLANES ATENUANTES) - CONTROLES ADMINISTRATIVOS / SEÑALIZACIÓN]]&"Controles de EPP; "&año24[[#This Row],[CONTROLES (TRATAMIENTO DEL RIESGO Y PLANES ATENUANTES) - ELEMENTOS DE PROTECCIÓN PERSONAL]] -> Eliminación del riesgo:NingunaSustitución del riesgo; NingunaControles de Ingenieria; Puesta a tierra de equipos en la locación Controles administrativos; Continuar con los controles implemetados: * Plan de emergencias *Unidad de Respuesta a Emergencias (URE)Controles de EPP; Ver matriz de EPP | AH11: HS Parex Contratista | AI11: 3 Serio | AJ11: Personas | AK11: 1 Remoto | AL11: =INDEX($AS$3:$AV$6,MATCH($AI11,$AR$3:$AR$6,FALSE),MATCH($AK11,$AS$7:$AV$7,FALSE)) -> 3 | AM11: =IF(año24[[#This Row],[VALORACION DEL RIESGO RESULTANTE CON CONTROLES (Riesgo residual) - Nivel de riesgo]]<=3,"Bajo",IF(año24[[#This Row],[VALORACION DEL RIESGO RESULTANTE CON CONTROLES (Riesgo residual) - Nivel de riesgo]]<=6,"Medio",IF(año24[[#This Row],[VALORACION DEL RIESGO RESULTANTE CON CONTROLES (Riesgo residual) - Nivel de riesgo]]<=12,"Alto","Extremo"))) -> Bajo | AO11: =IF(AL11<=4,"SI",IF(AL11>=5,"NO")) -> SI | AP11: ="El nivel del riesgo es"&" "&año24[[#This Row],[VALORACION DEL RIESGO RESULTANTE CON CONTROLES (Riesgo residual) - INTERPRETACIÓN DEL RIESGO]]&" siendo las principales consecuencias las siguientes; "&año24[[#This Row],[Consecuencias (AT/EL)]] -> El nivel del riesgo es Bajo siendo las principales consecuencias las siguientes; AT | AQ11: =_xlfn.XLOOKUP(año24[[#This Row],[VALORACION DEL RIESGO RESULTANTE CON CONTROLES (Riesgo residual) - INTERPRETACIÓN DEL RIESGO]], Nivel[Calsificación], Nivel[Imagen]) -> #VALUE!
B12: 3 | C12: 2024 | D12: Campos Parex | E12: MOVILIZACIÓN Y DESMOVILIZACIÓN | F12: Inspección de vía y nueva locación: Recorridos a pie / Supervisión en campo/ inspecciones/ Interaccion con la comunidad / Desplazamiento en vehículos | G12: Ruta de Movilización y Nueva locación | H12: Características del grupo social de trabajo (Relaciones, cohesión, calidad de interacciones, trabajo en equipo) Jornadas de trabajo (pausas, trabajo nocturno, rotación, horas extras, descanso) | I12: Psicosocial | J12: =_xlfn.XLOOKUP(año24[[#This Row],[PELIGRO -Tipo]], Tabla12[Calsificación], Tabla12[Imagen]) -> #VALUE! | K12: 4.4 Características del grupo social de trabajo | L12: EL | M12: Rutinaria | N12: Interna | O12: 2 | P12: 4 | Q12: 2 | R12: 8 | S12: Contratistas | T12: Organización del trabajo Definición de manuales de funciones y cargos | U12: Política de prevención de acoso laboral Comité de convivencia laboral | V12: *Aplicación de baterías de riesgo psicosocial * Capacitación en riesgo psicosocial * PVE de Riesgo Psicosocial | W12: 2 Moderado | X12: Personas | Y12: 2 Improbable | Z12: =INDEX($AS$3:$AV$6,MATCH($W12,$AR$3:$AR$6,FALSE),MATCH($Y12,AS$7:$AV$7,FALSE)) -> 4 | AA12: Si (Ver matriz de requisitos legales) | AB12: Ninguna | AC12: Ninguna | AD12: Ninguna | AE12: Continuidad en la aplicación de los controles: * Seguimiento a los planes de intervención del PVE de riesgo psicosocial * Pausas activas | AF12: Ninguna | AG12: ="Eliminación del riesgo:"&año24[[#This Row],[CONTROLES (TRATAMIENTO DEL RIESGO Y PLANES ATENUANTES) - ELIMINACIÓN]]&"Sustitución del riesgo; "&año24[[#This Row],[CONTROLES (TRATAMIENTO DEL RIESGO Y PLANES ATENUANTES) - SUSTITUCIÓN]]&"Controles de Ingenieria; "&año24[[#This Row],[CONTROLES (TRATAMIENTO DEL RIESGO Y PLANES ATENUANTES) - CONTROLES DE INGENIERIA]]&" Controles administrativos; "&año24[[#This Row],[CONTROLES (TRATAMIENTO DEL RIESGO Y PLANES ATENUANTES) - CONTROLES ADMINISTRATIVOS / SEÑALIZACIÓN]]&"Controles de EPP; "&año24[[#This Row],[CONTROLES (TRATAMIENTO DEL RIESGO Y PLANES ATENUANTES) - ELEMENTOS DE PROTECCIÓN PERSONAL]] -> Eliminación del riesgo:NingunaSustitución del riesgo; NingunaControles de Ingenieria; Ninguna Controles administrativos; Continuidad en la aplicación de los controles: * Seguimiento a los planes de intervención del PVE de riesgo psicosocial * Pausas activas Controles de EPP; Ninguna | AH12: HS Parex Contratista | AI12: 1 Menor | AJ12: Personas | AK12: 2 Improbable | AL12: =INDEX($AS$3:$AV$6,MATCH($AI12,$AR$3:$AR$6,FALSE),MATCH($AK12,$AS$7:$AV$7,FALSE)) -> 2 | AM12: =IF(año24[[#This Row],[VALORACION DEL RIESGO RESULTANTE CON CONTROLES (Riesgo residual) - Nivel de riesgo]]<=3,"Bajo",IF(año24[[#This Row],[VALORACION DEL RIESGO RESULTANTE CON CONTROLES (Riesgo residual) - Nivel de riesgo]]<=6,"Medio",IF(año24[[#This Row],[VALORACION DEL RIESGO RESULTANTE CON CONTROLES (Riesgo residual) - Nivel de riesgo]]<=12,"Alto","Extremo"))) -> Bajo | AO12: =IF(AL12<=4,"SI",IF(AL12>=5,"NO")) -> SI | AP12: ="El nivel del riesgo es"&" "&año24[[#This Row],[VALORACION DEL RIESGO RESULTANTE CON CONTROLES (Riesgo residual) - INTERPRETACIÓN DEL RIESGO]]&" siendo las principales consecuencias las siguientes; "&año24[[#This Row],[Consecuencias (AT/EL)]] -> El nivel del riesgo es Bajo siendo las principales consecuencias las siguientes; EL | AQ12: =_xlfn.XLOOKUP(año24[[#This Row],[VALORACION DEL RIESGO RESULTANTE CON CONTROLES (Riesgo residual) - INTERPRETACIÓN DEL RIESGO]], Nivel[Calsificación], Nivel[Imagen]) -> #VALUE!
B13: 4 | C13: 2024 | D13: Campos Parex | E13: MOVILIZACIÓN Y DESMOVILIZACIÓN | F13: Inspección de vía y nueva locación: Recorridos a pie / Supervisión en campo/ inspecciones/ Interaccion con la comunidad / Desplazamiento en vehículos | G13: Ruta de Movilización y Nueva locación | H13: Condiciones de la tarea (carga mental, demandas emocionales, sistemas de control, etc.) | I13: Psicosocial | J13: =_xlfn.XLOOKUP(año24[[#This Row],[PELIGRO -Tipo]], Tabla12[Calsificación], Tabla12[Imagen]) -> #VALUE! | K13: 4.3 Condiciones de la tarea | L13: EL | M13: Rutinaria | N13: Interna | O13: 2 | P13: 4 | Q13: 2 | R13: 8 | S13: Contratistas | T13: Organización del trabajo Definición de manuales de funciones y cargos | U13: Política de prevención de acoso laboral Comité de convivencia laboral | V13: *Aplicación de baterías de riesgo psicosocial * Capacitación en riesgo psicosocial * PVE de Riesgo Psicosocial | W13: 2 Moderado | X13: Personas | Y13: 2 Improbable | Z13: =INDEX($AS$3:$AV$6,MATCH($W13,$AR$3:$AR$6,FALSE),MATCH($Y13,AS$7:$AV$7,FALSE)) -> 4 | AA13: Si (Ver matriz de requisitos legales) | AB13: Ninguna | AC13: Ninguna | AD13: Ninguna | AE13: Continuidad en la aplicación de los controles: * Seguimiento a los planes de intervención del PVE de riesgo psicosocial * Pausas activas | AF13: Ninguna | AG13: ="Eliminación del riesgo:"&año24[[#This Row],[CONTROLES (TRATAMIENTO DEL RIESGO Y PLANES ATENUANTES) - ELIMINACIÓN]]&"Sustitución del riesgo; "&año24[[#This Row],[CONTROLES (TRATAMIENTO DEL RIESGO Y PLANES ATENUANTES) - SUSTITUCIÓN]]&"Controles de Ingenieria; "&año24[[#This Row],[CONTROLES (TRATAMIENTO DEL RIESGO Y PLANES ATENUANTES) - CONTROLES DE INGENIERIA]]&" Controles administrativos; "&año24[[#This Row],[CONTROLES (TRATAMIENTO DEL RIESGO Y PLANES ATENUANTES) - CONTROLES ADMINISTRATIVOS / SEÑALIZACIÓN]]&"Controles de EPP; "&año24[[#This Row],[CONTROLES (TRATAMIENTO DEL RIESGO Y PLANES ATENUANTES) - ELEMENTOS DE PROTECCIÓN PERSONAL]] -> Eliminación del riesgo:NingunaSustitución del riesgo; NingunaControles de Ingenieria; Ninguna Controles administrativos; Continuidad en la aplicación de los controles: * Seguimiento a los planes de intervención del PVE de riesgo psicosocial * Pausas activas Controles de EPP; Ninguna | AH13: HS Parex Contratista | AI13: 1 Menor | AJ13: Personas | AK13: 2 Improbable | AL13: =INDEX($AS$3:$AV$6,MATCH($AI13,$AR$3:$AR$6,FALSE),MATCH($AK13,$AS$7:$AV$7,FALSE)) -> 2 | AM13: =IF(año24[[#This Row],[VALORACION DEL RIESGO RESULTANTE CON CONTROLES (Riesgo residual) - Nivel de riesgo]]<=3,"Bajo",IF(año24[[#This Row],[VALORACION DEL RIESGO RESULTANTE CON CONTROLES (Riesgo residual) - Nivel de riesgo]]<=6,"Medio",IF(año24[[#This Row],[VALORACION DEL RIESGO RESULTANTE CON CONTROLES (Riesgo residual) - Nivel de riesgo]]<=12,"Alto","Extremo"))) -> Bajo | AO13: =IF(AL13<=4,"SI",IF(AL13>=5,"NO")) -> SI | AP13: ="El nivel del riesgo es"&" "&año24[[#This Row],[VALORACION DEL RIESGO RESULTANTE CON CONTROLES (Riesgo residual) - INTERPRETACIÓN DEL RIESGO]]&" siendo las principales consecuencias las siguientes; "&año24[[#This Row],[Consecuencias (AT/EL)]] -> El nivel del riesgo es Bajo siendo las principales consecuencias las siguientes; EL | AQ13: =_xlfn.XLOOKUP(año24[[#This Row],[VALORACION DEL RIESGO RESULTANTE CON CONTROLES (Riesgo residual) - INTERPRETACIÓN DEL RIESGO]], Nivel[Calsificación], Nivel[Imagen]) -> #VALUE!
B14: 5 | C14: 2024 | D14: Campos Parex | E14: MOVILIZACIÓN Y DESMOVILIZACIÓN | F14: Inspección de vía y nueva locación: Recorridos a pie / Supervisión en campo/ inspecciones/ Interaccion con la comunidad / Desplazamiento en vehículos | G14: Ruta de Movilización y Nueva locación | H14: Almacenamiento, manipulación y contacto con sustancias químicas para limpieza y desinfección de superficies | I14: Químico | J14: =_xlfn.XLOOKUP(año24[[#This Row],[PELIGRO -Tipo]], Tabla12[Calsificación], Tabla12[Imagen]) -> #VALUE! | K14: 3.4 Líquidos, rocíos | L14: AT/EL | M14: Rutinaria | N14: Interna | O14: 2 | P14: 4 | Q14: 2 | R14: 8 | S14: Contratistas | T14: Identificación de peligrosidad con Sistema Globalmente armonizado | U14: Programa de Higiene Ocupacional (Mediciones de higiene según cronoggrama) | V14: Programa de gestión de riesgo químico EPP Exámenes médicos ocupacionales Capacitación en riesgo químico | W14: 2 Moderado | X14: Personas | Y14: 3 Probable | Z14: =INDEX($AS$3:$AV$6,MATCH($W14,$AR$3:$AR$6,FALSE),MATCH($Y14,AS$7:$AV$7,FALSE)) -> 6 | AA14: Si (Ver matriz de requisitos legales) | AB14: Ninguna | AC14: Ninguna | AD14: Ninguna | AE14: Continuidad a los controles implementados: Seguimiento al programa de gestión del riesgo químico Programa de Seguridad Basada en el Comportamiento | AF14: Ver matriz de EPP | AG14: ="Eliminación del riesgo:"&año24[[#This Row],[CONTROLES (TRATAMIENTO DEL RIESGO Y PLANES ATENUANTES) - ELIMINACIÓN]]&"Sustitución del riesgo; "&año24[[#This Row],[CONTROLES (TRATAMIENTO DEL RIESGO Y PLANES ATENUANTES) - SUSTITUCIÓN]]&"Controles de Ingenieria; "&año24[[#This Row],[CONTROLES (TRATAMIENTO DEL RIESGO Y PLANES ATENUANTES) - CONTROLES DE INGENIERIA]]&" Controles administrativos; "&año24[[#This Row],[CONTROLES (TRATAMIENTO DEL RIESGO Y PLANES ATENUANTES) - CONTROLES ADMINISTRATIVOS / SEÑALIZACIÓN]]&"Controles de EPP; "&año24[[#This Row],[CONTROLES (TRATAMIENTO DEL RIESGO Y PLANES ATENUANTES) - ELEMENTOS DE PROTECCIÓN PERSONAL]] -> Eliminación del riesgo:NingunaSustitución del riesgo; NingunaControles de Ingenieria; Ninguna Controles administrativos; Continuidad a los controles implementados: Seguimiento al programa de gestión del riesgo químico Programa de Seguridad Basada en el ComportamientoControles de EPP; Ver matriz de EPP | AH14: HS Parex Contratista | AI14: 2 Moderado | AJ14: Personas | AK14: 2 Improbable | AL14: =INDEX($AS$3:$AV$6,MATCH($AI14,$AR$3:$AR$6,FALSE),MATCH($AK14,$AS$7:$AV$7,FALSE)) -> 4 | AM14: =IF(año24[[#This Row],[VALORACION DEL RIESGO RESULTANTE CON CONTROLES (Riesgo residual) - Nivel de riesgo]]<=3,"Bajo",IF(año24[[#This Row],[VALORACION DEL RIESGO RESULTANTE CON CONTROLES (Riesgo residual) - Nivel de riesgo]]<=6,"Medio",IF(año24[[#This Row],[VALORACION DEL RIESGO RESULTANTE CON CONTROLES (Riesgo residual) - Nivel de riesgo]]<=12,"Alto","Extremo"))) -> Medio | AO14: =IF(AL14<=4,"SI",IF(AL14>=5,"NO")) -> SI | AP14: ="El nivel del riesgo es"&" "&año24[[#This Row],[VALORACION DEL RIESGO RESULTANTE CON CONTROLES (Riesgo residual) - INTERPRETACIÓN DEL RIESGO]]&" siendo las principales consecuencias las siguientes; "&año24[[#This Row],[Consecuencias (AT/EL)]] -> El nivel del riesgo es Medio siendo las principales consecuencias las siguientes; AT/EL | AQ14: =_xlfn.XLOOKUP(año24[[#This Row],[VALORACION DEL RIESGO RESULTANTE CON CONTROLES (Riesgo residual) - INTERPRETACIÓN DEL RIESGO]], Nivel[Calsificación], Nivel[Imagen]) -> #VALUE!
B15: 6 | C15: 2024 | D15: Campos Parex | E15: MOVILIZACIÓN Y DESMOVILIZACIÓN | F15: Inspección de vía y nueva locación: Recorridos a pie / Supervisión en campo/ inspecciones/ Interaccion con la comunidad / Desplazamiento en vehículos | G15: Ruta de Movilización y Nueva locación | H15: Actos y comportamientos inseguros, por no cumplir políticas, estándares y procedimietos de trabajo | I15: Psicosocial | J15: =_xlfn.XLOOKUP(año24[[#This Row],[PELIGRO -Tipo]], Tabla12[Calsificación], Tabla12[Imagen]) -> #VALUE! | K15: 4.2 Características de la organización del trabajo | L15: EL | M15: Rutinaria | N15: Interna | O15: 2 | P15: 4 | Q15: 2 | R15: 8 | S15: Contratistas | T15: Organización del trabajo Definición de manuales de funciones y cargos | U15: Política de prevención de acoso laboral Comité de convivencia laboral | V15: *Aplicación de baterías de riesgo psicosocial * Capacitación en riesgo psicosocial * PVE de Riesgo Psicosocial | W15: 2 Moderado | X15: Personas | Y15: 2 Improbable | Z15: =INDEX($AS$3:$AV$6,MATCH($W15,$AR$3:$AR$6,FALSE),MATCH($Y15,AS$7:$AV$7,FALSE)) -> 4 | AA15: Si (Ver matriz de requisitos legales) | AB15: Ninguna | AC15: Ninguna | AD15: Ninguna | AE15: Continuidad en la aplicación de los controles: * Seguimiento a los planes de intervención del PVE de riesgo psicosocial * Pausas activas | AF15: Ninguna | AG15: ="Eliminación del riesgo:"&año24[[#This Row],[CONTROLES (TRATAMIENTO DEL RIESGO Y PLANES ATENUANTES) - ELIMINACIÓN]]&"Sustitución del riesgo; "&año24[[#This Row],[CONTROLES (TRATAMIENTO DEL RIESGO Y PLANES ATENUANTES) - SUSTITUCIÓN]]&"Controles de Ingenieria; "&año24[[#This Row],[CONTROLES (TRATAMIENTO DEL RIESGO Y PLANES ATENUANTES) - CONTROLES DE INGENIERIA]]&" Controles administrativos; "&año24[[#This Row],[CONTROLES (TRATAMIENTO DEL RIESGO Y PLANES ATENUANTES) - CONTROLES ADMINISTRATIVOS / SEÑALIZACIÓN]]&"Controles de EPP; "&año24[[#This Row],[CONTROLES (TRATAMIENTO DEL RIESGO Y PLANES ATENUANTES) - ELEMENTOS DE PROTECCIÓN PERSONAL]] -> Eliminación del riesgo:NingunaSustitución del riesgo; NingunaControles de Ingenieria; Ninguna Controles administrativos; Continuidad en la aplicación de los controles: * Seguimiento a los planes de intervención del PVE de riesgo psicosocial * Pausas activas Controles de EPP; Ninguna | AH15: HS Parex Contratista | AI15: 1 Menor | AJ15: Personas | AK15: 2 Improbable | AL15: =INDEX($AS$3:$AV$6,MATCH($AI15,$AR$3:$AR$6,FALSE),MATCH($AK15,$AS$7:$AV$7,FALSE)) -> 2 | AM15: =IF(año24[[#This Row],[VALORACION DEL RIESGO RESULTANTE CON CONTROLES (Riesgo residual) - Nivel de riesgo]]<=3,"Bajo",IF(año24[[#This Row],[VALORACION DEL RIESGO RESULTANTE CON CONTROLES (Riesgo residual) - Nivel de riesgo]]<=6,"Medio",IF(año24[[#This Row],[VALORACION DEL RIESGO RESULTANTE CON CONTROLES (Riesgo residual) - Nivel de riesgo]]<=12,"Alto","Extremo"))) -> Bajo | AO15: =IF(AL15<=4,"SI",IF(AL15>=5,"NO")) -> SI | AP15: ="El nivel del riesgo es"&" "&año24[[#This Row],[VALORACION DEL RIESGO RESULTANTE CON CONTROLES (Riesgo residual) - INTERPRETACIÓN DEL RIESGO]]&" siendo las principales consecuencias las siguientes; "&año24[[#This Row],[Consecuencias (AT/EL)]] -> El nivel del riesgo es Bajo siendo las principales consecuencias las siguientes; EL | AQ15: =_xlfn.XLOOKUP(año24[[#This Row],[VALORACION DEL RIESGO RESULTANTE CON CONTROLES (Riesgo residual) - INTERPRETACIÓN DEL RIESGO]], Nivel[Calsificación], Nivel[Imagen]) -> #VALUE!
B16: 7 | C16: 2024 | D16: Campos Parex | E16: MOVILIZACIÓN Y DESMOVILIZACIÓN | F16: Inspección de vía y nueva locación: Recorridos a pie / Supervisión en campo/ inspecciones/ Interaccion con la comunidad / Desplazamiento en vehículos | G16: Ruta de Movilización y Nueva locación | H16: Radiación no ionizante (Exposición a rayos solares) | I16: Físico | J16: =_xlfn.XLOOKUP(año24[[#This Row],[PELIGRO -Tipo]], Tabla12[Calsificación], Tabla12[Imagen]) -> #VALUE! | K16: 2.7 Radiaciones No ionizantes | L16: EL | M16: Rutinaria | N16: Interna | O16: 2 | P16: 4 | Q16: 2 | R16: 4 | S16: Contratistas | T16: Ninguna | U16: Ninguna | V16: Hidratación. Uso de bloqueador solar Examen Ocupacional con énfasis dermatológico | W16: 2 Moderado | X16: Personas | Y16: 3 Probable | Z16: =INDEX($AS$3:$AV$6,MATCH($W16,$AR$3:$AR$6,FALSE),MATCH($Y16,AS$7:$AV$7,FALSE)) -> 6 | AA16: Si (Ver matriz de requisitos legales) | AB16: Ninguna | AC16: Ninguna | AD16: Ninguna | AE16: Mantener controles existentes: Hidratación. Uso de bloqueador solar Examen Ocupacional con énfasis dermatológico Evitar la exposición directa a la luz solar dos horas antes y dos horas después del medio día. Capacitación en lesiones de piel | AF16: Ver matriz de EPP | AG16: ="Eliminación del riesgo:"&año24[[#This Row],[CONTROLES (TRATAMIENTO DEL RIESGO Y PLANES ATENUANTES) - ELIMINACIÓN]]&"Sustitución del riesgo; "&año24[[#This Row],[CONTROLES (TRATAMIENTO DEL RIESGO Y PLANES ATENUANTES) - SUSTITUCIÓN]]&"Controles de Ingenieria; "&año24[[#This Row],[CONTROLES (TRATAMIENTO DEL RIESGO Y PLANES ATENUANTES) - CONTROLES DE INGENIERIA]]&" Controles administrativos; "&año24[[#This Row],[CONTROLES (TRATAMIENTO DEL RIESGO Y PLANES ATENUANTES) - CONTROLES ADMINISTRATIVOS / SEÑALIZACIÓN]]&"Controles de EPP; "&año24[[#This Row],[CONTROLES (TRATAMIENTO DEL RIESGO Y PLANES ATENUANTES) - ELEMENTOS DE PROTECCIÓN PERSONAL]] -> Eliminación del riesgo:NingunaSustitución del riesgo; NingunaControles de Ingenieria; Ninguna Controles administrativos; Mantener controles existentes: Hidratación. Uso de bloqueador solar Examen Ocupacional con énfasis dermatológico Evitar la exposición directa a la luz solar dos horas antes y dos horas después del medio día. Capacitación en lesiones de piel Controles de EPP; Ver matriz de EPP | AH16: HS Parex Contratista | AI16: 2 Moderado | AJ16: Personas | AK16: 2 Improbable | AL16: =INDEX($AS$3:$AV$6,MATCH($AI16,$AR$3:$AR$6,FALSE),MATCH($AK16,$AS$7:$AV$7,FALSE)) -> 4 | AM16: =IF(año24[[#This Row],[VALORACION DEL RIESGO RESULTANTE CON CONTROLES (Riesgo residual) - Nivel de riesgo]]<=3,"Bajo",IF(año24[[#This Row],[VALORACION DEL RIESGO RESULTANTE CON CONTROLES (Riesgo residual) - Nivel de riesgo]]<=6,"Medio",IF(año24[[#This Row],[VALORACION DEL RIESGO RESULTANTE CON CONTROLES (Riesgo residual) - Nivel de riesgo]]<=12,"Alto","Extremo"))) -> Medio | AO16: =IF(AL16<=4,"SI",IF(AL16>=5,"NO")) -> SI | AP16: ="El nivel del riesgo es"&" "&año24[[#This Row],[VALORACION DEL RIESGO RESULTANTE CON CONTROLES (Riesgo residual) - INTERPRETACIÓN DEL RIESGO]]&" siendo las principales consecuencias las siguientes; "&año24[[#This Row],[Consecuencias (AT/EL)]] -> El nivel del riesgo es Medio siendo las principales consecuencias las siguientes; EL | AQ16: =_xlfn.XLOOKUP(año24[[#This Row],[VALORACION DEL RIESGO RESULTANTE CON CONTROLES (Riesgo residual) - INTERPRETACIÓN DEL RIESGO]], Nivel[Calsificación], Nivel[Imagen]) -> #VALUE!
B17: 8 | C17: 2024 | D17: Campos Parex | E17: MOVILIZACIÓN Y DESMOVILIZACIÓN | F17: Inspección de vía y nueva locación: Recorridos a pie / Supervisión en campo/ inspecciones/ Interaccion con la comunidad / Desplazamiento en vehículos | G17: Ruta de Movilización y Nueva locación | H17: Exposición a Virus, hongos, bacterias por la presencia de animales e insectos (picaduras, mordeduras) y por plantas (toxinas o alergias). | I17: Biológico | J17: =_xlfn.XLOOKUP(año24[[#This Row],[PELIGRO -Tipo]], Tabla12[Calsificación], Tabla12[Imagen]) -> #VALUE! | K17: 1.6 Picaduras | L17: AT | M17: Rutinaria | N17: Interna | O17: 2 | P17: 4 | Q17: 2 | R17: 8 | S17: Contratistas | T17: Ninguna | U17: Inspecciones de seguridad | V17: Esquema de vacunación completo (fiebre amarilla y tétano). Suero anti-ofídico Capacitación en Riesgo Biológico | W17: 2 Moderado | X17: Personas | Y17: 3 Probable | Z17: =INDEX($AS$3:$AV$6,MATCH($W17,$AR$3:$AR$6,FALSE),MATCH($Y17,AS$7:$AV$7,FALSE)) -> 6 | AA17: Si (Ver matriz de requisitos legales) | AB17: Ninguna | AC17: Ninguna | AD17: Ninguna | AE17: Actividades de promoción y prevención riesgos de Salud Pública (fiebre amarilla, dengue y tétano) Capacitar a los trabajadores en riesgo biológico (picaduras, clases de picaduras y tipo de animales que hay presentes en la zona). Campañas para la prevención de riesgos endémicos, socialización de SIVIGILA a la población trabajadora. Poda de la periferia de la locación Mantener controles existentes: Esquema de vacunación completo (fiebre amarilla y tétano). Suero anti-ofídico Capacitación en Riesgo Biológico * Programa de Gestión Seguridad Basada en el Comportamiento | AF17: Ver matriz de EPP | AG17: ="Eliminación del riesgo:"&año24[[#This Row],[CONTROLES (TRATAMIENTO DEL RIESGO Y PLANES ATENUANTES) - ELIMINACIÓN]]&"Sustitución del riesgo; "&año24[[#This Row],[CONTROLES (TRATAMIENTO DEL RIESGO Y PLANES ATENUANTES) - SUSTITUCIÓN]]&"Controles de Ingenieria; "&año24[[#This Row],[CONTROLES (TRATAMIENTO DEL RIESGO Y PLANES ATENUANTES) - CONTROLES DE INGENIERIA]]&" Controles administrativos; "&año24[[#This Row],[CONTROLES (TRATAMIENTO DEL RIESGO Y PLANES ATENUANTES) - CONTROLES ADMINISTRATIVOS / SEÑALIZACIÓN]]&"Controles de EPP; "&año24[[#This Row],[CONTROLES (TRATAMIENTO DEL RIESGO Y PLANES ATENUANTES) - ELEMENTOS DE PROTECCIÓN PERSONAL]] -> Eliminación del riesgo:NingunaSustitución del riesgo; NingunaControles de Ingenieria; Ninguna Controles administrativos; Actividades de promoción y prevención riesgos de Salud Pública (fiebre amarilla, dengue y tétano) Capacitar a los trabajadores en riesgo biológico (picaduras, clases de picaduras y tipo de animales que hay presentes en la zona). Campañas para la prevención de riesgos endémicos, socialización de SIVIGILA a la población trabajadora. Poda de la periferia de la locación Mantener controles existentes: Esquema de vacunación completo (fiebre amarilla y tétano). Suero anti-ofídico Capacitación en Riesgo Biológico * Programa de Gestión Seguridad Basada en el ComportamientoControles de EPP; Ver matriz de EPP | AH17: HS Parex Contratista | AI17: 2 Moderado | AJ17: Personas | AK17: 2 Improbable | AL17: =INDEX($AS$3:$AV$6,MATCH($AI17,$AR$3:$AR$6,FALSE),MATCH($AK17,$AS$7:$AV$7,FALSE)) -> 4 | AM17: =IF(año24[[#This Row],[VALORACION DEL RIESGO RESULTANTE CON CONTROLES (Riesgo residual) - Nivel de riesgo]]<=3,"Bajo",IF(año24[[#This Row],[VALORACION DEL RIESGO RESULTANTE CON CONTROLES (Riesgo residual) - Nivel de riesgo]]<=6,"Medio",IF(año24[[#This Row],[VALORACION DEL RIESGO RESULTANTE CON CONTROLES (Riesgo residual) - Nivel de riesgo]]<=12,"Alto","Extremo"))) -> Medio | AO17: =IF(AL17<=4,"SI",IF(AL17>=5,"NO")) -> SI | AP17: ="El nivel del riesgo es"&" "&año24[[#This Row],[VALORACION DEL RIESGO RESULTANTE CON CONTROLES (Riesgo residual) - INTERPRETACIÓN DEL RIESGO]]&" siendo las principales consecuencias las siguientes; "&año24[[#This Row],[Consecuencias (AT/EL)]] -> El nivel del riesgo es Medio siendo las principales consecuencias las siguientes; AT | AQ17: =_xlfn.XLOOKUP(año24[[#This Row],[VALORACION DEL RIESGO RESULTANTE CON CONTROLES (Riesgo residual) - INTERPRETACIÓN DEL RIESGO]], Nivel[Calsificación], Nivel[Imagen]) -> #VALUE!
B18: 9 | C18: 2024 | D18: Campos Parex | E18: MOVILIZACIÓN Y DESMOVILIZACIÓN | F18: Inspección de vía y nueva locación: Recorridos a pie / Supervisión en campo/ inspecciones/ Interaccion con la comunidad / Desplazamiento en vehículos | G18: Ruta de Movilización y Nueva locación | H18: Exposición a agentes biológicos por contacto, transmisión aérea o hídrica | I18: Biológico | J18: =_xlfn.XLOOKUP(año24[[#This Row],[PELIGRO -Tipo]], Tabla12[Calsificación], Tabla12[Imagen]) -> #VALUE! | K18: 1.1 Virus | L18: EL | M18: Rutinaria | N18: Interna | O18: 2 | P18: 4 | Q18: 2 | R18: 8 | S18: Contratistas | V18: EPP Vacunación Charlas de PYP | W18: 2 Moderado | X18: Personas | Y18: 3 Probable | Z18: =INDEX($AS$3:$AV$6,MATCH($W18,$AR$3:$AR$6,FALSE),MATCH($Y18,AS$7:$AV$7,FALSE)) -> 6 | AA18: Si (Ver matriz de requisitos legales) | AB18: Ninguna | AC18: Ninguna | AE18: Programa de capacitacion y entrenamiento Verificacion esquema de vacunacion Instructivo practica seguro en campo exposición a riesgo biológico COL-HSE-IN-018 | AF18: Ver matriz de EPP | AG18: ="Eliminación del riesgo:"&año24[[#This Row],[CONTROLES (TRATAMIENTO DEL RIESGO Y PLANES ATENUANTES) - ELIMINACIÓN]]&"Sustitución del riesgo; "&año24[[#This Row],[CONTROLES (TRATAMIENTO DEL RIESGO Y PLANES ATENUANTES) - SUSTITUCIÓN]]&"Controles de Ingenieria; "&año24[[#This Row],[CONTROLES (TRATAMIENTO DEL RIESGO Y PLANES ATENUANTES) - CONTROLES DE INGENIERIA]]&" Controles administrativos; "&año24[[#This Row],[CONTROLES (TRATAMIENTO DEL RIESGO Y PLANES ATENUANTES) - CONTROLES ADMINISTRATIVOS / SEÑALIZACIÓN]]&"Controles de EPP; "&año24[[#This Row],[CONTROLES (TRATAMIENTO DEL RIESGO Y PLANES ATENUANTES) - ELEMENTOS DE PROTECCIÓN PERSONAL]] -> Eliminación del riesgo:NingunaSustitución del riesgo; NingunaControles de Ingenieria; Controles administrativos; Programa de capacitacion y entrenamiento Verificacion esquema de vacunacion Instructivo practica seguro en campo exposición a riesgo biológico COL-HSE-IN-018Controles de EPP; Ver matriz de EPP | AH18: HS Parex Contratista | AI18: 2 Moderado | AJ18: Personas | AK18: 2 Improbable | AL18: =INDEX($AS$3:$AV$6,MATCH($AI18,$AR$3:$AR$6,FALSE),MATCH($AK18,$AS$7:$AV$7,FALSE)) -> 4 | AM18: =IF(año24[[#This Row],[VALORACION DEL RIESGO RESULTANTE CON CONTROLES (Riesgo residual) - Nivel de riesgo]]<=3,"Bajo",IF(año24[[#This Row],[VALORACION DEL RIESGO RESULTANTE CON CONTROLES (Riesgo residual) - Nivel de riesgo]]<=6,"Medio",IF(año24[[#This Row],[VALORACION DEL RIESGO RESULTANTE CON CONTROLES (Riesgo residual) - Nivel de riesgo]]<=12,"Alto","Extremo"))) -> Medio | AO18: =IF(AL18<=4,"SI",IF(AL18>=5,"NO")) -> SI | AP18: ="El nivel del riesgo es"&" "&año24[[#This Row],[VALORACION DEL RIESGO RESULTANTE CON CONTROLES (Riesgo residual) - INTERPRETACIÓN DEL RIESGO]]&" siendo las principales consecuencias las siguientes; "&año24[[#This Row],[Consecuencias (AT/EL)]] -> El nivel del riesgo es Medio siendo las principales consecuencias las siguientes; EL | AQ18: =_xlfn.XLOOKUP(año24[[#This Row],[VALORACION DEL RIESGO RESULTANTE CON CONTROLES (Riesgo residual) - INTERPRETACIÓN DEL RIESGO]], Nivel[Calsificación], Nivel[Imagen]) -> #VALUE!
B19: 10 | C19: 2024 | D19: Campos Parex | E19: MOVILIZACIÓN Y DESMOVILIZACIÓN | F19: Inspección de vía y nueva locación: Recorridos a pie / Supervisión en campo/ inspecciones/ Interaccion con la comunidad / Desplazamiento en vehículos | G19: Ruta de Movilización y Nueva locación | H19: Ignición incontrolada de agentes químicos inflamables por condiciones presentes en el lugar de trabajo | I19: Condiciones_de_seguridad | J19: =_xlfn.XLOOKUP(año24[[#This Row],[PELIGRO -Tipo]], Tabla12[Calsificación], Tabla12[Imagen]) -> #VALUE! | K19: 6.4 Tecnológico | L19: AT | M19: Rutinaria | N19: Interna | O19: 2 | P19: 4 | Q19: 2 | R19: 8 | S19: Contratistas | T19: Programa de mantenimiento de equipos y herramientas | U19: Disponibilidad de extintores Monitoreo de gases Inspección preoperacional de equipos y herramientas | V19: Uso de EPP Capacitación en Manejo de extintores y control de incendios Capacitación brigadistas | W19: 4 Crítico | X19: Personas | Y19: 2 Improbable | Z19: =INDEX($AS$3:$AV$6,MATCH($W19,$AR$3:$AR$6,FALSE),MATCH($Y19,AS$7:$AV$7,FALSE)) -> 8 | AA19: Si (Ver matriz de requisitos legales) | AB19: Ninguna | AC19: Ninguna | AD19: Ninguna | AE19: * Procedimiento de manejo seguro de sustancias químicas * Programa de Gestión Seguridad Basada en el Comportamiento * Procedimiento Sistema Permisos de Trabajo * Anexo HSEQ para contratistas * Plan de emergencias * Uso de herramienta antichispas en áreas calisificadas clase 1 división 1 y 2 | AF19: Ver matriz de EPP | AG19: ="Eliminación del riesgo:"&año24[[#This Row],[CONTROLES (TRATAMIENTO DEL RIESGO Y PLANES ATENUANTES) - ELIMINACIÓN]]&"Sustitución del riesgo; "&año24[[#This Row],[CONTROLES (TRATAMIENTO DEL RIESGO Y PLANES ATENUANTES) - SUSTITUCIÓN]]&"Controles de Ingenieria; "&año24[[#This Row],[CONTROLES (TRATAMIENTO DEL RIESGO Y PLANES ATENUANTES) - CONTROLES DE INGENIERIA]]&" Controles administrativos; "&año24[[#This Row],[CONTROLES (TRATAMIENTO DEL RIESGO Y PLANES ATENUANTES) - CONTROLES ADMINISTRATIVOS / SEÑALIZACIÓN]]&"Controles de EPP; "&año24[[#This Row],[CONTROLES (TRATAMIENTO DEL RIESGO Y PLANES ATENUANTES) - ELEMENTOS DE PROTECCIÓN PERSONAL]] -> Eliminación del riesgo:NingunaSustitución del riesgo; NingunaControles de Ingenieria; Ninguna Controles administrativos; * Procedimiento de manejo seguro de sustancias químicas * Programa de Gestión Seguridad Basada en el Comportamiento * Procedimiento Sistema Permisos de Trabajo * Anexo HSEQ para contratistas * Plan de emergencias * Uso de herramienta antichispas en áreas calisificadas clase 1 división 1 y 2Controles de EPP; Ver matriz de EPP | AH19: HS Parex Contratista | AI19: 4 Crítico | AJ19: Personas | AK19: 1 Remoto | AL19: =INDEX($AS$3:$AV$6,MATCH($AI19,$AR$3:$AR$6,FALSE),MATCH($AK19,$AS$7:$AV$7,FALSE)) -> 4 | AM19: =IF(año24[[#This Row],[VALORACION DEL RIESGO RESULTANTE CON CONTROLES (Riesgo residual) - Nivel de riesgo]]<=3,"Bajo",IF(año24[[#This Row],[VALORACION DEL RIESGO RESULTANTE CON CONTROLES (Riesgo residual) - Nivel de riesgo]]<=6,"Medio",IF(año24[[#This Row],[VALORACION DEL RIESGO RESULTANTE CON CONTROLES (Riesgo residual) - Nivel de riesgo]]<=12,"Alto","Extremo"))) -> Medio | AO19: =IF(AL19<=4,"SI",IF(AL19>=5,"NO")) -> SI | AP19: ="El nivel del riesgo es"&" "&año24[[#This Row],[VALORACION DEL RIESGO RESULTANTE CON CONTROLES (Riesgo residual) - INTERPRETACIÓN DEL RIESGO]]&" siendo las principales consecuencias las siguientes; "&año24[[#This Row],[Consecuencias (AT/EL)]] -> El nivel del riesgo es Medio siendo las principales consecuencias las siguientes; AT | AQ19: =_xlfn.XLOOKUP(año24[[#This Row],[VALORACION DEL RIESGO RESULTANTE CON CONTROLES (Riesgo residual) - INTERPRETACIÓN DEL RIESGO]], Nivel[Calsificación], Nivel[Imagen]) -> #VALUE!
B20: 11 | C20: 2024 | D20: Campos Parex | E20: MOVILIZACIÓN Y DESMOVILIZACIÓN | F20: Inspección de vía y nueva locación: Recorridos a pie / Supervisión en campo/ inspecciones/ Interaccion con la comunidad / Desplazamiento en vehículos | G20: Ruta de Movilización y Nueva locación | H20: Amedrentación o secuestro por presencia de grupos al margen de la Ley, y bloqueos de la actividad por paros de la comunidad. | I20: Condiciones_de_seguridad | J20: =_xlfn.XLOOKUP(año24[[#This Row],[PELIGRO -Tipo]], Tabla12[Calsificación], Tabla12[Imagen]) -> #VALUE! | K20: 6.6 Públicos | L20: AT | M20: Rutinaria | N20: Externa | O20: 2 | P20: 4 | Q20: 2 | R20: 8 | S20: Contratistas | U20: Sistema de seguridad y vigilancia privada Centro de control Cerramiento de la locación Control de ingreso y salida de visitantes | V20: Charlas Informativas Charlas de seguridad física. | W20: 4 Crítico | X20: Personas | Y20: 2 Improbable | Z20: =INDEX($AS$3:$AV$6,MATCH($W20,$AR$3:$AR$6,FALSE),MATCH($Y20,AS$7:$AV$7,FALSE)) -> 8 | AA20: Si (Ver matriz de requisitos legales) | AB20: Ninguna | AC20: Ninguna | AD20: Ninguna | AE20: * Plan de emergencias * Anexo HSEQ para contratistas * Protocolos de seguridad física * Disponibilidad de equipos de comunicación | AF20: Ninguna | AG20: ="Eliminación del riesgo:"&año24[[#This Row],[CONTROLES (TRATAMIENTO DEL RIESGO Y PLANES ATENUANTES) - ELIMINACIÓN]]&"Sustitución del riesgo; "&año24[[#This Row],[CONTROLES (TRATAMIENTO DEL RIESGO Y PLANES ATENUANTES) - SUSTITUCIÓN]]&"Controles de Ingenieria; "&año24[[#This Row],[CONTROLES (TRATAMIENTO DEL RIESGO Y PLANES ATENUANTES) - CONTROLES DE INGENIERIA]]&" Controles administrativos; "&año24[[#This Row],[CONTROLES (TRATAMIENTO DEL RIESGO Y PLANES ATENUANTES) - CONTROLES ADMINISTRATIVOS / SEÑALIZACIÓN]]&"Controles de EPP; "&año24[[#This Row],[CONTROLES (TRATAMIENTO DEL RIESGO Y PLANES ATENUANTES) - ELEMENTOS DE PROTECCIÓN PERSONAL]] -> Eliminación del riesgo:NingunaSustitución del riesgo; NingunaControles de Ingenieria; Ninguna Controles administrativos; * Plan de emergencias * Anexo HSEQ para contratistas * Protocolos de seguridad física * Disponibilidad de equipos de comunicaciónControles de EPP; Ninguna | AH20: HS Parex Contratista | AI20: 2 Moderado | AJ20: Personas | AK20: 2 Improbable | AL20: =INDEX($AS$3:$AV$6,MATCH($AI20,$AR$3:$AR$6,FALSE),MATCH($AK20,$AS$7:$AV$7,FALSE)) -> 4 | AM20: =IF(año24[[#This Row],[VALORACION DEL RIESGO RESULTANTE CON CONTROLES (Riesgo residual) - Nivel de riesgo]]<=3,"Bajo",IF(año24[[#This Row],[VALORACION DEL RIESGO RESULTANTE CON CONTROLES (Riesgo residual) - Nivel de riesgo]]<=6,"Medio",IF(año24[[#This Row],[VALORACION DEL RIESGO RESULTANTE CON CONTROLES (Riesgo residual) - Nivel de riesgo]]<=12,"Alto","Extremo"))) -> Medio | AO20: =IF(AL20<=4,"SI",IF(AL20>=5,"NO")) -> SI | AP20: ="El nivel del riesgo es"&" "&año24[[#This Row],[VALORACION DEL RIESGO RESULTANTE CON CONTROLES (Riesgo residual) - INTERPRETACIÓN DEL RIESGO]]&" siendo las principales consecuencias las siguientes; "&año24[[#This Row],[Consecuencias (AT/EL)]] -> El nivel del riesgo es Medio siendo las principales consecuencias las siguientes; AT | AQ20: =_xlfn.XLOOKUP(año24[[#This Row],[VALORACION DEL RIESGO RESULTANTE CON CONTROLES (Riesgo residual) - INTERPRETACIÓN DEL RIESGO]], Nivel[Calsificación], Nivel[Imagen]) -> #VALUE!
B21: 12 | C21: 2024 | D21: Campos Parex | E21: MOVILIZACIÓN Y DESMOVILIZACIÓN | F21: Movilización de equipo y campamento: Traslado terrestre de equipo, partes y campamento a locación. Ubicación del equipo en la locación (Ubicación de unidad básica, instalación de tanques, instalación de la mesa, anclaje vientos, instalación de choke manifold, instalación del acumulador, ubicación de casetas, ubicación de extintores y señalización ) | G21: Ruta de Movilización y Nueva locación | H21: Atropellos o golpes con vehículos | I21: Condiciones_de_seguridad | J21: =_xlfn.XLOOKUP(año24[[#This Row],[PELIGRO -Tipo]], Tabla12[Calsificación], Tabla12[Imagen]) -> #VALUE! | K21: 6.5 Accidentes de transito | L21: AT | M21: Rutinaria | N21: Interna | O21: 2 | P21: 68 | Q21: 2 | R21: 8 | S21: Contratistas | T21: Sistemas de seguridad del Vehículo (cinturón de seguridad, airbags, apoya cabezas, llantas) Sistema de monitoreo de velocidad acorde a la legislación | U21: Inspecciones de seguridad Plan de movilizaciones Señalización Controlador vial | V21: * Plan estratégico de seguridad via-PEVS * Control de contratistas de servicios de transporte * Anexo HSEQ para contratistas * Plan de Emergencias | W21: 3 Serio | X21: Personas | Y21: 3 Probable | Z21: =INDEX($AS$3:$AV$6,MATCH($W21,$AR$3:$AR$6,FALSE),MATCH($Y21,AS$7:$AV$7,FALSE)) -> 9 | AA21: Si (Ver matriz de requisitos legales) | AB21: Ninguna | AC21: Ninguna | AD21: Sistemas de seguridad del Vehículo (cinturón de seguridad, airbags, apoya cabezas, llantas) | AE21: Continuar con los controles implemetados: *Seguimiento cumplimiento del PESV * Evaluación de desempeño de cotratistas | AF21: Ver matriz de EPP | AG21: ="Eliminación del riesgo:"&año24[[#This Row],[CONTROLES (TRATAMIENTO DEL RIESGO Y PLANES ATENUANTES) - ELIMINACIÓN]]&"Sustitución del riesgo; "&año24[[#This Row],[CONTROLES (TRATAMIENTO DEL RIESGO Y PLANES ATENUANTES) - SUSTITUCIÓN]]&"Controles de Ingenieria; "&año24[[#This Row],[CONTROLES (TRATAMIENTO DEL RIESGO Y PLANES ATENUANTES) - CONTROLES DE INGENIERIA]]&" Controles administrativos; "&año24[[#This Row],[CONTROLES (TRATAMIENTO DEL RIESGO Y PLANES ATENUANTES) - CONTROLES ADMINISTRATIVOS / SEÑALIZACIÓN]]&"Controles de EPP; "&año24[[#This Row],[CONTROLES (TRATAMIENTO DEL RIESGO Y PLANES ATENUANTES) - ELEMENTOS DE PROTECCIÓN PERSONAL]] -> Eliminación del riesgo:NingunaSustitución del riesgo; NingunaControles de Ingenieria; Sistemas de seguridad del Vehículo (cinturón de seguridad, airbags, apoya cabezas, llantas) Controles administrativos; Continuar con los controles implemetados: *Seguimiento cumplimiento del PESV * Evaluación de desempeño de cotratistas Controles de EPP; Ver matriz de EPP | AH21: HS Parex Contratista | AI21: 2 Moderado | AJ21: Personas | AK21: 2 Improbable | AL21: =INDEX($AS$3:$AV$6,MATCH($AI21,$AR$3:$AR$6,FALSE),MATCH($AK21,$AS$7:$AV$7,FALSE)) -> 4 | AM21: =IF(año24[[#This Row],[VALORACION DEL RIESGO RESULTANTE CON CONTROLES (Riesgo residual) - Nivel de riesgo]]<=3,"Bajo",IF(año24[[#This Row],[VALORACION DEL RIESGO RESULTANTE CON CONTROLES (Riesgo residual) - Nivel de riesgo]]<=6,"Medio",IF(año24[[#This Row],[VALORACION DEL RIESGO RESULTANTE CON CONTROLES (Riesgo residual) - Nivel de riesgo]]<=12,"Alto","Extremo"))) -> Medio | AO21: =IF(AL21<=4,"SI",IF(AL21>=5,"NO")) -> SI | AP21: ="El nivel del riesgo es"&" "&año24[[#This Row],[VALORACION DEL RIESGO RESULTANTE CON CONTROLES (Riesgo residual) - INTERPRETACIÓN DEL RIESGO]]&" siendo las principales consecuencias las siguientes; "&año24[[#This Row],[Consecuencias (AT/EL)]] -> El nivel del riesgo es Medio siendo las principales consecuencias las siguientes; AT | AQ21: =_xlfn.XLOOKUP(año24[[#This Row],[VALORACION DEL RIESGO RESULTANTE CON CONTROLES (Riesgo residual) - INTERPRETACIÓN DEL RIESGO]], Nivel[Calsificación], Nivel[Imagen]) -> #VALUE!
B22: 13 | C22: 2024 | D22: Campos Parex | E22: MOVILIZACIÓN Y DESMOVILIZACIÓN | F22: Movilización de equipo y campamento: Traslado terrestre de equipo, partes y campamento a locación. Ubicación del equipo en la locación (Ubicación de unidad básica, instalación de tanques, instalación de la mesa, anclaje vientos, instalación de choke manifold, instalación del acumulador, ubicación de casetas, ubicación de extintores y señalización ) | G22: Ruta de Movilización y Nueva locación | H22: Ser golpeados y quedar atrapados al producirse el vuelco de cargas al transportar las mismas. | I22: Condiciones_de_seguridad | J22: =_xlfn.XLOOKUP(año24[[#This Row],[PELIGRO -Tipo]], Tabla12[Calsificación], Tabla12[Imagen]) -> #VALUE! | K22: 6.1 Mecánico | L22: AT | M22: Rutinaria | N22: Interna | O22: 2 | P22: 68 | Q22: 2 | R22: 8 | S22: Contratistas | T22: Programa de mantenimiento de equipos | U22: Inspecciones de seguridad | V22: Programa de capacitación (Riesgo Mecánico, cuidado de manos) Procedimiento de permisos de trabajo, ATS Programa de seguridad basada en el comportamiento | W22: 3 Serio | X22: Personas | Y22: 3 Probable | Z22: =INDEX($AS$3:$AV$6,MATCH($W22,$AR$3:$AR$6,FALSE),MATCH($Y22,AS$7:$AV$7,FALSE)) -> 9 | AA22: Si (Ver matriz de requisitos legales) | AB22: Ninguna | AC22: Ninguna | AD22: * Identificar en herramienta puntos de peligro (Pellizco; machucon; agarre) * Instalación de guayas antilatigos | AE22: *Implementar Programa de Gestión del Riesgo Mecánico * Seguimiento Programa de mantenimiento mecánico y eléctrico *Programa DROPS Mantener controles existentes: * Programa de Gestión Seguridad Basada en el Comportamiento * Programa de Gestión Cuidado de Manos * Manual de gestión de proyectos de facilidades * Procedimiento Sistema Permisos de Trabajo * Procedimiento Manejo Seguro de Herramientas Manuales * Procedimiento Levantamiento de Cargas * Anexo HSEQ para contratistas * Plan de Emergencias | AF22: Ver matriz de EPP | AG22: ="Eliminación del riesgo:"&año24[[#This Row],[CONTROLES (TRATAMIENTO DEL RIESGO Y PLANES ATENUANTES) - ELIMINACIÓN]]&"Sustitución del riesgo; "&año24[[#This Row],[CONTROLES (TRATAMIENTO DEL RIESGO Y PLANES ATENUANTES) - SUSTITUCIÓN]]&"Controles de Ingenieria; "&año24[[#This Row],[CONTROLES (TRATAMIENTO DEL RIESGO Y PLANES ATENUANTES) - CONTROLES DE INGENIERIA]]&" Controles administrativos; "&año24[[#This Row],[CONTROLES (TRATAMIENTO DEL RIESGO Y PLANES ATENUANTES) - CONTROLES ADMINISTRATIVOS / SEÑALIZACIÓN]]&"Controles de EPP; "&año24[[#This Row],[CONTROLES (TRATAMIENTO DEL RIESGO Y PLANES ATENUANTES) - ELEMENTOS DE PROTECCIÓN PERSONAL]] -> Eliminación del riesgo:NingunaSustitución del riesgo; NingunaControles de Ingenieria; * Identificar en herramienta puntos de peligro (Pellizco; machucon; agarre) * Instalación de guayas antilatigos Controles administrativos; *Implementar Programa de Gestión del Riesgo Mecánico * Seguimiento Programa de mantenimiento mecánico y eléctrico *Programa DROPS Mantener controles existentes: * Programa de Gestión Seguridad Basada en el Comportamiento * Programa de Gestión Cuidado de Manos * Manual de gestión de proyectos de facilidades * Procedimiento Sistema Permisos de Trabajo * Procedimiento Manejo Seguro de Herramientas Manuales * Procedimiento Levantamiento de Cargas * Anexo HSEQ para contratistas * Plan de EmergenciasControles de EPP; Ver matriz de EPP | AH22: HS Parex Contratista | AI22: 2 Moderado | AJ22: Personas | AK22: 2 Improbable | AL22: =INDEX($AS$3:$AV$6,MATCH($AI22,$AR$3:$AR$6,FALSE),MATCH($AK22,$AS$7:$AV$7,FALSE)) -> 4 | AM22: =IF(año24[[#This Row],[VALORACION DEL RIESGO RESULTANTE CON CONTROLES (Riesgo residual) - Nivel de riesgo]]<=3,"Bajo",IF(año24[[#This Row],[VALORACION DEL RIESGO RESULTANTE CON CONTROLES (Riesgo residual) - Nivel de riesgo]]<=6,"Medio",IF(año24[[#This Row],[VALORACION DEL RIESGO RESULTANTE CON CONTROLES (Riesgo residual) - Nivel de riesgo]]<=12,"Alto","Extremo"))) -> Medio | AO22: =IF(AL22<=4,"SI",IF(AL22>=5,"NO")) -> SI | AP22: ="El nivel del riesgo es"&" "&año24[[#This Row],[VALORACION DEL RIESGO RESULTANTE CON CONTROLES (Riesgo residual) - INTERPRETACIÓN DEL RIESGO]]&" siendo las principales consecuencias las siguientes; "&año24[[#This Row],[Consecuencias (AT/EL)]] -> El nivel del riesgo es Medio siendo las principales consecuencias las siguientes; AT | AQ22: =_xlfn.XLOOKUP(año24[[#This Row],[VALORACION DEL RIESGO RESULTANTE CON CONTROLES (Riesgo residual) - INTERPRETACIÓN DEL RIESGO]], Nivel[Calsificación], Nivel[Imagen]) -> #VALUE!
B23: 14 | C23: 2024 | D23: Campos Parex | E23: MOVILIZACIÓN Y DESMOVILIZACIÓN | F23: Movilización de equipo y campamento: Traslado terrestre de equipo, partes y campamento a locación. Ubicación del equipo en la locación (Ubicación de unidad básica, instalación de tanques, instalación de la mesa, anclaje vientos, instalación de choke manifold, instalación del acumulador, ubicación de casetas, ubicación de extintores y señalización ) | G23: Ruta de Movilización y Nueva locación | H23: Cuerdas de baja, media y alta tensión | I23: Condiciones_de_seguridad | J23: =_xlfn.XLOOKUP(año24[[#This Row],[PELIGRO -Tipo]], Tabla12[Calsificación], Tabla12[Imagen]) -> #VALUE! | K23: 6.2 Eléctrico | L23: AT | M23: Rutinaria | N23: Interna | O23: 2 | P23: 68 | Q23: 2 | R23: 8 | S23: Contratistas | T23: Mantenimientos preventivos y predictivos a los equipos | U23: Sistema puesta a tierra Inspecciones de seguridad Señalización reglamentaria riesgo eléctrico | V23: Certificado de Aislamiento (Bloqueo, candado y Etiquetado). Sistema lock out 5 Reglas de oro aislamiento. Procedimiento Permisos de trabajo, ATS Personal competente para trabajos eléctricos de acuerdo con certificación conte Capacitación riesgo eléctrico | W23: 3 Serio | X23: Personas | Y23: 3 Probable | Z23: =INDEX($AS$3:$AV$6,MATCH($W23,$AR$3:$AR$6,FALSE),MATCH($Y23,AS$7:$AV$7,FALSE)) -> 9 | AA23: Si (Ver matriz de requisitos legales) | AB23: Ninguna | AC23: Ninguna | AD23: Mantener Controles Existentes: Sistema de aterrizaje pararrayos Puesta a tierra de equipos | AE23: Implementar programa de gestión de riesgo eléctrico Mantener controles existentes: *Inspección Vial (Identificación de cuerdas de alta, media, baja) *Uso de pertigueros en puntos identificados *Señalización riesgo eléctrico * Programa de Gestión Seguridad Basada en el Comportamiento * Procedimiento sistemas permiso de trabajo * Procedimiento Aislamiento de Fuentes de Energia * Anexo HSEQ para contratistas * Plan de emergencias | AF23: Ver matriz de EPP | AG23: ="Eliminación del riesgo:"&año24[[#This Row],[CONTROLES (TRATAMIENTO DEL RIESGO Y PLANES ATENUANTES) - ELIMINACIÓN]]&"Sustitución del riesgo; "&año24[[#This Row],[CONTROLES (TRATAMIENTO DEL RIESGO Y PLANES ATENUANTES) - SUSTITUCIÓN]]&"Controles de Ingenieria; "&año24[[#This Row],[CONTROLES (TRATAMIENTO DEL RIESGO Y PLANES ATENUANTES) - CONTROLES DE INGENIERIA]]&" Controles administrativos; "&año24[[#This Row],[CONTROLES (TRATAMIENTO DEL RIESGO Y PLANES ATENUANTES) - CONTROLES ADMINISTRATIVOS / SEÑALIZACIÓN]]&"Controles de EPP; "&año24[[#This Row],[CONTROLES (TRATAMIENTO DEL RIESGO Y PLANES ATENUANTES) - ELEMENTOS DE PROTECCIÓN PERSONAL]] -> Eliminación del riesgo:NingunaSustitución del riesgo; NingunaControles de Ingenieria; Mantener Controles Existentes: Sistema de aterrizaje pararrayos Puesta a tierra de equipos Controles administrativos; Implementar programa de gestión de riesgo eléctrico Mantener controles existentes: *Inspección Vial (Identificación de cuerdas de alta, media, baja) *Uso de pertigueros en puntos identificados *Señalización riesgo eléctrico * Programa de Gestión Seguridad Basada en el Comportamiento * Procedimiento sistemas permiso de trabajo * Procedimiento Aislamiento de Fuentes de Energia * Anexo HSEQ para contratistas * Plan de emergenciasControles de EPP; Ver matriz de EPP | AH23: HS Parex Contratista | AI23: 2 Moderado | AJ23: Personas | AK23: 2 Improbable | AL23: =INDEX($AS$3:$AV$6,MATCH($AI23,$AR$3:$AR$6,FALSE),MATCH($AK23,$AS$7:$AV$7,FALSE)) -> 4 | AM23: =IF(año24[[#This Row],[VALORACION DEL RIESGO RESULTANTE CON CONTROLES (Riesgo residual) - Nivel de riesgo]]<=3,"Bajo",IF(año24[[#This Row],[VALORACION DEL RIESGO RESULTANTE CON CONTROLES (Riesgo residual) - Nivel de riesgo]]<=6,"Medio",IF(año24[[#This Row],[VALORACION DEL RIESGO RESULTANTE CON CONTROLES (Riesgo residual) - Nivel de riesgo]]<=12,"Alto","Extremo"))) -> Medio | AO23: =IF(AL23<=4,"SI",IF(AL23>=5,"NO")) -> SI | AP23: ="El nivel del riesgo es"&" "&año24[[#This Row],[VALORACION DEL RIESGO RESULTANTE CON CONTROLES (Riesgo residual) - INTERPRETACIÓN DEL RIESGO]]&" siendo las principales consecuencias las siguientes; "&año24[[#This Row],[Consecuencias (AT/EL)]] -> El nivel del riesgo es Medio siendo las principales consecuencias las siguientes; AT | AQ23: =_xlfn.XLOOKUP(año24[[#This Row],[VALORACION DEL RIESGO RESULTANTE CON CONTROLES (Riesgo residual) - INTERPRETACIÓN DEL RIESGO]], Nivel[Calsificación], Nivel[Imagen]) -> #VALUE!
B24: 15 | C24: 2024 | D24: Campos Parex | E24: MOVILIZACIÓN Y DESMOVILIZACIÓN | F24: Movilización de equipo y campamento: Traslado terrestre de equipo, partes y campamento a locación. Ubicación del equipo en la locación (Ubicación de unidad básica, instalación de tanques, instalación de la mesa, anclaje vientos, instalación de choke manifold, instalación del acumulador, ubicación de casetas, ubicación de extintores y señalización ) | G24: Ruta de Movilización y Nueva locación | H24: Lluvias, tormentas eléctricas | I24: Fenómenos_naturales | J24: =_xlfn.XLOOKUP(año24[[#This Row],[PELIGRO -Tipo]], Tabla12[Calsificación], Tabla12[Imagen]) -> #VALUE! | K24: 7.6 Precipitaciones | L24: AT | M24: Rutinaria | N24: Externa | O24: 2 | P24: 68 | Q24: 2 | R24: 1 | S24: Contratistas | T24: Inspección preoperacional de equipos y herramientas | U24: Señalización Layout de la locación Sistema de alarma Detector de tormentas Pararrayos Brigada de emergencias | V24: Uso de EPP (Dotación de invierno) Charlas Informativas | W24: 3 Serio | X24: Personas | Y24: 2 Improbable | Z24: =INDEX($AS$3:$AV$6,MATCH($W24,$AR$3:$AR$6,FALSE),MATCH($Y24,AS$7:$AV$7,FALSE)) -> 6 | AA24: Si (Ver matriz de requisitos legales) | AB24: Ninguna | AC24: Ninguna | AD24: Puesta a tierra de equipos en la locación | AE24: Continuar con los controles implemetados: * Plan de emergencias *Unidad de Respuesta a Emergencias (URE) | AF24: Ver matriz de EPP | AG24: ="Eliminación del riesgo:"&año24[[#This Row],[CONTROLES (TRATAMIENTO DEL RIESGO Y PLANES ATENUANTES) - ELIMINACIÓN]]&"Sustitución del riesgo; "&año24[[#This Row],[CONTROLES (TRATAMIENTO DEL RIESGO Y PLANES ATENUANTES) - SUSTITUCIÓN]]&"Controles de Ingenieria; "&año24[[#This Row],[CONTROLES (TRATAMIENTO DEL RIESGO Y PLANES ATENUANTES) - CONTROLES DE INGENIERIA]]&" Controles administrativos; "&año24[[#This Row],[CONTROLES (TRATAMIENTO DEL RIESGO Y PLANES ATENUANTES) - CONTROLES ADMINISTRATIVOS / SEÑALIZACIÓN]]&"Controles de EPP; "&año24[[#This Row],[CONTROLES (TRATAMIENTO DEL RIESGO Y PLANES ATENUANTES) - ELEMENTOS DE PROTECCIÓN PERSONAL]] -> Eliminación del riesgo:NingunaSustitución del riesgo; NingunaControles de Ingenieria; Puesta a tierra de equipos en la locación Controles administrativos; Continuar con los controles implemetados: * Plan de emergencias *Unidad de Respuesta a Emergencias (URE)Controles de EPP; Ver matriz de EPP | AH24: HS Parex Contratista | AI24: 3 Serio | AJ24: Personas | AK24: 1 Remoto | AL24: =INDEX($AS$3:$AV$6,MATCH($AI24,$AR$3:$AR$6,FALSE),MATCH($AK24,$AS$7:$AV$7,FALSE)) -> 3 | AM24: =IF(año24[[#This Row],[VALORACION DEL RIESGO RESULTANTE CON CONTROLES (Riesgo residual) - Nivel de riesgo]]<=3,"Bajo",IF(año24[[#This Row],[VALORACION DEL RIESGO RESULTANTE CON CONTROLES (Riesgo residual) - Nivel de riesgo]]<=6,"Medio",IF(año24[[#This Row],[VALORACION DEL RIESGO RESULTANTE CON CONTROLES (Riesgo residual) - Nivel de riesgo]]<=12,"Alto","Extremo"))) -> Bajo | AO24: =IF(AL24<=4,"SI",IF(AL24>=5,"NO")) -> SI | AP24: ="El nivel del riesgo es"&" "&año24[[#This Row],[VALORACION DEL RIESGO RESULTANTE CON CONTROLES (Riesgo residual) - INTERPRETACIÓN DEL RIESGO]]&" siendo las principales consecuencias las siguientes; "&año24[[#This Row],[Consecuencias (AT/EL)]] -> El nivel del riesgo es Bajo siendo las principales consecuencias las siguientes; AT | AQ24: =_xlfn.XLOOKUP(año24[[#This Row],[VALORACION DEL RIESGO RESULTANTE CON CONTROLES (Riesgo residual) - INTERPRETACIÓN DEL RIESGO]], Nivel[Calsificación], Nivel[Imagen]) -> #VALUE!
B25: 16 | C25: 2024 | D25: Campos Parex | E25: MOVILIZACIÓN Y DESMOVILIZACIÓN | F25: Movilización de equipo y campamento: Traslado terrestre de equipo, partes y campamento a locación. Ubicación del equipo en la locación (Ubicación de unidad básica, instalación de tanques, instalación de la mesa, anclaje vientos, instalación de choke manifold, instalación del acumulador, ubicación de casetas, ubicación de extintores y señalización ) | G25: Ruta de Movilización y Nueva locación | H25: Caídas de objetos, ser golpeados por objetos proyectados de las cargas (ramas, piedras, roturas de estaqueros) | I25: Condiciones_de_seguridad | J25: =_xlfn.XLOOKUP(año24[[#This Row],[PELIGRO -Tipo]], Tabla12[Calsificación], Tabla12[Imagen]) -> #VALUE! | K25: 6.1 Mecánico | L25: AT | M25: Rutinaria | N25: Interna | O25: 2 | P25: 68 | Q25: 2 | R25: 8 | S25: Contratistas | T25: Inspección de equipos y herramientas | U25: Inspecciones de seguridad | V25: Programa de capacitación (Riesgo Mecánico, cuidado de manos) Procedimiento de permisos de trabajo, ATS Programa de seguridad basada en el comportamiento | W25: 3 Serio | X25: Personas | Y25: 3 Probable | Z25: =INDEX($AS$3:$AV$6,MATCH($W25,$AR$3:$AR$6,FALSE),MATCH($Y25,AS$7:$AV$7,FALSE)) -> 9 | AA25: Si (Ver matriz de requisitos legales) | AB25: Ninguna | AC25: Ninguna | AD25: * Identificar en herramienta puntos de peligro (Pellizco; machucon; agarre) * Instalación de guayas antilatigos | AE25: *Implementar Programa de Gestión del Riesgo Mecánico * Seguimiento Programa de mantenimiento mecánico y eléctrico *Programa DROPS Mantener controles existentes: * Programa de Gestión Seguridad Basada en el Comportamiento * Programa de Gestión Cuidado de Manos * Manual de gestión de proyectos de facilidades * Procedimiento Sistema Permisos de Trabajo * Procedimiento Manejo Seguro de Herramientas Manuales * Procedimiento Levantamiento de Cargas * Anexo HSEQ para contratistas * Plan de Emergencias | AF25: Ver matriz de EPP | AG25: ="Eliminación del riesgo:"&año24[[#This Row],[CONTROLES (TRATAMIENTO DEL RIESGO Y PLANES ATENUANTES) - ELIMINACIÓN]]&"Sustitución del riesgo; "&año24[[#This Row],[CONTROLES (TRATAMIENTO DEL RIESGO Y PLANES ATENUANTES) - SUSTITUCIÓN]]&"Controles de Ingenieria; "&año24[[#This Row],[CONTROLES (TRATAMIENTO DEL RIESGO Y PLANES ATENUANTES) - CONTROLES DE INGENIERIA]]&" Controles administrativos; "&año24[[#This Row],[CONTROLES (TRATAMIENTO DEL RIESGO Y PLANES ATENUANTES) - CONTROLES ADMINISTRATIVOS / SEÑALIZACIÓN]]&"Controles de EPP; "&año24[[#This Row],[CONTROLES (TRATAMIENTO DEL RIESGO Y PLANES ATENUANTES) - ELEMENTOS DE PROTECCIÓN PERSONAL]] -> Eliminación del riesgo:NingunaSustitución del riesgo; NingunaControles de Ingenieria; * Identificar en herramienta puntos de peligro (Pellizco; machucon; agarre) * Instalación de guayas antilatigos Controles administrativos; *Implementar Programa de Gestión del Riesgo Mecánico * Seguimiento Programa de mantenimiento mecánico y eléctrico *Programa DROPS Mantener controles existentes: * Programa de Gestión Seguridad Basada en el Comportamiento * Programa de Gestión Cuidado de Manos * Manual de gestión de proyectos de facilidades * Procedimiento Sistema Permisos de Trabajo * Procedimiento Manejo Seguro de Herramientas Manuales * Procedimiento Levantamiento de Cargas * Anexo HSEQ para contratistas * Plan de EmergenciasControles de EPP; Ver matriz de EPP | AH25: HS Parex Contratista | AI25: 2 Moderado | AJ25: Personas | AK25: 2 Improbable | AL25: =INDEX($AS$3:$AV$6,MATCH($AI25,$AR$3:$AR$6,FALSE),MATCH($AK25,$AS$7:$AV$7,FALSE)) -> 4 | AM25: =IF(año24[[#This Row],[VALORACION DEL RIESGO RESULTANTE CON CONTROLES (Riesgo residual) - Nivel de riesgo]]<=3,"Bajo",IF(año24[[#This Row],[VALORACION DEL RIESGO RESULTANTE CON CONTROLES (Riesgo residual) - Nivel de riesgo]]<=6,"Medio",IF(año24[[#This Row],[VALORACION DEL RIESGO RESULTANTE CON CONTROLES (Riesgo residual) - Nivel de riesgo]]<=12,"Alto","Extremo"))) -> Medio | AO25: =IF(AL25<=4,"SI",IF(AL25>=5,"NO")) -> SI | AP25: ="El nivel del riesgo es"&" "&año24[[#This Row],[VALORACION DEL RIESGO RESULTANTE CON CONTROLES (Riesgo residual) - INTERPRETACIÓN DEL RIESGO]]&" siendo las principales consecuencias las siguientes; "&año24[[#This Row],[Consecuencias (AT/EL)]] -> El nivel del riesgo es Medio siendo las principales consecuencias las siguientes; AT | AQ25: =_xlfn.XLOOKUP(año24[[#This Row],[VALORACION DEL RIESGO RESULTANTE CON CONTROLES (Riesgo residual) - INTERPRETACIÓN DEL RIESGO]], Nivel[Calsificación], Nivel[Imagen]) -> #VALUE!
B26: 17 | C26: 2024 | D26: Campos Parex | E26: MOVILIZACIÓN Y DESMOVILIZACIÓN | F26: Movilización de equipo y campamento: Traslado terrestre de equipo, partes y campamento a locación. Ubicación del equipo en la locación (Ubicación de unidad básica, instalación de tanques, instalación de la mesa, anclaje vientos, instalación de choke manifold, instalación del acumulador, ubicación de casetas, ubicación de extintores y señalización ) | G26: Ruta de Movilización y Nueva locación | H26: Atropellos o golpes con vehículos | I26: Condiciones_de_seguridad | J26: =_xlfn.XLOOKUP(año24[[#This Row],[PELIGRO -Tipo]], Tabla12[Calsificación], Tabla12[Imagen]) -> #VALUE! | K26: 6.5 Accidentes de transito | L26: AT | M26: Rutinaria | N26: Externa | O26: 2 | P26: 68 | Q26: 2 | R26: 8 | S26: Contratistas | T26: Sistemas de seguridad del Vehículo (cinturón de seguridad, airbags, apoya cabezas, llantas) Sistema de monitoreo de velocidad acorde a la legislación | U26: Inspecciones de seguridad Plan de movilizaciones Señalización Controlador vial | V26: * Plan estratégico de seguridad via-PEVS * Control de contratistas de servicios de transporte * Anexo HSEQ para contratistas * Plan de Emergencias | W26: 3 Serio | X26: Personas | Y26: 3 Probable | Z26: =INDEX($AS$3:$AV$6,MATCH($W26,$AR$3:$AR$6,FALSE),MATCH($Y26,AS$7:$AV$7,FALSE)) -> 9 | AA26: Si (Ver matriz de requisitos legales) | AB26: Ninguna | AC26: Ninguna | AD26: Sistemas de seguridad del Vehículo (cinturón de seguridad, airbags, apoya cabezas, llantas) | AE26: Continuar con los controles implemetados: *Seguimiento cumplimiento del PESV * Evaluación de desempeño de cotratistas | AF26: Ver matriz de EPP | AG26: ="Eliminación del riesgo:"&año24[[#This Row],[CONTROLES (TRATAMIENTO DEL RIESGO Y PLANES ATENUANTES) - ELIMINACIÓN]]&"Sustitución del riesgo; "&año24[[#This Row],[CONTROLES (TRATAMIENTO DEL RIESGO Y PLANES ATENUANTES) - SUSTITUCIÓN]]&"Controles de Ingenieria; "&año24[[#This Row],[CONTROLES (TRATAMIENTO DEL RIESGO Y PLANES ATENUANTES) - CONTROLES DE INGENIERIA]]&" Controles administrativos; "&año24[[#This Row],[CONTROLES (TRATAMIENTO DEL RIESGO Y PLANES ATENUANTES) - CONTROLES ADMINISTRATIVOS / SEÑALIZACIÓN]]&"Controles de EPP; "&año24[[#This Row],[CONTROLES (TRATAMIENTO DEL RIESGO Y PLANES ATENUANTES) - ELEMENTOS DE PROTECCIÓN PERSONAL]] -> Eliminación del riesgo:NingunaSustitución del riesgo; NingunaControles de Ingenieria; Sistemas de seguridad del Vehículo (cinturón de seguridad, airbags, apoya cabezas, llantas) Controles administrativos; Continuar con los controles implemetados: *Seguimiento cumplimiento del PESV * Evaluación de desempeño de cotratistas Controles de EPP; Ver matriz de EPP | AH26: HS Parex Contratista | AI26: 2 Moderado | AJ26: Personas | AK26: 2 Improbable | AL26: =INDEX($AS$3:$AV$6,MATCH($AI26,$AR$3:$AR$6,FALSE),MATCH($AK26,$AS$7:$AV$7,FALSE)) -> 4 | AM26: =IF(año24[[#This Row],[VALORACION DEL RIESGO RESULTANTE CON CONTROLES (Riesgo residual) - Nivel de riesgo]]<=3,"Bajo",IF(año24[[#This Row],[VALORACION DEL RIESGO RESULTANTE CON CONTROLES (Riesgo residual) - Nivel de riesgo]]<=6,"Medio",IF(año24[[#This Row],[VALORACION DEL RIESGO RESULTANTE CON CONTROLES (Riesgo residual) - Nivel de riesgo]]<=12,"Alto","Extremo"))) -> Medio | AO26: =IF(AL26<=4,"SI",IF(AL26>=5,"NO")) -> SI | AP26: ="El nivel del riesgo es"&" "&año24[[#This Row],[VALORACION DEL RIESGO RESULTANTE CON CONTROLES (Riesgo residual) - INTERPRETACIÓN DEL RIESGO]]&" siendo las principales consecuencias las siguientes; "&año24[[#This Row],[Consecuencias (AT/EL)]] -> El nivel del riesgo es Medio siendo las principales consecuencias las siguientes; AT | AQ26: =_xlfn.XLOOKUP(año24[[#This Row],[VALORACION DEL RIESGO RESULTANTE CON CONTROLES (Riesgo residual) - INTERPRETACIÓN DEL RIESGO]], Nivel[Calsificación], Nivel[Imagen]) -> #VALUE!
B27: 18 | C27: 2024 | D27: Campos Parex | E27: MOVILIZACIÓN Y DESMOVILIZACIÓN | F27: Movilización de equipo y campamento: Traslado terrestre de equipo, partes y campamento a locación. Ubicación del equipo en la locación (Ubicación de unidad básica, instalación de tanques, instalación de la mesa, anclaje vientos, instalación de choke manifold, instalación del acumulador, ubicación de casetas, ubicación de extintores y señalización ) | G27: Ruta de Movilización y Nueva locación | H27: Características del grupo social de trabajo (Relaciones, cohesión, calidad de interacciones, trabajo en equipo) Jornadas de trabajo (pausas, trabajo nocturno, rotación, horas extras, descanso) | I27: Psicosocial | J27: =_xlfn.XLOOKUP(año24[[#This Row],[PELIGRO -Tipo]], Tabla12[Calsificación], Tabla12[Imagen]) -> #VALUE! | K27: 4.4 Características del grupo social de trabajo | L27: EL | M27: Rutinaria | N27: Interna | O27: 2 | P27: 68 | Q27: 2 | R27: 8 | S27: Contratistas | T27: Organización del trabajo Definición de manuales de funciones y cargos | U27: Política de prevención de acoso laboral Comité de convivencia laboral | V27: *Aplicación de baterías de riesgo psicosocial * Capacitación en riesgo psicosocial * PVE de Riesgo Psicosocial | W27: 2 Moderado | X27: Personas | Y27: 2 Improbable | Z27: =INDEX($AS$3:$AV$6,MATCH($W27,$AR$3:$AR$6,FALSE),MATCH($Y27,AS$7:$AV$7,FALSE)) -> 4 | AA27: Si (Ver matriz de requisitos legales) | AB27: Ninguna | AC27: Ninguna | AD27: Ninguna | AE27: Continuidad en la aplicación de los controles: * Seguimiento a los planes de intervención del PVE de riesgo psicosocial * Pausas activas | AF27: Ninguna | AG27: ="Eliminación del riesgo:"&año24[[#This Row],[CONTROLES (TRATAMIENTO DEL RIESGO Y PLANES ATENUANTES) - ELIMINACIÓN]]&"Sustitución del riesgo; "&año24[[#This Row],[CONTROLES (TRATAMIENTO DEL RIESGO Y PLANES ATENUANTES) - SUSTITUCIÓN]]&"Controles de Ingenieria; "&año24[[#This Row],[CONTROLES (TRATAMIENTO DEL RIESGO Y PLANES ATENUANTES) - CONTROLES DE INGENIERIA]]&" Controles administrativos; "&año24[[#This Row],[CONTROLES (TRATAMIENTO DEL RIESGO Y PLANES ATENUANTES) - CONTROLES ADMINISTRATIVOS / SEÑALIZACIÓN]]&"Controles de EPP; "&año24[[#This Row],[CONTROLES (TRATAMIENTO DEL RIESGO Y PLANES ATENUANTES) - ELEMENTOS DE PROTECCIÓN PERSONAL]] -> Eliminación del riesgo:NingunaSustitución del riesgo; NingunaControles de Ingenieria; Ninguna Controles administrativos; Continuidad en la aplicación de los controles: * Seguimiento a los planes de intervención del PVE de riesgo psicosocial * Pausas activas Controles de EPP; Ninguna | AH27: HS Parex Contratista | AI27: 1 Menor | AJ27: Personas | AK27: 2 Improbable | AL27: =INDEX($AS$3:$AV$6,MATCH($AI27,$AR$3:$AR$6,FALSE),MATCH($AK27,$AS$7:$AV$7,FALSE)) -> 2 | AM27: =IF(año24[[#This Row],[VALORACION DEL RIESGO RESULTANTE CON CONTROLES (Riesgo residual) - Nivel de riesgo]]<=3,"Bajo",IF(año24[[#This Row],[VALORACION DEL RIESGO RESULTANTE CON CONTROLES (Riesgo residual) - Nivel de riesgo]]<=6,"Medio",IF(año24[[#This Row],[VALORACION DEL RIESGO RESULTANTE CON CONTROLES (Riesgo residual) - Nivel de riesgo]]<=12,"Alto","Extremo"))) -> Bajo | AO27: =IF(AL27<=4,"SI",IF(AL27>=5,"NO")) -> SI | AP27: ="El nivel del riesgo es"&" "&año24[[#This Row],[VALORACION DEL RIESGO RESULTANTE CON CONTROLES (Riesgo residual) - INTERPRETACIÓN DEL RIESGO]]&" siendo las principales consecuencias las siguientes; "&año24[[#This Row],[Consecuencias (AT/EL)]] -> El nivel del riesgo es Bajo siendo las principales consecuencias las siguientes; EL | AQ27: =_xlfn.XLOOKUP(año24[[#This Row],[VALORACION DEL RIESGO RESULTANTE CON CONTROLES (Riesgo residual) - INTERPRETACIÓN DEL RIESGO]], Nivel[Calsificación], Nivel[Imagen]) -> #VALUE!
B28: 19 | C28: 2024 | D28: Campos Parex | E28: MOVILIZACIÓN Y DESMOVILIZACIÓN | F28: Movilización de equipo y campamento: Traslado terrestre de equipo, partes y campamento a locación. Ubicación del equipo en la locación (Ubicación de unidad básica, instalación de tanques, instalación de la mesa, anclaje vientos, instalación de choke manifold, instalación del acumulador, ubicación de casetas, ubicación de extintores y señalización ) | G28: Ruta de Movilización y Nueva locación | H28: Condiciones de la tarea (carga mental, demandas emocionales, sistemas de control, etc.) | I28: Psicosocial | J28: =_xlfn.XLOOKUP(año24[[#This Row],[PELIGRO -Tipo]], Tabla12[Calsificación], Tabla12[Imagen]) -> #VALUE! | K28: 4.3 Condiciones de la tarea | L28: EL | M28: Rutinaria | N28: Interna | O28: 2 | P28: 68 | Q28: 2 | R28: 8 | S28: Contratistas | T28: Organización del trabajo Definición de manuales de funciones y cargos | U28: Política de prevención de acoso laboral Comité de convivencia laboral | V28: *Aplicación de baterías de riesgo psicosocial * Capacitación en riesgo psicosocial * PVE de Riesgo Psicosocial | W28: 2 Moderado | X28: Personas | Y28: 2 Improbable | Z28: =INDEX($AS$3:$AV$6,MATCH($W28,$AR$3:$AR$6,FALSE),MATCH($Y28,AS$7:$AV$7,FALSE)) -> 4 | AA28: Si (Ver matriz de requisitos legales) | AB28: Ninguna | AC28: Ninguna | AD28: Ninguna | AE28: Continuidad en la aplicación de los controles: * Seguimiento a los planes de intervención del PVE de riesgo psicosocial * Pausas activas | AF28: Ninguna | AG28: ="Eliminación del riesgo:"&año24[[#This Row],[CONTROLES (TRATAMIENTO DEL RIESGO Y PLANES ATENUANTES) - ELIMINACIÓN]]&"Sustitución del riesgo; "&año24[[#This Row],[CONTROLES (TRATAMIENTO DEL RIESGO Y PLANES ATENUANTES) - SUSTITUCIÓN]]&"Controles de Ingenieria; "&año24[[#This Row],[CONTROLES (TRATAMIENTO DEL RIESGO Y PLANES ATENUANTES) - CONTROLES DE INGENIERIA]]&" Controles administrativos; "&año24[[#This Row],[CONTROLES (TRATAMIENTO DEL RIESGO Y PLANES ATENUANTES) - CONTROLES ADMINISTRATIVOS / SEÑALIZACIÓN]]&"Controles de EPP; "&año24[[#This Row],[CONTROLES (TRATAMIENTO DEL RIESGO Y PLANES ATENUANTES) - ELEMENTOS DE PROTECCIÓN PERSONAL]] -> Eliminación del riesgo:NingunaSustitución del riesgo; NingunaControles de Ingenieria; Ninguna Controles administrativos; Continuidad en la aplicación de los controles: * Seguimiento a los planes de intervención del PVE de riesgo psicosocial * Pausas activas Controles de EPP; Ninguna | AH28: HS Parex Contratista | AI28: 1 Menor | AJ28: Personas | AK28: 2 Improbable | AL28: =INDEX($AS$3:$AV$6,MATCH($AI28,$AR$3:$AR$6,FALSE),MATCH($AK28,$AS$7:$AV$7,FALSE)) -> 2 | AM28: =IF(año24[[#This Row],[VALORACION DEL RIESGO RESULTANTE CON CONTROLES (Riesgo residual) - Nivel de riesgo]]<=3,"Bajo",IF(año24[[#This Row],[VALORACION DEL RIESGO RESULTANTE CON CONTROLES (Riesgo residual) - Nivel de riesgo]]<=6,"Medio",IF(año24[[#This Row],[VALORACION DEL RIESGO RESULTANTE CON CONTROLES (Riesgo residual) - Nivel de riesgo]]<=12,"Alto","Extremo"))) -> Bajo | AO28: =IF(AL28<=4,"SI",IF(AL28>=5,"NO")) -> SI | AP28: ="El nivel del riesgo es"&" "&año24[[#This Row],[VALORACION DEL RIESGO RESULTANTE CON CONTROLES (Riesgo residual) - INTERPRETACIÓN DEL RIESGO]]&" siendo las principales consecuencias las siguientes; "&año24[[#This Row],[Consecuencias (AT/EL)]] -> El nivel del riesgo es Bajo siendo las principales consecuencias las siguientes; EL | AQ28: =_xlfn.XLOOKUP(año24[[#This Row],[VALORACION DEL RIESGO RESULTANTE CON CONTROLES (Riesgo residual) - INTERPRETACIÓN DEL RIESGO]], Nivel[Calsificación], Nivel[Imagen]) -> #VALUE!
B29: 20 | C29: 2024 | D29: Campos Parex | E29: MOVILIZACIÓN Y DESMOVILIZACIÓN | F29: Movilización de equipo y campamento: Traslado terrestre de equipo, partes y campamento a locación. Ubicación del equipo en la locación (Ubicación de unidad básica, instalación de tanques, instalación de la mesa, anclaje vientos, instalación de choke manifold, instalación del acumulador, ubicación de casetas, ubicación de extintores y señalización ) | G29: Ruta de Movilización y Nueva locación | H29: Jornadas de trabajo (pausas, trabajo nocturno, rotación, horas extras, descanso) | I29: Psicosocial | J29: =_xlfn.XLOOKUP(año24[[#This Row],[PELIGRO -Tipo]], Tabla12[Calsificación], Tabla12[Imagen]) -> #VALUE! | K29: 4.6 Jornada de trabajo | L29: EL | M29: Rutinaria | N29: Interna | O29: 2 | P29: 68 | Q29: 2 | R29: 8 | S29: Contratistas | T29: Organización del trabajo Definición de manuales de funciones y cargos | U29: Política de prevención de acoso laboral Comité de convivencia laboral | V29: *Aplicación de baterías de riesgo psicosocial * Capacitación en riesgo psicosocial * PVE de Riesgo Psicosocial | W29: 2 Moderado | X29: Personas | Y29: 2 Improbable | Z29: =INDEX($AS$3:$AV$6,MATCH($W29,$AR$3:$AR$6,FALSE),MATCH($Y29,AS$7:$AV$7,FALSE)) -> 4 | AA29: Si (Ver matriz de requisitos legales) | AB29: Ninguna | AC29: Ninguna | AD29: Ninguna | AE29: Continuidad en la aplicación de los controles: * Seguimiento a los planes de intervención del PVE de riesgo psicosocial * Pausas activas | AF29: Ninguna | AG29: ="Eliminación del riesgo:"&año24[[#This Row],[CONTROLES (TRATAMIENTO DEL RIESGO Y PLANES ATENUANTES) - ELIMINACIÓN]]&"Sustitución del riesgo; "&año24[[#This Row],[CONTROLES (TRATAMIENTO DEL RIESGO Y PLANES ATENUANTES) - SUSTITUCIÓN]]&"Controles de Ingenieria; "&año24[[#This Row],[CONTROLES (TRATAMIENTO DEL RIESGO Y PLANES ATENUANTES) - CONTROLES DE INGENIERIA]]&" Controles administrativos; "&año24[[#This Row],[CONTROLES (TRATAMIENTO DEL RIESGO Y PLANES ATENUANTES) - CONTROLES ADMINISTRATIVOS / SEÑALIZACIÓN]]&"Controles de EPP; "&año24[[#This Row],[CONTROLES (TRATAMIENTO DEL RIESGO Y PLANES ATENUANTES) - ELEMENTOS DE PROTECCIÓN PERSONAL]] -> Eliminación del riesgo:NingunaSustitución del riesgo; NingunaControles de Ingenieria; Ninguna Controles administrativos; Continuidad en la aplicación de los controles: * Seguimiento a los planes de intervención del PVE de riesgo psicosocial * Pausas activas Controles de EPP; Ninguna | AH29: HS Parex Contratista | AI29: 1 Menor | AJ29: Personas | AK29: 2 Improbable | AL29: =INDEX($AS$3:$AV$6,MATCH($AI29,$AR$3:$AR$6,FALSE),MATCH($AK29,$AS$7:$AV$7,FALSE)) -> 2 | AM29: =IF(año24[[#This Row],[VALORACION DEL RIESGO RESULTANTE CON CONTROLES (Riesgo residual) - Nivel de riesgo]]<=3,"Bajo",IF(año24[[#This Row],[VALORACION DEL RIESGO RESULTANTE CON CONTROLES (Riesgo residual) - Nivel de riesgo]]<=6,"Medio",IF(año24[[#This Row],[VALORACION DEL RIESGO RESULTANTE CON CONTROLES (Riesgo residual) - Nivel de riesgo]]<=12,"Alto","Extremo"))) -> Bajo | AO29: =IF(AL29<=4,"SI",IF(AL29>=5,"NO")) -> SI | AP29: ="El nivel del riesgo es"&" "&año24[[#This Row],[VALORACION DEL RIESGO RESULTANTE CON CONTROLES (Riesgo residual) - INTERPRETACIÓN DEL RIESGO]]&" siendo las principales consecuencias las siguientes; "&año24[[#This Row],[Consecuencias (AT/EL)]] -> El nivel del riesgo es Bajo siendo las principales consecuencias las siguientes; EL | AQ29: =_xlfn.XLOOKUP(año24[[#This Row],[VALORACION DEL RIESGO RESULTANTE CON CONTROLES (Riesgo residual) - INTERPRETACIÓN DEL RIESGO]], Nivel[Calsificación], Nivel[Imagen]) -> #VALUE!
B30: 21 | C30: 2024 | D30: Campos Parex | E30: MOVILIZACIÓN Y DESMOVILIZACIÓN | F30: Movilización de equipo y campamento: Traslado terrestre de equipo, partes y campamento a locación. Ubicación del equipo en la locación (Ubicación de unidad básica, instalación de tanques, instalación de la mesa, anclaje vientos, instalación de choke manifold, instalación del acumulador, ubicación de casetas, ubicación de extintores y señalización ) | G30: Ruta de Movilización y Nueva locación | H30: Actos y comportamientos inseguros, por no cumplir políticas, estándares y procedimietos de trabajo | I30: Psicosocial | J30: =_xlfn.XLOOKUP(año24[[#This Row],[PELIGRO -Tipo]], Tabla12[Calsificación], Tabla12[Imagen]) -> #VALUE! | K30: 4.2 Características de la organización del trabajo | L30: EL | M30: Rutinaria | N30: Interna | O30: 2 | P30: 68 | Q30: 2 | R30: 8 | S30: Contratistas | T30: Organización del trabajo Definición de manuales de funciones y cargos | U30: Política de prevención de acoso laboral Comité de convivencia laboral | V30: *Aplicación de baterías de riesgo psicosocial * Capacitación en riesgo psicosocial * PVE de Riesgo Psicosocial | W30: 2 Moderado | X30: Personas | Y30: 2 Improbable | Z30: =INDEX($AS$3:$AV$6,MATCH($W30,$AR$3:$AR$6,FALSE),MATCH($Y30,AS$7:$AV$7,FALSE)) -> 4 | AA30: Si (Ver matriz de requisitos legales) | AB30: Ninguna | AC30: Ninguna | AD30: Ninguna | AE30: Continuidad en la aplicación de los controles: * Seguimiento a los planes de intervención del PVE de riesgo psicosocial * Pausas activas | AF30: Ninguna | AG30: ="Eliminación del riesgo:"&año24[[#This Row],[CONTROLES (TRATAMIENTO DEL RIESGO Y PLANES ATENUANTES) - ELIMINACIÓN]]&"Sustitución del riesgo; "&año24[[#This Row],[CONTROLES (TRATAMIENTO DEL RIESGO Y PLANES ATENUANTES) - SUSTITUCIÓN]]&"Controles de Ingenieria; "&año24[[#This Row],[CONTROLES (TRATAMIENTO DEL RIESGO Y PLANES ATENUANTES) - CONTROLES DE INGENIERIA]]&" Controles administrativos; "&año24[[#This Row],[CONTROLES (TRATAMIENTO DEL RIESGO Y PLANES ATENUANTES) - CONTROLES ADMINISTRATIVOS / SEÑALIZACIÓN]]&"Controles de EPP; "&año24[[#This Row],[CONTROLES (TRATAMIENTO DEL RIESGO Y PLANES ATENUANTES) - ELEMENTOS DE PROTECCIÓN PERSONAL]] -> Eliminación del riesgo:NingunaSustitución del riesgo; NingunaControles de Ingenieria; Ninguna Controles administrativos; Continuidad en la aplicación de los controles: * Seguimiento a los planes de intervención del PVE de riesgo psicosocial * Pausas activas Controles de EPP; Ninguna | AH30: HS Parex Contratista | AI30: 1 Menor | AJ30: Personas | AK30: 2 Improbable | AL30: =INDEX($AS$3:$AV$6,MATCH($AI30,$AR$3:$AR$6,FALSE),MATCH($AK30,$AS$7:$AV$7,FALSE)) -> 2 | AM30: =IF(año24[[#This Row],[VALORACION DEL RIESGO RESULTANTE CON CONTROLES (Riesgo residual) - Nivel de riesgo]]<=3,"Bajo",IF(año24[[#This Row],[VALORACION DEL RIESGO RESULTANTE CON CONTROLES (Riesgo residual) - Nivel de riesgo]]<=6,"Medio",IF(año24[[#This Row],[VALORACION DEL RIESGO RESULTANTE CON CONTROLES (Riesgo residual) - Nivel de riesgo]]<=12,"Alto","Extremo"))) -> Bajo | AO30: =IF(AL30<=4,"SI",IF(AL30>=5,"NO")) -> SI | AP30: ="El nivel del riesgo es"&" "&año24[[#This Row],[VALORACION DEL RIESGO RESULTANTE CON CONTROLES (Riesgo residual) - INTERPRETACIÓN DEL RIESGO]]&" siendo las principales consecuencias las siguientes; "&año24[[#This Row],[Consecuencias (AT/EL)]] -> El nivel del riesgo es Bajo siendo las principales consecuencias las siguientes; EL | AQ30: =_xlfn.XLOOKUP(año24[[#This Row],[VALORACION DEL RIESGO RESULTANTE CON CONTROLES (Riesgo residual) - INTERPRETACIÓN DEL RIESGO]], Nivel[Calsificación], Nivel[Imagen]) -> #VALUE!
B31: 22 | C31: 2024 | D31: Campos Parex | E31: MOVILIZACIÓN Y DESMOVILIZACIÓN | F31: Movilización de equipo y campamento: Traslado terrestre de equipo, partes y campamento a locación. Ubicación del equipo en la locación (Ubicación de unidad básica, instalación de tanques, instalación de la mesa, anclaje vientos, instalación de choke manifold, instalación del acumulador, ubicación de casetas, ubicación de extintores y señalización ) | G31: Ruta de Movilización y Nueva locación | H31: Incendio provocado por el vuelco de la carga. | I31: Condiciones_de_seguridad | J31: =_xlfn.XLOOKUP(año24[[#This Row],[PELIGRO -Tipo]], Tabla12[Calsificación], Tabla12[Imagen]) -> #VALUE! | K31: 6.4 Tecnológico | L31: AT | M31: Rutinaria | N31: Interna | O31: 2 | P31: 68 | Q31: 2 | R31: 8 | S31: Contratistas | T31: Programa de mantenimiento de equipos y herramientas | U31: Disponibilidad de extintores Monitoreo de gases Inspección preoperacional de equipos y herramientas | V31: Uso de EPP Capacitación en Manejo de extintores y control de incendios Capacitación brigadistas | W31: 4 Crítico | X31: Personas | Y31: 2 Improbable | Z31: =INDEX($AS$3:$AV$6,MATCH($W31,$AR$3:$AR$6,FALSE),MATCH($Y31,AS$7:$AV$7,FALSE)) -> 8 | AA31: Si (Ver matriz de requisitos legales) | AB31: Ninguna | AC31: Ninguna | AD31: Ninguna | AE31: * Procedimiento de manejo seguro de sustancias químicas * Programa de Gestión Seguridad Basada en el Comportamiento * Procedimiento Sistema Permisos de Trabajo * Anexo HSEQ para contratistas * Plan de emergencias * Uso de herramienta antichispas en áreas calisificadas clase 1 división 1 y 2 | AF31: Ver matriz de EPP | AG31: ="Eliminación del riesgo:"&año24[[#This Row],[CONTROLES (TRATAMIENTO DEL RIESGO Y PLANES ATENUANTES) - ELIMINACIÓN]]&"Sustitución del riesgo; "&año24[[#This Row],[CONTROLES (TRATAMIENTO DEL RIESGO Y PLANES ATENUANTES) - SUSTITUCIÓN]]&"Controles de Ingenieria; "&año24[[#This Row],[CONTROLES (TRATAMIENTO DEL RIESGO Y PLANES ATENUANTES) - CONTROLES DE INGENIERIA]]&" Controles administrativos; "&año24[[#This Row],[CONTROLES (TRATAMIENTO DEL RIESGO Y PLANES ATENUANTES) - CONTROLES ADMINISTRATIVOS / SEÑALIZACIÓN]]&"Controles de EPP; "&año24[[#This Row],[CONTROLES (TRATAMIENTO DEL RIESGO Y PLANES ATENUANTES) - ELEMENTOS DE PROTECCIÓN PERSONAL]] -> Eliminación del riesgo:NingunaSustitución del riesgo; NingunaControles de Ingenieria; Ninguna Controles administrativos; * Procedimiento de manejo seguro de sustancias químicas * Programa de Gestión Seguridad Basada en el Comportamiento * Procedimiento Sistema Permisos de Trabajo * Anexo HSEQ para contratistas * Plan de emergencias * Uso de herramienta antichispas en áreas calisificadas clase 1 división 1 y 2Controles de EPP; Ver matriz de EPP | AH31: HS Parex Contratista | AI31: 4 Crítico | AJ31: Personas | AK31: 1 Remoto | AL31: =INDEX($AS$3:$AV$6,MATCH($AI31,$AR$3:$AR$6,FALSE),MATCH($AK31,$AS$7:$AV$7,FALSE)) -> 4 | AM31: =IF(año24[[#This Row],[VALORACION DEL RIESGO RESULTANTE CON CONTROLES (Riesgo residual) - Nivel de riesgo]]<=3,"Bajo",IF(año24[[#This Row],[VALORACION DEL RIESGO RESULTANTE CON CONTROLES (Riesgo residual) - Nivel de riesgo]]<=6,"Medio",IF(año24[[#This Row],[VALORACION DEL RIESGO RESULTANTE CON CONTROLES (Riesgo residual) - Nivel de riesgo]]<=12,"Alto","Extremo"))) -> Medio | AO31: =IF(AL31<=4,"SI",IF(AL31>=5,"NO")) -> SI | AP31: ="El nivel del riesgo es"&" "&año24[[#This Row],[VALORACION DEL RIESGO RESULTANTE CON CONTROLES (Riesgo residual) - INTERPRETACIÓN DEL RIESGO]]&" siendo las principales consecuencias las siguientes; "&año24[[#This Row],[Consecuencias (AT/EL)]] -> El nivel del riesgo es Medio siendo las principales consecuencias las siguientes; AT | AQ31: =_xlfn.XLOOKUP(año24[[#This Row],[VALORACION DEL RIESGO RESULTANTE CON CONTROLES (Riesgo residual) - INTERPRETACIÓN DEL RIESGO]], Nivel[Calsificación], Nivel[Imagen]) -> #VALUE!
B32: 23 | C32: 2024 | D32: Campos Parex | E32: MOVILIZACIÓN Y DESMOVILIZACIÓN | F32: Movilización de equipo y campamento: Traslado terrestre de equipo, partes y campamento a locación. Ubicación del equipo en la locación (Ubicación de unidad básica, instalación de tanques, instalación de la mesa, anclaje vientos, instalación de choke manifold, instalación del acumulador, ubicación de casetas, ubicación de extintores y señalización ) | G32: Ruta de Movilización y Nueva locación | H32: Ignición incontrolada de agentes químicos inflamables por condiciones presentes en el lugar de trabajo | I32: Condiciones_de_seguridad | J32: =_xlfn.XLOOKUP(año24[[#This Row],[PELIGRO -Tipo]], Tabla12[Calsificación], Tabla12[Imagen]) -> #VALUE! | K32: 6.4 Tecnológico | L32: AT | M32: Rutinaria | N32: Interna | O32: 2 | P32: 68 | Q32: 2 | R32: 8 | S32: Contratistas | T32: Programa de mantenimiento de equipos y herramientas | U32: Disponibilidad de extintores Monitoreo de gases Inspección preoperacional de equipos y herramientas | V32: Uso de EPP Capacitación en Manejo de extintores y control de incendios Capacitación brigadistas | W32: 4 Crítico | X32: Personas | Y32: 2 Improbable | Z32: =INDEX($AS$3:$AV$6,MATCH($W32,$AR$3:$AR$6,FALSE),MATCH($Y32,AS$7:$AV$7,FALSE)) -> 8 | AA32: Si (Ver matriz de requisitos legales) | AB32: Ninguna | AC32: Ninguna | AD32: Ninguna | AE32: * Procedimiento de manejo seguro de sustancias químicas * Programa de Gestión Seguridad Basada en el Comportamiento * Procedimiento Sistema Permisos de Trabajo * Anexo HSEQ para contratistas * Plan de emergencias * Uso de herramienta antichispas en áreas calisificadas clase 1 división 1 y 2 | AF32: Ver matriz de EPP | AG32: ="Eliminación del riesgo:"&año24[[#This Row],[CONTROLES (TRATAMIENTO DEL RIESGO Y PLANES ATENUANTES) - ELIMINACIÓN]]&"Sustitución del riesgo; "&año24[[#This Row],[CONTROLES (TRATAMIENTO DEL RIESGO Y PLANES ATENUANTES) - SUSTITUCIÓN]]&"Controles de Ingenieria; "&año24[[#This Row],[CONTROLES (TRATAMIENTO DEL RIESGO Y PLANES ATENUANTES) - CONTROLES DE INGENIERIA]]&" Controles administrativos; "&año24[[#This Row],[CONTROLES (TRATAMIENTO DEL RIESGO Y PLANES ATENUANTES) - CONTROLES ADMINISTRATIVOS / SEÑALIZACIÓN]]&"Controles de EPP; "&año24[[#This Row],[CONTROLES (TRATAMIENTO DEL RIESGO Y PLANES ATENUANTES) - ELEMENTOS DE PROTECCIÓN PERSONAL]] -> Eliminación del riesgo:NingunaSustitución del riesgo; NingunaControles de Ingenieria; Ninguna Controles administrativos; * Procedimiento de manejo seguro de sustancias químicas * Programa de Gestión Seguridad Basada en el Comportamiento * Procedimiento Sistema Permisos de Trabajo * Anexo HSEQ para contratistas * Plan de emergencias * Uso de herramienta antichispas en áreas calisificadas clase 1 división 1 y 2Controles de EPP; Ver matriz de EPP | AH32: HS Parex Contratista | AI32: 4 Crítico | AJ32: Personas | AK32: 1 Remoto | AL32: =INDEX($AS$3:$AV$6,MATCH($AI32,$AR$3:$AR$6,FALSE),MATCH($AK32,$AS$7:$AV$7,FALSE)) -> 4 | AM32: =IF(año24[[#This Row],[VALORACION DEL RIESGO RESULTANTE CON CONTROLES (Riesgo residual) - Nivel de riesgo]]<=3,"Bajo",IF(año24[[#This Row],[VALORACION DEL RIESGO RESULTANTE CON CONTROLES (Riesgo residual) - Nivel de riesgo]]<=6,"Medio",IF(año24[[#This Row],[VALORACION DEL RIESGO RESULTANTE CON CONTROLES (Riesgo residual) - Nivel de riesgo]]<=12,"Alto","Extremo"))) -> Medio | AO32: =IF(AL32<=4,"SI",IF(AL32>=5,"NO")) -> SI | AP32: ="El nivel del riesgo es"&" "&año24[[#This Row],[VALORACION DEL RIESGO RESULTANTE CON CONTROLES (Riesgo residual) - INTERPRETACIÓN DEL RIESGO]]&" siendo las principales consecuencias las siguientes; "&año24[[#This Row],[Consecuencias (AT/EL)]] -> El nivel del riesgo es Medio siendo las principales consecuencias las siguientes; AT | AQ32: =_xlfn.XLOOKUP(año24[[#This Row],[VALORACION DEL RIESGO RESULTANTE CON CONTROLES (Riesgo residual) - INTERPRETACIÓN DEL RIESGO]], Nivel[Calsificación], Nivel[Imagen]) -> #VALUE!
... B35: 26 | C35: 2024 | D35: Campos Parex | E35: MOVILIZACIÓN Y DESMOVILIZACIÓN | F35: Movilización de equipo y campamento: Traslado terrestre de equipo, partes y campamento a locación. Ubicación del equipo en la locación (Ubicación de unidad básica, instalación de tanques, instalación de la mesa, anclaje vientos, instalación de choke manifold, instalación del acumulador, ubicación de casetas, ubicación de extintores y señalización ) | G35: Ruta de Movilización y Nueva locación | H35: Desordenes musculo esqueléticos ocasionados al conductor durante la movilización debido a posturas sedente | I35: Biomecánicas | J35: =_xlfn.XLOOKUP(año24[[#This Row],[PELIGRO -Tipo]], Tabla12[Calsificación], Tabla12[Imagen]) -> #VALUE! | K35: 5.1 Postura | L35: EL | M35: Rutinaria | N35: Interna | O35: 2 | P35: 68 | Q35: 2 | R35: 8 | S35: Contratistas | T35: Identificación de Peso de carga Ayudas mecánica (diferenciales, minicargador, cargador, brazo grua, grúas, carretillas, etc.) | U35: Estudio de puestos de trabajo | V35: Exámen médico ocupacional con enfásis osteomuscular PVE Lesiones osteomusculares Capacitación en Higiene postural y manejo de cargas | W35: 3 Serio | X35: Personas | Y35: 2 Improbable | Z35: =INDEX($AS$3:$AV$6,MATCH($W35,$AR$3:$AR$6,FALSE),MATCH($Y35,AS$7:$AV$7,FALSE)) -> 6 | AA35: Si (Ver matriz de requisitos legales) | AB35: Ninguna | AC35: Ninguna | AD35: Ninguna | AE35: * Programa de Gestión Seguridad Basada en el Comportamiento * Sequimiento Programa de Vigilancia Epidemiológica condiciones ergonómicas inadecuadas y Desórdenes Músculo Esqueléticos * Anexo HSEQ para contratistas | AF35: Ver matriz de EPP | AG35: ="Eliminación del riesgo:"&año24[[#This Row],[CONTROLES (TRATAMIENTO DEL RIESGO Y PLANES ATENUANTES) - ELIMINACIÓN]]&"Sustitución del riesgo; "&año24[[#This Row],[CONTROLES (TRATAMIENTO DEL RIESGO Y PLANES ATENUANTES) - SUSTITUCIÓN]]&"Controles de Ingenieria; "&año24[[#This Row],[CONTROLES (TRATAMIENTO DEL RIESGO Y PLANES ATENUANTES) - CONTROLES DE INGENIERIA]]&" Controles administrativos; "&año24[[#This Row],[CONTROLES (TRATAMIENTO DEL RIESGO Y PLANES ATENUANTES) - CONTROLES ADMINISTRATIVOS / SEÑALIZACIÓN]]&"Controles de EPP; "&año24[[#This Row],[CONTROLES (TRATAMIENTO DEL RIESGO Y PLANES ATENUANTES) - ELEMENTOS DE PROTECCIÓN PERSONAL]] -> Eliminación del riesgo:NingunaSustitución del riesgo; NingunaControles de Ingenieria; Ninguna Controles administrativos; * Programa de Gestión Seguridad Basada en el Comportamiento * Sequimiento Programa de Vigilancia Epidemiológica condiciones ergonómicas inadecuadas y Desórdenes Músculo Esqueléticos * Anexo HSEQ para contratistas Controles de EPP; Ver matriz de EPP | AH35: HS Parex Contratista | AI35: 2 Moderado | AJ35: Personas | AK35: 2 Improbable | AL35: =INDEX($AS$3:$AV$6,MATCH($AI35,$AR$3:$AR$6,FALSE),MATCH($AK35,$AS$7:$AV$7,FALSE)) -> 4 | AM35: =IF(año24[[#This Row],[VALORACION DEL RIESGO RESULTANTE CON CONTROLES (Riesgo residual) - Nivel de riesgo]]<=3,"Bajo",IF(año24[[#This Row],[VALORACION DEL RIESGO RESULTANTE CON CONTROLES (Riesgo residual) - Nivel de riesgo]]<=6,"Medio",IF(año24[[#This Row],[VALORACION DEL RIESGO RESULTANTE CON CONTROLES (Riesgo residual) - Nivel de riesgo]]<=12,"Alto","Extremo"))) -> Medio | AO35: =IF(AL35<=4,"SI",IF(AL35>=5,"NO")) -> SI | AP35: ="El nivel del riesgo es"&" "&año24[[#This Row],[VALORACION DEL RIESGO RESULTANTE CON CONTROLES (Riesgo residual) - INTERPRETACIÓN DEL RIESGO]]&" siendo las principales consecuencias las siguientes; "&año24[[#This Row],[Consecuencias (AT/EL)]] -> El nivel del riesgo es Medio siendo las principales consecuencias las siguientes; EL | AQ35: =_xlfn.XLOOKUP(año24[[#This Row],[VALORACION DEL RIESGO RESULTANTE CON CONTROLES (Riesgo residual) - INTERPRETACIÓN DEL RIESGO]], Nivel[Calsificación], Nivel[Imagen]) -> #VALUE!
B36: 27 | C36: 2024 | D36: Campos Parex | E36: MOVILIZACIÓN Y DESMOVILIZACIÓN | F36: Movilización de equipo y campamento: Traslado terrestre de equipo, partes y campamento a locación. Ubicación del equipo en la locación (Ubicación de unidad básica, instalación de tanques, instalación de la mesa, anclaje vientos, instalación de choke manifold, instalación del acumulador, ubicación de casetas, ubicación de extintores y señalización ) | G36: Ruta de Movilización y Nueva locación | H36: Exposición a agentes biológicos por contacto, transmisión aérea o hídrica | I36: Biológico | J36: =_xlfn.XLOOKUP(año24[[#This Row],[PELIGRO -Tipo]], Tabla12[Calsificación], Tabla12[Imagen]) -> #VALUE! | K36: 1.1 Virus | L36: EL | M36: Rutinaria | N36: Interna | O36: 2 | P36: 68 | Q36: 2 | R36: 8 | S36: Contratistas | V36: EPP Vacunación Charlas de PYP | W36: 2 Moderado | X36: Personas | Y36: 3 Probable | Z36: =INDEX($AS$3:$AV$6,MATCH($W36,$AR$3:$AR$6,FALSE),MATCH($Y36,AS$7:$AV$7,FALSE)) -> 6 | AA36: Si (Ver matriz de requisitos legales) | AB36: Ninguna | AC36: Ninguna | AE36: Programa de capacitacion y entrenamiento Verificacion esquema de vacunacion Instructivo practica seguro en campo exposición a riesgo biológico COL-HSE-IN-018 | AF36: Ver matriz de EPP | AG36: ="Eliminación del riesgo:"&año24[[#This Row],[CONTROLES (TRATAMIENTO DEL RIESGO Y PLANES ATENUANTES) - ELIMINACIÓN]]&"Sustitución del riesgo; "&año24[[#This Row],[CONTROLES (TRATAMIENTO DEL RIESGO Y PLANES ATENUANTES) - SUSTITUCIÓN]]&"Controles de Ingenieria; "&año24[[#This Row],[CONTROLES (TRATAMIENTO DEL RIESGO Y PLANES ATENUANTES) - CONTROLES DE INGENIERIA]]&" Controles administrativos; "&año24[[#This Row],[CONTROLES (TRATAMIENTO DEL RIESGO Y PLANES ATENUANTES) - CONTROLES ADMINISTRATIVOS / SEÑALIZACIÓN]]&"Controles de EPP; "&año24[[#This Row],[CONTROLES (TRATAMIENTO DEL RIESGO Y PLANES ATENUANTES) - ELEMENTOS DE PROTECCIÓN PERSONAL]] -> Eliminación del riesgo:NingunaSustitución del riesgo; NingunaControles de Ingenieria; Controles administrativos; Programa de capacitacion y entrenamiento Verificacion esquema de vacunacion Instructivo practica seguro en campo exposición a riesgo biológico COL-HSE-IN-018Controles de EPP; Ver matriz de EPP | AH36: HS Parex Contratista | AI36: 2 Moderado | AJ36: Personas | AK36: 2 Improbable | AL36: =INDEX($AS$3:$AV$6,MATCH($AI36,$AR$3:$AR$6,FALSE),MATCH($AK36,$AS$7:$AV$7,FALSE)) -> 4 | AM36: =IF(año24[[#This Row],[VALORACION DEL RIESGO RESULTANTE CON CONTROLES (Riesgo residual) - Nivel de riesgo]]<=3,"Bajo",IF(año24[[#This Row],[VALORACION DEL RIESGO RESULTANTE CON CONTROLES (Riesgo residual) - Nivel de riesgo]]<=6,"Medio",IF(año24[[#This Row],[VALORACION DEL RIESGO RESULTANTE CON CONTROLES (Riesgo residual) - Nivel de riesgo]]<=12,"Alto","Extremo"))) -> Medio | AO36: =IF(AL36<=4,"SI",IF(AL36>=5,"NO")) -> SI | AP36: ="El nivel del riesgo es"&" "&año24[[#This Row],[VALORACION DEL RIESGO RESULTANTE CON CONTROLES (Riesgo residual) - INTERPRETACIÓN DEL RIESGO]]&" siendo las principales consecuencias las siguientes; "&año24[[#This Row],[Consecuencias (AT/EL)]] -> El nivel del riesgo es Medio siendo las principales consecuencias las siguientes; EL | AQ36: =_xlfn.XLOOKUP(año24[[#This Row],[VALORACION DEL RIESGO RESULTANTE CON CONTROLES (Riesgo residual) - INTERPRETACIÓN DEL RIESGO]], Nivel[Calsificación], Nivel[Imagen]) -> #VALUE!
B37: 28 | C37: 2024 | D37: Campos Parex | E37: MOVILIZACIÓN Y DESMOVILIZACIÓN | F37: Movilización de equipo y campamento: Traslado terrestre de equipo, partes y campamento a locación. Ubicación del equipo en la locación (Ubicación de unidad básica, instalación de tanques, instalación de la mesa, anclaje vientos, instalación de choke manifold, instalación del acumulador, ubicación de casetas, ubicación de extintores y señalización ) | G37: Ruta de Movilización y Nueva locación | H37: Exposición a Virus, hongos, bacterias por la presencia de animales e insectos (picaduras, mordeduras) y por plantas (toxinas o alergias). | I37: Biológico | J37: =_xlfn.XLOOKUP(año24[[#This Row],[PELIGRO -Tipo]], Tabla12[Calsificación], Tabla12[Imagen]) -> #VALUE! | K37: 1.6 Picaduras | L37: AT | M37: Rutinaria | N37: Interna | O37: 2 | P37: 68 | Q37: 2 | R37: 8 | S37: Contratistas | T37: Ninguna | U37: Inspecciones de seguridad | V37: Esquema de vacunación completo (fiebre amarilla y tétano). Suero anti-ofídico Capacitación en Riesgo Biológico | W37: 2 Moderado | X37: Personas | Y37: 3 Probable | Z37: =INDEX($AS$3:$AV$6,MATCH($W37,$AR$3:$AR$6,FALSE),MATCH($Y37,AS$7:$AV$7,FALSE)) -> 6 | AA37: Si (Ver matriz de requisitos legales) | AB37: Ninguna | AC37: Ninguna | AD37: Ninguna | AE37: Actividades de promoción y prevención riesgos de Salud Pública (fiebre amarilla, dengue y tétano) Capacitar a los trabajadores en riesgo biológico (picaduras, clases de picaduras y tipo de animales que hay presentes en la zona). Campañas para la prevención de riesgos endémicos, socialización de SIVIGILA a la población trabajadora. Poda de la periferia de la locación Mantener controles existentes: Esquema de vacunación completo (fiebre amarilla y tétano). Suero anti-ofídico Capacitación en Riesgo Biológico * Programa de Gestión Seguridad Basada en el Comportamiento | AF37: Ver matriz de EPP | AG37: ="Eliminación del riesgo:"&año24[[#This Row],[CONTROLES (TRATAMIENTO DEL RIESGO Y PLANES ATENUANTES) - ELIMINACIÓN]]&"Sustitución del riesgo; "&año24[[#This Row],[CONTROLES (TRATAMIENTO DEL RIESGO Y PLANES ATENUANTES) - SUSTITUCIÓN]]&"Controles de Ingenieria; "&año24[[#This Row],[CONTROLES (TRATAMIENTO DEL RIESGO Y PLANES ATENUANTES) - CONTROLES DE INGENIERIA]]&" Controles administrativos; "&año24[[#This Row],[CONTROLES (TRATAMIENTO DEL RIESGO Y PLANES ATENUANTES) - CONTROLES ADMINISTRATIVOS / SEÑALIZACIÓN]]&"Controles de EPP; "&año24[[#This Row],[CONTROLES (TRATAMIENTO DEL RIESGO Y PLANES ATENUANTES) - ELEMENTOS DE PROTECCIÓN PERSONAL]] -> Eliminación del riesgo:NingunaSustitución del riesgo; NingunaControles de Ingenieria; Ninguna Controles administrativos; Actividades de promoción y prevención riesgos de Salud Pública (fiebre amarilla, dengue y tétano) Capacitar a los trabajadores en riesgo biológico (picaduras, clases de picaduras y tipo de animales que hay presentes en la zona). Campañas para la prevención de riesgos endémicos, socialización de SIVIGILA a la población trabajadora. Poda de la periferia de la locación Mantener controles existentes: Esquema de vacunación completo (fiebre amarilla y tétano). Suero anti-ofídico Capacitación en Riesgo Biológico * Programa de Gestión Seguridad Basada en el ComportamientoControles de EPP; Ver matriz de EPP | AH37: HS Parex Contratista | AI37: 2 Moderado | AJ37: Personas | AK37: 2 Improbable | AL37: =INDEX($AS$3:$AV$6,MATCH($AI37,$AR$3:$AR$6,FALSE),MATCH($AK37,$AS$7:$AV$7,FALSE)) -> 4 | AM37: =IF(año24[[#This Row],[VALORACION DEL RIESGO RESULTANTE CON CONTROLES (Riesgo residual) - Nivel de riesgo]]<=3,"Bajo",IF(año24[[#This Row],[VALORACION DEL RIESGO RESULTANTE CON CONTROLES (Riesgo residual) - Nivel de riesgo]]<=6,"Medio",IF(año24[[#This Row],[VALORACION DEL RIESGO RESULTANTE CON CONTROLES (Riesgo residual) - Nivel de riesgo]]<=12,"Alto","Extremo"))) -> Medio | AO37: =IF(AL37<=4,"SI",IF(AL37>=5,"NO")) -> SI | AP37: ="El nivel del riesgo es"&" "&año24[[#This Row],[VALORACION DEL RIESGO RESULTANTE CON CONTROLES (Riesgo residual) - INTERPRETACIÓN DEL RIESGO]]&" siendo las principales consecuencias las siguientes; "&año24[[#This Row],[Consecuencias (AT/EL)]] -> El nivel del riesgo es Medio siendo las principales consecuencias las siguientes; AT | AQ37: =_xlfn.XLOOKUP(año24[[#This Row],[VALORACION DEL RIESGO RESULTANTE CON CONTROLES (Riesgo residual) - INTERPRETACIÓN DEL RIESGO]], Nivel[Calsificación], Nivel[Imagen]) -> #VALUE!
B38: 29 | C38: 2024 | D38: Campos Parex | E38: MOVILIZACIÓN Y DESMOVILIZACIÓN | F38: Movilización de equipo y campamento: Traslado terrestre de equipo, partes y campamento a locación. Ubicación del equipo en la locación (Ubicación de unidad básica, instalación de tanques, instalación de la mesa, anclaje vientos, instalación de choke manifold, instalación del acumulador, ubicación de casetas, ubicación de extintores y señalización ) | G38: Ruta de Movilización y Nueva locación | H38: Amedrentación o secuestro por presencia de grupos al margen de la Ley, y bloqueos de la actividad por paros de la comunidad. | I38: Condiciones_de_seguridad | J38: =_xlfn.XLOOKUP(año24[[#This Row],[PELIGRO -Tipo]], Tabla12[Calsificación], Tabla12[Imagen]) -> #VALUE! | K38: 6.6 Públicos | L38: AT | M38: Rutinaria | N38: Externa | O38: 2 | P38: 68 | Q38: 2 | R38: 8 | S38: Contratistas | U38: Sistema de seguridad y vigilancia privada Centro de control Cerramiento de la locación Control de ingreso y salida de visitantes | V38: Charlas Informativas Charlas de seguridad física. | W38: 4 Crítico | X38: Personas | Y38: 2 Improbable | Z38: =INDEX($AS$3:$AV$6,MATCH($W38,$AR$3:$AR$6,FALSE),MATCH($Y38,AS$7:$AV$7,FALSE)) -> 8 | AA38: Si (Ver matriz de requisitos legales) | AB38: Ninguna | AC38: Ninguna | AD38: Ninguna | AE38: * Plan de emergencias * Anexo HSEQ para contratistas * Protocolos de seguridad física * Disponibilidad de equipos de comunicación | AF38: Ninguna | AG38: ="Eliminación del riesgo:"&año24[[#This Row],[CONTROLES (TRATAMIENTO DEL RIESGO Y PLANES ATENUANTES) - ELIMINACIÓN]]&"Sustitución del riesgo; "&año24[[#This Row],[CONTROLES (TRATAMIENTO DEL RIESGO Y PLANES ATENUANTES) - SUSTITUCIÓN]]&"Controles de Ingenieria; "&año24[[#This Row],[CONTROLES (TRATAMIENTO DEL RIESGO Y PLANES ATENUANTES) - CONTROLES DE INGENIERIA]]&" Controles administrativos; "&año24[[#This Row],[CONTROLES (TRATAMIENTO DEL RIESGO Y PLANES ATENUANTES) - CONTROLES ADMINISTRATIVOS / SEÑALIZACIÓN]]&"Controles de EPP; "&año24[[#This Row],[CONTROLES (TRATAMIENTO DEL RIESGO Y PLANES ATENUANTES) - ELEMENTOS DE PROTECCIÓN PERSONAL]] -> Eliminación del riesgo:NingunaSustitución del riesgo; NingunaControles de Ingenieria; Ninguna Controles administrativos; * Plan de emergencias * Anexo HSEQ para contratistas * Protocolos de seguridad física * Disponibilidad de equipos de comunicaciónControles de EPP; Ninguna | AH38: HS Parex Contratista | AI38: 2 Moderado | AJ38: Personas | AK38: 2 Improbable | AL38: =INDEX($AS$3:$AV$6,MATCH($AI38,$AR$3:$AR$6,FALSE),MATCH($AK38,$AS$7:$AV$7,FALSE)) -> 4 | AM38: =IF(año24[[#This Row],[VALORACION DEL RIESGO RESULTANTE CON CONTROLES (Riesgo residual) - Nivel de riesgo]]<=3,"Bajo",IF(año24[[#This Row],[VALORACION DEL RIESGO RESULTANTE CON CONTROLES (Riesgo residual) - Nivel de riesgo]]<=6,"Medio",IF(año24[[#This Row],[VALORACION DEL RIESGO RESULTANTE CON CONTROLES (Riesgo residual) - Nivel de riesgo]]<=12,"Alto","Extremo"))) -> Medio | AO38: =IF(AL38<=4,"SI",IF(AL38>=5,"NO")) -> SI | AP38: ="El nivel del riesgo es"&" "&año24[[#This Row],[VALORACION DEL RIESGO RESULTANTE CON CONTROLES (Riesgo residual) - INTERPRETACIÓN DEL RIESGO]]&" siendo las principales consecuencias las siguientes; "&año24[[#This Row],[Consecuencias (AT/EL)]] -> El nivel del riesgo es Medio siendo las principales consecuencias las siguientes; AT | AQ38: =_xlfn.XLOOKUP(año24[[#This Row],[VALORACION DEL RIESGO RESULTANTE CON CONTROLES (Riesgo residual) - INTERPRETACIÓN DEL RIESGO]], Nivel[Calsificación], Nivel[Imagen]) -> #VALUE!
B39: 30 | C39: 2024 | D39: Campos Parex | E39: MOVILIZACIÓN Y DESMOVILIZACIÓN | F39: Movilización de equipo y campamento: Traslado terrestre de equipo, partes y campamento a locación. Ubicación del equipo en la locación (Ubicación de unidad básica, instalación de tanques, instalación de la mesa, anclaje vientos, instalación de choke manifold, instalación del acumulador, ubicación de casetas, ubicación de extintores y señalización ) | G39: Ruta de Movilización y Nueva locación | H39: Amedrentación o secuestro por presencia de grupos al margen de la Ley, y bloqueos de la actividad por paros de la comunidad. | I39: Condiciones_de_seguridad | J39: =_xlfn.XLOOKUP(año24[[#This Row],[PELIGRO -Tipo]], Tabla12[Calsificación], Tabla12[Imagen]) -> #VALUE! | K39: 6.6 Públicos | L39: AT | M39: Rutinaria | N39: Externa | O39: 2 | P39: 68 | Q39: 2 | R39: 8 | S39: Contratistas | U39: Sistema de seguridad y vigilancia privada Centro de control Cerramiento de la locación Control de ingreso y salida de visitantes | V39: Charlas Informativas Charlas de seguridad física. | W39: 4 Crítico | X39: Personas | Y39: 2 Improbable | Z39: =INDEX($AS$3:$AV$6,MATCH($W39,$AR$3:$AR$6,FALSE),MATCH($Y39,AS$7:$AV$7,FALSE)) -> 8 | AA39: Si (Ver matriz de requisitos legales) | AB39: Ninguna | AC39: Ninguna | AD39: Ninguna | AE39: * Plan de emergencias * Anexo HSEQ para contratistas * Protocolos de seguridad física * Disponibilidad de equipos de comunicación | AF39: Ninguna | AG39: ="Eliminación del riesgo:"&año24[[#This Row],[CONTROLES (TRATAMIENTO DEL RIESGO Y PLANES ATENUANTES) - ELIMINACIÓN]]&"Sustitución del riesgo; "&año24[[#This Row],[CONTROLES (TRATAMIENTO DEL RIESGO Y PLANES ATENUANTES) - SUSTITUCIÓN]]&"Controles de Ingenieria; "&año24[[#This Row],[CONTROLES (TRATAMIENTO DEL RIESGO Y PLANES ATENUANTES) - CONTROLES DE INGENIERIA]]&" Controles administrativos; "&año24[[#This Row],[CONTROLES (TRATAMIENTO DEL RIESGO Y PLANES ATENUANTES) - CONTROLES ADMINISTRATIVOS / SEÑALIZACIÓN]]&"Controles de EPP; "&año24[[#This Row],[CONTROLES (TRATAMIENTO DEL RIESGO Y PLANES ATENUANTES) - ELEMENTOS DE PROTECCIÓN PERSONAL]] -> Eliminación del riesgo:NingunaSustitución del riesgo; NingunaControles de Ingenieria; Ninguna Controles administrativos; * Plan de emergencias * Anexo HSEQ para contratistas * Protocolos de seguridad física * Disponibilidad de equipos de comunicaciónControles de EPP; Ninguna | AH39: HS Parex Contratista | AI39: 2 Moderado | AJ39: Personas | AK39: 2 Improbable | AL39: =INDEX($AS$3:$AV$6,MATCH($AI39,$AR$3:$AR$6,FALSE),MATCH($AK39,$AS$7:$AV$7,FALSE)) -> 4 | AM39: =IF(año24[[#This Row],[VALORACION DEL RIESGO RESULTANTE CON CONTROLES (Riesgo residual) - Nivel de riesgo]]<=3,"Bajo",IF(año24[[#This Row],[VALORACION DEL RIESGO RESULTANTE CON CONTROLES (Riesgo residual) - Nivel de riesgo]]<=6,"Medio",IF(año24[[#This Row],[VALORACION DEL RIESGO RESULTANTE CON CONTROLES (Riesgo residual) - Nivel de riesgo]]<=12,"Alto","Extremo"))) -> Medio | AO39: =IF(AL39<=4,"SI",IF(AL39>=5,"NO")) -> SI | AP39: ="El nivel del riesgo es"&" "&año24[[#This Row],[VALORACION DEL RIESGO RESULTANTE CON CONTROLES (Riesgo residual) - INTERPRETACIÓN DEL RIESGO]]&" siendo las principales consecuencias las siguientes; "&año24[[#This Row],[Consecuencias (AT/EL)]] -> El nivel del riesgo es Medio siendo las principales consecuencias las siguientes; AT | AQ39: =_xlfn.XLOOKUP(año24[[#This Row],[VALORACION DEL RIESGO RESULTANTE CON CONTROLES (Riesgo residual) - INTERPRETACIÓN DEL RIESGO]], Nivel[Calsificación], Nivel[Imagen]) -> #VALUE!
B40: 31 | C40: 2024 | D40: Campos Parex | E40: Rig Up- Rig Down | F40: Rig Up- Rig Down de equipo / campamento Traslado de la mesa, líneas de succión, limpiar filtros de succión, correr y cortar cables de perforación, campamento Stack Out de Equipos en Patios | G40: Locación | H40: Atrapamiento durante la carga y descarga de materiales y equipos | I40: Condiciones_de_seguridad | J40: =_xlfn.XLOOKUP(año24[[#This Row],[PELIGRO -Tipo]], Tabla12[Calsificación], Tabla12[Imagen]) -> #VALUE! | K40: 6.1 Mecánico | L40: AT | M40: Rutinaria | N40: Interna | O40: 2 | P40: 53 | Q40: 2 | R40: 8 | S40: Contratistas | T40: Inspección de equipos y herramientas | U40: Inspecciones de seguridad | V40: Programa de capacitación (Riesgo Mecánico, cuidado de manos) Procedimiento de permisos de trabajo, ATS Programa de seguridad basada en el comportamiento | W40: 3 Serio | X40: Personas | Y40: 3 Probable | Z40: =INDEX($AS$3:$AV$6,MATCH($W40,$AR$3:$AR$6,FALSE),MATCH($Y40,AS$7:$AV$7,FALSE)) -> 9 | AA40: Si (Ver matriz de requisitos legales) | AB40: Ninguna | AC40: Ninguna | AD40: * Identificar en herramienta puntos de peligro (Pellizco; machucon; agarre) * Instalación de guayas antilatigos | AE40: *Implementar Programa de Gestión del Riesgo Mecánico * Seguimiento Programa de mantenimiento mecánico y eléctrico *Programa DROPS Mantener controles existentes: * Programa de Gestión Seguridad Basada en el Comportamiento * Programa de Gestión Cuidado de Manos * Manual de gestión de proyectos de facilidades * Procedimiento Sistema Permisos de Trabajo * Procedimiento Manejo Seguro de Herramientas Manuales * Procedimiento Levantamiento de Cargas * Anexo HSEQ para contratistas * Plan de Emergencias | AF40: Ver matriz de EPP | AG40: ="Eliminación del riesgo:"&año24[[#This Row],[CONTROLES (TRATAMIENTO DEL RIESGO Y PLANES ATENUANTES) - ELIMINACIÓN]]&"Sustitución del riesgo; "&año24[[#This Row],[CONTROLES (TRATAMIENTO DEL RIESGO Y PLANES ATENUANTES) - SUSTITUCIÓN]]&"Controles de Ingenieria; "&año24[[#This Row],[CONTROLES (TRATAMIENTO DEL RIESGO Y PLANES ATENUANTES) - CONTROLES DE INGENIERIA]]&" Controles administrativos; "&año24[[#This Row],[CONTROLES (TRATAMIENTO DEL RIESGO Y PLANES ATENUANTES) - CONTROLES ADMINISTRATIVOS / SEÑALIZACIÓN]]&"Controles de EPP; "&año24[[#This Row],[CONTROLES (TRATAMIENTO DEL RIESGO Y PLANES ATENUANTES) - ELEMENTOS DE PROTECCIÓN PERSONAL]] -> Eliminación del riesgo:NingunaSustitución del riesgo; NingunaControles de Ingenieria; * Identificar en herramienta puntos de peligro (Pellizco; machucon; agarre) * Instalación de guayas antilatigos Controles administrativos; *Implementar Programa de Gestión del Riesgo Mecánico * Seguimiento Programa de mantenimiento mecánico y eléctrico *Programa DROPS Mantener controles existentes: * Programa de Gestión Seguridad Basada en el Comportamiento * Programa de Gestión Cuidado de Manos * Manual de gestión de proyectos de facilidades * Procedimiento Sistema Permisos de Trabajo * Procedimiento Manejo Seguro de Herramientas Manuales * Procedimiento Levantamiento de Cargas * Anexo HSEQ para contratistas * Plan de EmergenciasControles de EPP; Ver matriz de EPP | AH40: HS Parex Contratista | AI40: 2 Moderado | AJ40: Personas | AK40: 2 Improbable | AL40: =INDEX($AS$3:$AV$6,MATCH($AI40,$AR$3:$AR$6,FALSE),MATCH($AK40,$AS$7:$AV$7,FALSE)) -> 4 | AM40: =IF(año24[[#This Row],[VALORACION DEL RIESGO RESULTANTE CON CONTROLES (Riesgo residual) - Nivel de riesgo]]<=3,"Bajo",IF(año24[[#This Row],[VALORACION DEL RIESGO RESULTANTE CON CONTROLES (Riesgo residual) - Nivel de riesgo]]<=6,"Medio",IF(año24[[#This Row],[VALORACION DEL RIESGO RESULTANTE CON CONTROLES (Riesgo residual) - Nivel de riesgo]]<=12,"Alto","Extremo"))) -> Medio | AN40: FAC 29/11/2021 En actividades de desarme del rig, el trabajador se encontraba levantando la bandeja donde se ubican las mangueras hidraulicas en la subestructura para posteriormente realizar Izaje de la base. En ese momento llega otro trabajador para brindarle apoyo y levanta del lado opuesto la bandeja ocasionando machucon del 4 dedo de la mano derecha de sus compañer. Posteriormente el trabajador se traslada a la ambulancia donde se brinda primeros auxilios y es remitido para valoración externa. | AO40: =IF(AL40<=4,"SI",IF(AL40>=5,"NO")) -> SI | AP40: ="El nivel del riesgo es"&" "&año24[[#This Row],[VALORACION DEL RIESGO RESULTANTE CON CONTROLES (Riesgo residual) - INTERPRETACIÓN DEL RIESGO]]&" siendo las principales consecuencias las siguientes; "&año24[[#This Row],[Consecuencias (AT/EL)]] -> El nivel del riesgo es Medio siendo las principales consecuencias las siguientes; AT | AQ40: =_xlfn.XLOOKUP(año24[[#This Row],[VALORACION DEL RIESGO RESULTANTE CON CONTROLES (Riesgo residual) - INTERPRETACIÓN DEL RIESGO]], Nivel[Calsificación], Nivel[Imagen]) -> #VALUE!
B41: 32 | C41: 2024 | D41: Campos Parex | E41: Rig Up- Rig Down | F41: Rig Up- Rig Down de equipo / campamento Traslado de la mesa, líneas de succión, limpiar filtros de succión, correr y cortar cables de perforación, campamento Stack Out de Equipos en Patios | G41: Locación | H41: Golpes y apretones de miembros superiores durante el trabajo con herramientas menores (martillo, masa, destornilladores, barretas) | I41: Condiciones_de_seguridad | J41: =_xlfn.XLOOKUP(año24[[#This Row],[PELIGRO -Tipo]], Tabla12[Calsificación], Tabla12[Imagen]) -> #VALUE! | K41: 6.1 Mecánico | L41: AT | M41: Rutinaria | N41: Interna | O41: 2 | P41: 53 | Q41: 2 | R41: 8 | S41: Contratistas | T41: Identificación de Peso de carga Ayudas mecánica (diferenciales, minicargador, cargador, brazo grua, grúas, carretillas, etc.) | U41: Inspecciones de seguridad | V41: Programa de capacitación (Riesgo Mecánico, cuidado de manos) Procedimiento de permisos de trabajo, ATS Programa de seguridad basada en el comportamiento | W41: 3 Serio | X41: Personas | Y41: 3 Probable | Z41: =INDEX($AS$3:$AV$6,MATCH($W41,$AR$3:$AR$6,FALSE),MATCH($Y41,AS$7:$AV$7,FALSE)) -> 9 | AA41: Si (Ver matriz de requisitos legales) | AB41: Ninguna | AC41: Ninguna | AD41: * Identificar en herramienta puntos de peligro (Pellizco; machucon; agarre) * Instalación de guayas antilatigos | AE41: *Implementar Programa de Gestión del Riesgo Mecánico * Seguimiento Programa de mantenimiento mecánico y eléctrico *Programa DROPS Mantener controles existentes: * Programa de Gestión Seguridad Basada en el Comportamiento * Programa de Gestión Cuidado de Manos * Manual de gestión de proyectos de facilidades * Procedimiento Sistema Permisos de Trabajo * Procedimiento Manejo Seguro de Herramientas Manuales * Procedimiento Levantamiento de Cargas * Anexo HSEQ para contratistas * Plan de Emergencias | AF41: Ver matriz de EPP | AG41: ="Eliminación del riesgo:"&año24[[#This Row],[CONTROLES (TRATAMIENTO DEL RIESGO Y PLANES ATENUANTES) - ELIMINACIÓN]]&"Sustitución del riesgo; "&año24[[#This Row],[CONTROLES (TRATAMIENTO DEL RIESGO Y PLANES ATENUANTES) - SUSTITUCIÓN]]&"Controles de Ingenieria; "&año24[[#This Row],[CONTROLES (TRATAMIENTO DEL RIESGO Y PLANES ATENUANTES) - CONTROLES DE INGENIERIA]]&" Controles administrativos; "&año24[[#This Row],[CONTROLES (TRATAMIENTO DEL RIESGO Y PLANES ATENUANTES) - CONTROLES ADMINISTRATIVOS / SEÑALIZACIÓN]]&"Controles de EPP; "&año24[[#This Row],[CONTROLES (TRATAMIENTO DEL RIESGO Y PLANES ATENUANTES) - ELEMENTOS DE PROTECCIÓN PERSONAL]] -> Eliminación del riesgo:NingunaSustitución del riesgo; NingunaControles de Ingenieria; * Identificar en herramienta puntos de peligro (Pellizco; machucon; agarre) * Instalación de guayas antilatigos Controles administrativos; *Implementar Programa de Gestión del Riesgo Mecánico * Seguimiento Programa de mantenimiento mecánico y eléctrico *Programa DROPS Mantener controles existentes: * Programa de Gestión Seguridad Basada en el Comportamiento * Programa de Gestión Cuidado de Manos * Manual de gestión de proyectos de facilidades * Procedimiento Sistema Permisos de Trabajo * Procedimiento Manejo Seguro de Herramientas Manuales * Procedimiento Levantamiento de Cargas * Anexo HSEQ para contratistas * Plan de EmergenciasControles de EPP; Ver matriz de EPP | AH41: HS Parex Contratista | AI41: 2 Moderado | AJ41: Personas | AK41: 2 Improbable | AL41: =INDEX($AS$3:$AV$6,MATCH($AI41,$AR$3:$AR$6,FALSE),MATCH($AK41,$AS$7:$AV$7,FALSE)) -> 4 | AM41: =IF(año24[[#This Row],[VALORACION DEL RIESGO RESULTANTE CON CONTROLES (Riesgo residual) - Nivel de riesgo]]<=3,"Bajo",IF(año24[[#This Row],[VALORACION DEL RIESGO RESULTANTE CON CONTROLES (Riesgo residual) - Nivel de riesgo]]<=6,"Medio",IF(año24[[#This Row],[VALORACION DEL RIESGO RESULTANTE CON CONTROLES (Riesgo residual) - Nivel de riesgo]]<=12,"Alto","Extremo"))) -> Medio | AO41: =IF(AL41<=4,"SI",IF(AL41>=5,"NO")) -> SI | AP41: ="El nivel del riesgo es"&" "&año24[[#This Row],[VALORACION DEL RIESGO RESULTANTE CON CONTROLES (Riesgo residual) - INTERPRETACIÓN DEL RIESGO]]&" siendo las principales consecuencias las siguientes; "&año24[[#This Row],[Consecuencias (AT/EL)]] -> El nivel del riesgo es Medio siendo las principales consecuencias las siguientes; AT | AQ41: =_xlfn.XLOOKUP(año24[[#This Row],[VALORACION DEL RIESGO RESULTANTE CON CONTROLES (Riesgo residual) - INTERPRETACIÓN DEL RIESGO]], Nivel[Calsificación], Nivel[Imagen]) -> #VALUE!
B42: 33 | C42: 2024 | D42: Campos Parex | E42: Rig Up- Rig Down | F42: Rig Up- Rig Down de equipo / campamento Traslado de la mesa, líneas de succión, limpiar filtros de succión, correr y cortar cables de perforación, campamento Stack Out de Equipos en Patios | G42: Locación | H42: Lluvias, tormentas eléctricas | I42: Fenómenos_naturales | J42: =_xlfn.XLOOKUP(año24[[#This Row],[PELIGRO -Tipo]], Tabla12[Calsificación], Tabla12[Imagen]) -> #VALUE! | K42: 7.6 Precipitaciones | L42: AT | M42: Rutinaria | N42: Externa | O42: 2 | P42: 53 | Q42: 2 | R42: 1 | S42: Contratistas | T42: Ninguna | U42: Señalización Layout de la locación Sistema de alarma Detector de tormentas Pararrayos Brigada de emergencias | V42: Uso de EPP (Dotación de invierno) Charlas Informativas | W42: 3 Serio | X42: Personas | Y42: 2 Improbable | Z42: =INDEX($AS$3:$AV$6,MATCH($W42,$AR$3:$AR$6,FALSE),MATCH($Y42,AS$7:$AV$7,FALSE)) -> 6 | AA42: Si (Ver matriz de requisitos legales) | AB42: Ninguna | AC42: Ninguna | AD42: Puesta a tierra de equipos en la locación | AE42: Continuar con los controles implemetados: * Plan de emergencias *Unidad de Respuesta a Emergencias (URE) | AF42: Ver matriz de EPP | AG42: ="Eliminación del riesgo:"&año24[[#This Row],[CONTROLES (TRATAMIENTO DEL RIESGO Y PLANES ATENUANTES) - ELIMINACIÓN]]&"Sustitución del riesgo; "&año24[[#This Row],[CONTROLES (TRATAMIENTO DEL RIESGO Y PLANES ATENUANTES) - SUSTITUCIÓN]]&"Controles de Ingenieria; "&año24[[#This Row],[CONTROLES (TRATAMIENTO DEL RIESGO Y PLANES ATENUANTES) - CONTROLES DE INGENIERIA]]&" Controles administrativos; "&año24[[#This Row],[CONTROLES (TRATAMIENTO DEL RIESGO Y PLANES ATENUANTES) - CONTROLES ADMINISTRATIVOS / SEÑALIZACIÓN]]&"Controles de EPP; "&año24[[#This Row],[CONTROLES (TRATAMIENTO DEL RIESGO Y PLANES ATENUANTES) - ELEMENTOS DE PROTECCIÓN PERSONAL]] -> Eliminación del riesgo:NingunaSustitución del riesgo; NingunaControles de Ingenieria; Puesta a tierra de equipos en la locación Controles administrativos; Continuar con los controles implemetados: * Plan de emergencias *Unidad de Respuesta a Emergencias (URE)Controles de EPP; Ver matriz de EPP | AH42: HS Parex Contratista | AI42: 3 Serio | AJ42: Personas | AK42: 1 Remoto | AL42: =INDEX($AS$3:$AV$6,MATCH($AI42,$AR$3:$AR$6,FALSE),MATCH($AK42,$AS$7:$AV$7,FALSE)) -> 3 | AM42: =IF(año24[[#This Row],[VALORACION DEL RIESGO RESULTANTE CON CONTROLES (Riesgo residual) - Nivel de riesgo]]<=3,"Bajo",IF(año24[[#This Row],[VALORACION DEL RIESGO RESULTANTE CON CONTROLES (Riesgo residual) - Nivel de riesgo]]<=6,"Medio",IF(año24[[#This Row],[VALORACION DEL RIESGO RESULTANTE CON CONTROLES (Riesgo residual) - Nivel de riesgo]]<=12,"Alto","Extremo"))) -> Bajo | AO42: =IF(AL42<=4,"SI",IF(AL42>=5,"NO")) -> SI | AP42: ="El nivel del riesgo es"&" "&año24[[#This Row],[VALORACION DEL RIESGO RESULTANTE CON CONTROLES (Riesgo residual) - INTERPRETACIÓN DEL RIESGO]]&" siendo las principales consecuencias las siguientes; "&año24[[#This Row],[Consecuencias (AT/EL)]] -> El nivel del riesgo es Bajo siendo las principales consecuencias las siguientes; AT | AQ42: =_xlfn.XLOOKUP(año24[[#This Row],[VALORACION DEL RIESGO RESULTANTE CON CONTROLES (Riesgo residual) - INTERPRETACIÓN DEL RIESGO]], Nivel[Calsificación], Nivel[Imagen]) -> #VALUE!
B43: 34 | C43: 2024 | D43: Campos Parex | E43: Rig Up- Rig Down | F43: Rig Up- Rig Down de equipo / campamento Traslado de la mesa, líneas de succión, limpiar filtros de succión, correr y cortar cables de perforación, campamento Stack Out de Equipos en Patios | G43: Locación | H43: Gestión organizacional (Estilo de mando) características de la organización del trabajo (comunicación y organización del trabajo) | I43: Psicosocial | J43: =_xlfn.XLOOKUP(año24[[#This Row],[PELIGRO -Tipo]], Tabla12[Calsificación], Tabla12[Imagen]) -> #VALUE! | K43: 4.1 Gestión organizacional | L43: EL | M43: Rutinaria | N43: Interna | O43: 2 | P43: 53 | Q43: 2 | R43: 8 | S43: Contratistas | T43: Organización del trabajo Definición de manuales de funciones y cargos | U43: Política de prevención de acoso laboral Comité de convivencia laboral | V43: *Aplicación de baterías de riesgo psicosocial * Capacitación en riesgo psicosocial * PVE de Riesgo Psicosocial | W43: 2 Moderado | X43: Personas | Y43: 2 Improbable | Z43: =INDEX($AS$3:$AV$6,MATCH($W43,$AR$3:$AR$6,FALSE),MATCH($Y43,AS$7:$AV$7,FALSE)) -> 4 | AA43: Si (Ver matriz de requisitos legales) | AB43: Ninguna | AC43: Ninguna | AD43: Ninguna | AE43: Continuidad en la aplicación de los controles: * Seguimiento a los planes de intervención del PVE de riesgo psicosocial * Pausas activas | AF43: Ninguna | AG43: ="Eliminación del riesgo:"&año24[[#This Row],[CONTROLES (TRATAMIENTO DEL RIESGO Y PLANES ATENUANTES) - ELIMINACIÓN]]&"Sustitución del riesgo; "&año24[[#This Row],[CONTROLES (TRATAMIENTO DEL RIESGO Y PLANES ATENUANTES) - SUSTITUCIÓN]]&"Controles de Ingenieria; "&año24[[#This Row],[CONTROLES (TRATAMIENTO DEL RIESGO Y PLANES ATENUANTES) - CONTROLES DE INGENIERIA]]&" Controles administrativos; "&año24[[#This Row],[CONTROLES (TRATAMIENTO DEL RIESGO Y PLANES ATENUANTES) - CONTROLES ADMINISTRATIVOS / SEÑALIZACIÓN]]&"Controles de EPP; "&año24[[#This Row],[CONTROLES (TRATAMIENTO DEL RIESGO Y PLANES ATENUANTES) - ELEMENTOS DE PROTECCIÓN PERSONAL]] -> Eliminación del riesgo:NingunaSustitución del riesgo; NingunaControles de Ingenieria; Ninguna Controles administrativos; Continuidad en la aplicación de los controles: * Seguimiento a los planes de intervención del PVE de riesgo psicosocial * Pausas activas Controles de EPP; Ninguna | AH43: HS Parex Contratista | AI43: 1 Menor | AJ43: Personas | AK43: 2 Improbable | AL43: =INDEX($AS$3:$AV$6,MATCH($AI43,$AR$3:$AR$6,FALSE),MATCH($AK43,$AS$7:$AV$7,FALSE)) -> 2 | AM43: =IF(año24[[#This Row],[VALORACION DEL RIESGO RESULTANTE CON CONTROLES (Riesgo residual) - Nivel de riesgo]]<=3,"Bajo",IF(año24[[#This Row],[VALORACION DEL RIESGO RESULTANTE CON CONTROLES (Riesgo residual) - Nivel de riesgo]]<=6,"Medio",IF(año24[[#This Row],[VALORACION DEL RIESGO RESULTANTE CON CONTROLES (Riesgo residual) - Nivel de riesgo]]<=12,"Alto","Extremo"))) -> Bajo | AO43: =IF(AL43<=4,"SI",IF(AL43>=5,"NO")) -> SI | AP43: ="El nivel del riesgo es"&" "&año24[[#This Row],[VALORACION DEL RIESGO RESULTANTE CON CONTROLES (Riesgo residual) - INTERPRETACIÓN DEL RIESGO]]&" siendo las principales consecuencias las siguientes; "&año24[[#This Row],[Consecuencias (AT/EL)]] -> El nivel del riesgo es Bajo siendo las principales consecuencias las siguientes; EL | AQ43: =_xlfn.XLOOKUP(año24[[#This Row],[VALORACION DEL RIESGO RESULTANTE CON CONTROLES (Riesgo residual) - INTERPRETACIÓN DEL RIESGO]], Nivel[Calsificación], Nivel[Imagen]) -> #VALUE!
B44: 35 | C44: 2024 | D44: Campos Parex | E44: Rig Up- Rig Down | F44: Rig Up- Rig Down de equipo / campamento Traslado de la mesa, líneas de succión, limpiar filtros de succión, correr y cortar cables de perforación, campamento Stack Out de Equipos en Patios | G44: Locación | H44: Características del grupo social de trabajo (Relaciones, cohesión, calidad de interacciones, trabajo en equipo) Jornadas de trabajo (pausas, trabajo nocturno, rotación, horas extras, descanso) | I44: Psicosocial | J44: =_xlfn.XLOOKUP(año24[[#This Row],[PELIGRO -Tipo]], Tabla12[Calsificación], Tabla12[Imagen]) -> #VALUE! | K44: 4.4 Características del grupo social de trabajo | L44: EL | M44: Rutinaria | N44: Interna | O44: 2 | P44: 53 | Q44: 2 | R44: 8 | S44: Contratistas | T44: Organización del trabajo Definición de manuales de funciones y cargos | U44: Política de prevención de acoso laboral Comité de convivencia laboral | V44: *Aplicación de baterías de riesgo psicosocial * Capacitación en riesgo psicosocial * PVE de Riesgo Psicosocial | W44: 2 Moderado | X44: Personas | Y44: 2 Improbable | Z44: =INDEX($AS$3:$AV$6,MATCH($W44,$AR$3:$AR$6,FALSE),MATCH($Y44,AS$7:$AV$7,FALSE)) -> 4 | AA44: Si (Ver matriz de requisitos legales) | AB44: Ninguna | AC44: Ninguna | AD44: Ninguna | AE44: Continuidad en la aplicación de los controles: * Seguimiento a los planes de intervención del PVE de riesgo psicosocial * Pausas activas | AF44: Ninguna | AG44: ="Eliminación del riesgo:"&año24[[#This Row],[CONTROLES (TRATAMIENTO DEL RIESGO Y PLANES ATENUANTES) - ELIMINACIÓN]]&"Sustitución del riesgo; "&año24[[#This Row],[CONTROLES (TRATAMIENTO DEL RIESGO Y PLANES ATENUANTES) - SUSTITUCIÓN]]&"Controles de Ingenieria; "&año24[[#This Row],[CONTROLES (TRATAMIENTO DEL RIESGO Y PLANES ATENUANTES) - CONTROLES DE INGENIERIA]]&" Controles administrativos; "&año24[[#This Row],[CONTROLES (TRATAMIENTO DEL RIESGO Y PLANES ATENUANTES) - CONTROLES ADMINISTRATIVOS / SEÑALIZACIÓN]]&"Controles de EPP; "&año24[[#This Row],[CONTROLES (TRATAMIENTO DEL RIESGO Y PLANES ATENUANTES) - ELEMENTOS DE PROTECCIÓN PERSONAL]] -> Eliminación del riesgo:NingunaSustitución del riesgo; NingunaControles de Ingenieria; Ninguna Controles administrativos; Continuidad en la aplicación de los controles: * Seguimiento a los planes de intervención del PVE de riesgo psicosocial * Pausas activas Controles de EPP; Ninguna | AH44: HS Parex Contratista | AI44: 1 Menor | AJ44: Personas | AK44: 2 Improbable | AL44: =INDEX($AS$3:$AV$6,MATCH($AI44,$AR$3:$AR$6,FALSE),MATCH($AK44,$AS$7:$AV$7,FALSE)) -> 2 | AM44: =IF(año24[[#This Row],[VALORACION DEL RIESGO RESULTANTE CON CONTROLES (Riesgo residual) - Nivel de riesgo]]<=3,"Bajo",IF(año24[[#This Row],[VALORACION DEL RIESGO RESULTANTE CON CONTROLES (Riesgo residual) - Nivel de riesgo]]<=6,"Medio",IF(año24[[#This Row],[VALORACION DEL RIESGO RESULTANTE CON CONTROLES (Riesgo residual) - Nivel de riesgo]]<=12,"Alto","Extremo"))) -> Bajo | AO44: =IF(AL44<=4,"SI",IF(AL44>=5,"NO")) -> SI | AP44: ="El nivel del riesgo es"&" "&año24[[#This Row],[VALORACION DEL RIESGO RESULTANTE CON CONTROLES (Riesgo residual) - INTERPRETACIÓN DEL RIESGO]]&" siendo las principales consecuencias las siguientes; "&año24[[#This Row],[Consecuencias (AT/EL)]] -> El nivel del riesgo es Bajo siendo las principales consecuencias las siguientes; EL | AQ44: =_xlfn.XLOOKUP(año24[[#This Row],[VALORACION DEL RIESGO RESULTANTE CON CONTROLES (Riesgo residual) - INTERPRETACIÓN DEL RIESGO]], Nivel[Calsificación], Nivel[Imagen]) -> #VALUE!
B45: 36 | C45: 2024 | D45: Campos Parex | E45: Rig Up- Rig Down | F45: Rig Up- Rig Down de equipo / campamento Traslado de la mesa, líneas de succión, limpiar filtros de succión, correr y cortar cables de perforación, campamento Stack Out de Equipos en Patios | G45: Locación | H45: Condiciones de la tarea (carga mental, demandas emocionales, sistemas de control, etc.) | I45: Psicosocial | J45: =_xlfn.XLOOKUP(año24[[#This Row],[PELIGRO -Tipo]], Tabla12[Calsificación], Tabla12[Imagen]) -> #VALUE! | K45: 4.3 Condiciones de la tarea | L45: EL | M45: Rutinaria | N45: Interna | O45: 2 | P45: 53 | Q45: 2 | R45: 8 | S45: Contratistas | T45: Organización del trabajo Definición de manuales de funciones y cargos | U45: Política de prevención de acoso laboral Comité de convivencia laboral | V45: *Aplicación de baterías de riesgo psicosocial * Capacitación en riesgo psicosocial * PVE de Riesgo Psicosocial | W45: 2 Moderado | X45: Personas | Y45: 2 Improbable | Z45: =INDEX($AS$3:$AV$6,MATCH($W45,$AR$3:$AR$6,FALSE),MATCH($Y45,AS$7:$AV$7,FALSE)) -> 4 | AA45: Si (Ver matriz de requisitos legales) | AB45: Ninguna | AC45: Ninguna | AD45: Ninguna | AE45: Continuidad en la aplicación de los controles: * Seguimiento a los planes de intervención del PVE de riesgo psicosocial * Pausas activas | AF45: Ninguna | AG45: ="Eliminación del riesgo:"&año24[[#This Row],[CONTROLES (TRATAMIENTO DEL RIESGO Y PLANES ATENUANTES) - ELIMINACIÓN]]&"Sustitución del riesgo; "&año24[[#This Row],[CONTROLES (TRATAMIENTO DEL RIESGO Y PLANES ATENUANTES) - SUSTITUCIÓN]]&"Controles de Ingenieria; "&año24[[#This Row],[CONTROLES (TRATAMIENTO DEL RIESGO Y PLANES ATENUANTES) - CONTROLES DE INGENIERIA]]&" Controles administrativos; "&año24[[#This Row],[CONTROLES (TRATAMIENTO DEL RIESGO Y PLANES ATENUANTES) - CONTROLES ADMINISTRATIVOS / SEÑALIZACIÓN]]&"Controles de EPP; "&año24[[#This Row],[CONTROLES (TRATAMIENTO DEL RIESGO Y PLANES ATENUANTES) - ELEMENTOS DE PROTECCIÓN PERSONAL]] -> Eliminación del riesgo:NingunaSustitución del riesgo; NingunaControles de Ingenieria; Ninguna Controles administrativos; Continuidad en la aplicación de los controles: * Seguimiento a los planes de intervención del PVE de riesgo psicosocial * Pausas activas Controles de EPP; Ninguna | AH45: HS Parex Contratista | AI45: 1 Menor | AJ45: Personas | AK45: 2 Improbable | AL45: =INDEX($AS$3:$AV$6,MATCH($AI45,$AR$3:$AR$6,FALSE),MATCH($AK45,$AS$7:$AV$7,FALSE)) -> 2 | AM45: =IF(año24[[#This Row],[VALORACION DEL RIESGO RESULTANTE CON CONTROLES (Riesgo residual) - Nivel de riesgo]]<=3,"Bajo",IF(año24[[#This Row],[VALORACION DEL RIESGO RESULTANTE CON CONTROLES (Riesgo residual) - Nivel de riesgo]]<=6,"Medio",IF(año24[[#This Row],[VALORACION DEL RIESGO RESULTANTE CON CONTROLES (Riesgo residual) - Nivel de riesgo]]<=12,"Alto","Extremo"))) -> Bajo | AO45: =IF(AL45<=4,"SI",IF(AL45>=5,"NO")) -> SI | AP45: ="El nivel del riesgo es"&" "&año24[[#This Row],[VALORACION DEL RIESGO RESULTANTE CON CONTROLES (Riesgo residual) - INTERPRETACIÓN DEL RIESGO]]&" siendo las principales consecuencias las siguientes; "&año24[[#This Row],[Consecuencias (AT/EL)]] -> El nivel del riesgo es Bajo siendo las principales consecuencias las siguientes; EL | AQ45: =_xlfn.XLOOKUP(año24[[#This Row],[VALORACION DEL RIESGO RESULTANTE CON CONTROLES (Riesgo residual) - INTERPRETACIÓN DEL RIESGO]], Nivel[Calsificación], Nivel[Imagen]) -> #VALUE!
B46: 37 | C46: 2024 | D46: Campos Parex | E46: Rig Up- Rig Down | F46: Rig Up- Rig Down de equipo / campamento Traslado de la mesa, líneas de succión, limpiar filtros de succión, correr y cortar cables de perforación, campamento Stack Out de Equipos en Patios | G46: Locación | H46: Actos y comportamientos inseguros, por no cumplir políticas, estándares y procedimietos de trabajo | I46: Psicosocial | J46: =_xlfn.XLOOKUP(año24[[#This Row],[PELIGRO -Tipo]], Tabla12[Calsificación], Tabla12[Imagen]) -> #VALUE! | K46: 4.2 Características de la organización del trabajo | L46: EL | M46: Rutinaria | N46: Interna | O46: 2 | P46: 53 | Q46: 2 | R46: 8 | S46: Contratistas | T46: Organización del trabajo Definición de manuales de funciones y cargos | U46: Política de prevención de acoso laboral Comité de convivencia laboral | V46: *Aplicación de baterías de riesgo psicosocial * Capacitación en riesgo psicosocial * PVE de Riesgo Psicosocial | W46: 2 Moderado | X46: Personas | Y46: 2 Improbable | Z46: =INDEX($AS$3:$AV$6,MATCH($W46,$AR$3:$AR$6,FALSE),MATCH($Y46,AS$7:$AV$7,FALSE)) -> 4 | AA46: Si (Ver matriz de requisitos legales) | AB46: Ninguna | AC46: Ninguna | AD46: Ninguna | AE46: Continuidad en la aplicación de los controles: * Seguimiento a los planes de intervención del PVE de riesgo psicosocial * Pausas activas | AF46: Ninguna | AG46: ="Eliminación del riesgo:"&año24[[#This Row],[CONTROLES (TRATAMIENTO DEL RIESGO Y PLANES ATENUANTES) - ELIMINACIÓN]]&"Sustitución del riesgo; "&año24[[#This Row],[CONTROLES (TRATAMIENTO DEL RIESGO Y PLANES ATENUANTES) - SUSTITUCIÓN]]&"Controles de Ingenieria; "&año24[[#This Row],[CONTROLES (TRATAMIENTO DEL RIESGO Y PLANES ATENUANTES) - CONTROLES DE INGENIERIA]]&" Controles administrativos; "&año24[[#This Row],[CONTROLES (TRATAMIENTO DEL RIESGO Y PLANES ATENUANTES) - CONTROLES ADMINISTRATIVOS / SEÑALIZACIÓN]]&"Controles de EPP; "&año24[[#This Row],[CONTROLES (TRATAMIENTO DEL RIESGO Y PLANES ATENUANTES) - ELEMENTOS DE PROTECCIÓN PERSONAL]] -> Eliminación del riesgo:NingunaSustitución del riesgo; NingunaControles de Ingenieria; Ninguna Controles administrativos; Continuidad en la aplicación de los controles: * Seguimiento a los planes de intervención del PVE de riesgo psicosocial * Pausas activas Controles de EPP; Ninguna | AH46: HS Parex Contratista | AI46: 1 Menor | AJ46: Personas | AK46: 2 Improbable | AL46: =INDEX($AS$3:$AV$6,MATCH($AI46,$AR$3:$AR$6,FALSE),MATCH($AK46,$AS$7:$AV$7,FALSE)) -> 2 | AM46: =IF(año24[[#This Row],[VALORACION DEL RIESGO RESULTANTE CON CONTROLES (Riesgo residual) - Nivel de riesgo]]<=3,"Bajo",IF(año24[[#This Row],[VALORACION DEL RIESGO RESULTANTE CON CONTROLES (Riesgo residual) - Nivel de riesgo]]<=6,"Medio",IF(año24[[#This Row],[VALORACION DEL RIESGO RESULTANTE CON CONTROLES (Riesgo residual) - Nivel de riesgo]]<=12,"Alto","Extremo"))) -> Bajo | AO46: =IF(AL46<=4,"SI",IF(AL46>=5,"NO")) -> SI | AP46: ="El nivel del riesgo es"&" "&año24[[#This Row],[VALORACION DEL RIESGO RESULTANTE CON CONTROLES (Riesgo residual) - INTERPRETACIÓN DEL RIESGO]]&" siendo las principales consecuencias las siguientes; "&año24[[#This Row],[Consecuencias (AT/EL)]] -> El nivel del riesgo es Bajo siendo las principales consecuencias las siguientes; EL | AQ46: =_xlfn.XLOOKUP(año24[[#This Row],[VALORACION DEL RIESGO RESULTANTE CON CONTROLES (Riesgo residual) - INTERPRETACIÓN DEL RIESGO]], Nivel[Calsificación], Nivel[Imagen]) -> #VALUE!
B47: 38 | C47: 2024 | D47: Campos Parex | E47: Rig Up- Rig Down | F47: Rig Up- Rig Down de equipo / campamento Traslado de la mesa, líneas de succión, limpiar filtros de succión, correr y cortar cables de perforación, campamento Stack Out de Equipos en Patios | G47: Locación | H47: Radiación no ionizante (Exposición a rayos solares) | I47: Físico | J47: =_xlfn.XLOOKUP(año24[[#This Row],[PELIGRO -Tipo]], Tabla12[Calsificación], Tabla12[Imagen]) -> #VALUE! | K47: 2.7 Radiaciones No ionizantes | L47: EL | M47: Rutinaria | N47: Interna | O47: 2 | P47: 53 | Q47: 2 | R47: 4 | S47: Contratistas | T47: Ninguna | U47: Ninguna | V47: Hidratación. Uso de bloqueador solar Examen Ocupacional con énfasis dermatológico | W47: 2 Moderado | X47: Personas | Y47: 3 Probable | Z47: =INDEX($AS$3:$AV$6,MATCH($W47,$AR$3:$AR$6,FALSE),MATCH($Y47,AS$7:$AV$7,FALSE)) -> 6 | AA47: Si (Ver matriz de requisitos legales) | AB47: Ninguna | AC47: Ninguna | AD47: Ninguna | AE47: Mantener controles existentes: Hidratación. Uso de bloqueador solar Examen Ocupacional con énfasis dermatológico Evitar la exposición directa a la luz solar dos horas antes y dos horas después del medio día. Capacitación en lesiones de piel | AF47: Ver matriz de EPP | AG47: ="Eliminación del riesgo:"&año24[[#This Row],[CONTROLES (TRATAMIENTO DEL RIESGO Y PLANES ATENUANTES) - ELIMINACIÓN]]&"Sustitución del riesgo; "&año24[[#This Row],[CONTROLES (TRATAMIENTO DEL RIESGO Y PLANES ATENUANTES) - SUSTITUCIÓN]]&"Controles de Ingenieria; "&año24[[#This Row],[CONTROLES (TRATAMIENTO DEL RIESGO Y PLANES ATENUANTES) - CONTROLES DE INGENIERIA]]&" Controles administrativos; "&año24[[#This Row],[CONTROLES (TRATAMIENTO DEL RIESGO Y PLANES ATENUANTES) - CONTROLES ADMINISTRATIVOS / SEÑALIZACIÓN]]&"Controles de EPP; "&año24[[#This Row],[CONTROLES (TRATAMIENTO DEL RIESGO Y PLANES ATENUANTES) - ELEMENTOS DE PROTECCIÓN PERSONAL]] -> Eliminación del riesgo:NingunaSustitución del riesgo; NingunaControles de Ingenieria; Ninguna Controles administrativos; Mantener controles existentes: Hidratación. Uso de bloqueador solar Examen Ocupacional con énfasis dermatológico Evitar la exposición directa a la luz solar dos horas antes y dos horas después del medio día. Capacitación en lesiones de piel Controles de EPP; Ver matriz de EPP | AH47: HS Parex Contratista | AI47: 2 Moderado | AJ47: Personas | AK47: 2 Improbable | AL47: =INDEX($AS$3:$AV$6,MATCH($AI47,$AR$3:$AR$6,FALSE),MATCH($AK47,$AS$7:$AV$7,FALSE)) -> 4 | AM47: =IF(año24[[#This Row],[VALORACION DEL RIESGO RESULTANTE CON CONTROLES (Riesgo residual) - Nivel de riesgo]]<=3,"Bajo",IF(año24[[#This Row],[VALORACION DEL RIESGO RESULTANTE CON CONTROLES (Riesgo residual) - Nivel de riesgo]]<=6,"Medio",IF(año24[[#This Row],[VALORACION DEL RIESGO RESULTANTE CON CONTROLES (Riesgo residual) - Nivel de riesgo]]<=12,"Alto","Extremo"))) -> Medio | AO47: =IF(AL47<=4,"SI",IF(AL47>=5,"NO")) -> SI | AP47: ="El nivel del riesgo es"&" "&año24[[#This Row],[VALORACION DEL RIESGO RESULTANTE CON CONTROLES (Riesgo residual) - INTERPRETACIÓN DEL RIESGO]]&" siendo las principales consecuencias las siguientes; "&año24[[#This Row],[Consecuencias (AT/EL)]] -> El nivel del riesgo es Medio siendo las principales consecuencias las siguientes; EL | AQ47: =_xlfn.XLOOKUP(año24[[#This Row],[VALORACION DEL RIESGO RESULTANTE CON CONTROLES (Riesgo residual) - INTERPRETACIÓN DEL RIESGO]], Nivel[Calsificación], Nivel[Imagen]) -> #VALUE!
B48: 39 | C48: 2024 | D48: Campos Parex | E48: Rig Up- Rig Down | F48: Rig Up- Rig Down de equipo / campamento Traslado de la mesa, líneas de succión, limpiar filtros de succión, correr y cortar cables de perforación, campamento Stack Out de Equipos en Patios | G48: Locación | H48: Caídas a nivel y golpes, superficies irregulares, deslizantes con diferencia del nivel, condiciones de orden, caída de objetos y aseo durante el Rig up Rig down del equipo- campamento | I48: Condiciones_de_seguridad | J48: =_xlfn.XLOOKUP(año24[[#This Row],[PELIGRO -Tipo]], Tabla12[Calsificación], Tabla12[Imagen]) -> #VALUE! | K48: 6.3 Locativos | L48: AT/EL | M48: Rutinaria | N48: Interna | O48: 2 | P48: 53 | Q48: 2 | R48: 1 | S48: Contratistas | T48: Mantenimiento de vias, nivelación de áreas de circulación, señalización y adecuación de pasos peatonales | U48: Inspecciones de seguridad | V48: Uso de EPP Charlas informativas, preoperacionales y de seguridad | W48: 2 Moderado | X48: Personas | Y48: 3 Probable | Z48: =INDEX($AS$3:$AV$6,MATCH($W48,$AR$3:$AR$6,FALSE),MATCH($Y48,AS$7:$AV$7,FALSE)) -> 6 | AA48: Si (Ver matriz de requisitos legales) | AB48: Ninguna | AC48: Ninguna | AD48: Ninguna | AE48: * Programa de inspecciones * Programa de Gestión Seguridad Basada en el Comportamiento * Programa de Gestión caídas a Nivel * Anexo HSEQ para contratistas | AF48: Ver matriz de EPP | AG48: ="Eliminación del riesgo:"&año24[[#This Row],[CONTROLES (TRATAMIENTO DEL RIESGO Y PLANES ATENUANTES) - ELIMINACIÓN]]&"Sustitución del riesgo; "&año24[[#This Row],[CONTROLES (TRATAMIENTO DEL RIESGO Y PLANES ATENUANTES) - SUSTITUCIÓN]]&"Controles de Ingenieria; "&año24[[#This Row],[CONTROLES (TRATAMIENTO DEL RIESGO Y PLANES ATENUANTES) - CONTROLES DE INGENIERIA]]&" Controles administrativos; "&año24[[#This Row],[CONTROLES (TRATAMIENTO DEL RIESGO Y PLANES ATENUANTES) - CONTROLES ADMINISTRATIVOS / SEÑALIZACIÓN]]&"Controles de EPP; "&año24[[#This Row],[CONTROLES (TRATAMIENTO DEL RIESGO Y PLANES ATENUANTES) - ELEMENTOS DE PROTECCIÓN PERSONAL]] -> Eliminación del riesgo:NingunaSustitución del riesgo; NingunaControles de Ingenieria; Ninguna Controles administrativos; * Programa de inspecciones * Programa de Gestión Seguridad Basada en el Comportamiento * Programa de Gestión caídas a Nivel * Anexo HSEQ para contratistasControles de EPP; Ver matriz de EPP | AH48: HS Parex Contratista | AI48: 2 Moderado | AJ48: Personas | AK48: 2 Improbable | AL48: =INDEX($AS$3:$AV$6,MATCH($AI48,$AR$3:$AR$6,FALSE),MATCH($AK48,$AS$7:$AV$7,FALSE)) -> 4 | AM48: =IF(año24[[#This Row],[VALORACION DEL RIESGO RESULTANTE CON CONTROLES (Riesgo residual) - Nivel de riesgo]]<=3,"Bajo",IF(año24[[#This Row],[VALORACION DEL RIESGO RESULTANTE CON CONTROLES (Riesgo residual) - Nivel de riesgo]]<=6,"Medio",IF(año24[[#This Row],[VALORACION DEL RIESGO RESULTANTE CON CONTROLES (Riesgo residual) - Nivel de riesgo]]<=12,"Alto","Extremo"))) -> Medio | AN48: FAC 28/06/2022 Durante actividades de rig up de los equipos de control de sólidos el trabajador se encontraba en el stand ubicando las centrifugas y no se percata de un hueco ubicado en la malla eslabonada del piso por donde pasa el tubo PVC de 6" de la descarga líquida de la centrifuga, al dar un paso introduce y roza su pierna con dicha malla ocasionando una herida en la parte posterior de su muslo izquierdo.. | AO48: =IF(AL48<=4,"SI",IF(AL48>=5,"NO")) -> SI | AP48: ="El nivel del riesgo es"&" "&año24[[#This Row],[VALORACION DEL RIESGO RESULTANTE CON CONTROLES (Riesgo residual) - INTERPRETACIÓN DEL RIESGO]]&" siendo las principales consecuencias las siguientes; "&año24[[#This Row],[Consecuencias (AT/EL)]] -> El nivel del riesgo es Medio siendo las principales consecuencias las siguientes; AT/EL | AQ48: =_xlfn.XLOOKUP(año24[[#This Row],[VALORACION DEL RIESGO RESULTANTE CON CONTROLES (Riesgo residual) - INTERPRETACIÓN DEL RIESGO]], Nivel[Calsificación], Nivel[Imagen]) -> #VALUE!
B49: 40 | C49: 2024 | D49: Campos Parex | E49: Rig Up- Rig Down | F49: Rig Up- Rig Down de equipo / campamento Traslado de la mesa, líneas de succión, limpiar filtros de succión, correr y cortar cables de perforación, campamento Stack Out de Equipos en Patios | G49: Locación | H49: Esfuerzos excesivos ( manipulación de elementos de gran peso) Posturas inadecuadas para macear y forma de manipular herramientas y equipos) | I49: Biomecánicas | J49: =_xlfn.XLOOKUP(año24[[#This Row],[PELIGRO -Tipo]], Tabla12[Calsificación], Tabla12[Imagen]) -> #VALUE! | K49: 5.1 Postura | L49: EL | M49: Rutinaria | N49: Interna | O49: 2 | P49: 25 | Q49: 2 | R49: 1 | S49: Contratistas | U49: Estudio de puestos de trabajo | V49: Exámen médico ocupacional con enfásis osteomuscular PVE Lesiones osteomusculares Capacitación en Higiene postural y manejo de cargas | W49: 2 Moderado | X49: Personas | Y49: 2 Improbable | Z49: =INDEX($AS$3:$AV$6,MATCH($W49,$AR$3:$AR$6,FALSE),MATCH($Y49,AS$7:$AV$7,FALSE)) -> 4 | AA49: Si (Ver matriz de requisitos legales) | AB49: Ninguna | AC49: Ninguna | AD49: Ninguna | AE49: * Programa de Gestión Seguridad Basada en el Comportamiento * Sequimiento Programa de Vigilancia Epidemiológica condiciones ergonómicas inadecuadas y Desórdenes Músculo Esqueléticos * Anexo HSEQ para contratistas | AF49: Ver matriz de EPP | AG49: ="Eliminación del riesgo:"&año24[[#This Row],[CONTROLES (TRATAMIENTO DEL RIESGO Y PLANES ATENUANTES) - ELIMINACIÓN]]&"Sustitución del riesgo; "&año24[[#This Row],[CONTROLES (TRATAMIENTO DEL RIESGO Y PLANES ATENUANTES) - SUSTITUCIÓN]]&"Controles de Ingenieria; "&año24[[#This Row],[CONTROLES (TRATAMIENTO DEL RIESGO Y PLANES ATENUANTES) - CONTROLES DE INGENIERIA]]&" Controles administrativos; "&año24[[#This Row],[CONTROLES (TRATAMIENTO DEL RIESGO Y PLANES ATENUANTES) - CONTROLES ADMINISTRATIVOS / SEÑALIZACIÓN]]&"Controles de EPP; "&año24[[#This Row],[CONTROLES (TRATAMIENTO DEL RIESGO Y PLANES ATENUANTES) - ELEMENTOS DE PROTECCIÓN PERSONAL]] -> Eliminación del riesgo:NingunaSustitución del riesgo; NingunaControles de Ingenieria; Ninguna Controles administrativos; * Programa de Gestión Seguridad Basada en el Comportamiento * Sequimiento Programa de Vigilancia Epidemiológica condiciones ergonómicas inadecuadas y Desórdenes Músculo Esqueléticos * Anexo HSEQ para contratistas Controles de EPP; Ver matriz de EPP | AH49: HS Parex Contratista | AI49: 2 Moderado | AJ49: Personas | AK49: 1 Remoto | AL49: =INDEX($AS$3:$AV$6,MATCH($AI49,$AR$3:$AR$6,FALSE),MATCH($AK49,$AS$7:$AV$7,FALSE)) -> 2 | AM49: =IF(año24[[#This Row],[VALORACION DEL RIESGO RESULTANTE CON CONTROLES (Riesgo residual) - Nivel de riesgo]]<=3,"Bajo",IF(año24[[#This Row],[VALORACION DEL RIESGO RESULTANTE CON CONTROLES (Riesgo residual) - Nivel de riesgo]]<=6,"Medio",IF(año24[[#This Row],[VALORACION DEL RIESGO RESULTANTE CON CONTROLES (Riesgo residual) - Nivel de riesgo]]<=12,"Alto","Extremo"))) -> Bajo | AO49: =IF(AL49<=4,"SI",IF(AL49>=5,"NO")) -> SI | AP49: ="El nivel del riesgo es"&" "&año24[[#This Row],[VALORACION DEL RIESGO RESULTANTE CON CONTROLES (Riesgo residual) - INTERPRETACIÓN DEL RIESGO]]&" siendo las principales consecuencias las siguientes; "&año24[[#This Row],[Consecuencias (AT/EL)]] -> El nivel del riesgo es Bajo siendo las principales consecuencias las siguientes; EL | AQ49: =_xlfn.XLOOKUP(año24[[#This Row],[VALORACION DEL RIESGO RESULTANTE CON CONTROLES (Riesgo residual) - INTERPRETACIÓN DEL RIESGO]], Nivel[Calsificación], Nivel[Imagen]) -> #VALUE!
B50: 41 | C50: 2024 | D50: Campos Parex | E50: Rig Up- Rig Down | F50: Rig Up- Rig Down de equipo / campamento Traslado de la mesa, líneas de succión, limpiar filtros de succión, correr y cortar cables de perforación, campamento Stack Out de Equipos en Patios | G50: Locación | H50: Trabajo en alturas | I50: Condiciones_de_seguridad | J50: =_xlfn.XLOOKUP(año24[[#This Row],[PELIGRO -Tipo]], Tabla12[Calsificación], Tabla12[Imagen]) -> #VALUE! | K50: 6.7 Trabajo en alturas | L50: AT | M50: Rutinaria | N50: Interna | O50: 2 | P50: 53 | Q50: 2 | R50: 8 | S50: Contratistas | T50: Líneas de vida Barandas en escaleras Instalacion de sistemas de proteccion colectiva, Certificado de andamios Certificación de puntos de anclaje | U50: Inspecciones de seguridad | V50: Uso de EPP Uso de Equipo de Protección Contra Caídas Certificado de competencia para trabajo en alturas Charlas Informativas Procedimiento Sistema Permisos de Trabajo, ATS | W50: 4 Crítico | X50: Personas | Y50: 2 Improbable | Z50: =INDEX($AS$3:$AV$6,MATCH($W50,$AR$3:$AR$6,FALSE),MATCH($Y50,AS$7:$AV$7,FALSE)) -> 8 | AA50: Si (Ver matriz de requisitos legales) | AE50: * Programa de Gestión Seguridad Basada en el Comportamiento * Programa de gestión trabajo en alturas * Procedimiento para trabajo en alturas * Procedimiento Sistema Permisos de Trabajo * Anexo HSEQ para contratistas * Plan de emergencias, plan de rescate en alturas * Programa de capacitaciones | AF50: Ver matriz de EPP | AG50: ="Eliminación del riesgo:"&año24[[#This Row],[CONTROLES (TRATAMIENTO DEL RIESGO Y PLANES ATENUANTES) - ELIMINACIÓN]]&"Sustitución del riesgo; "&año24[[#This Row],[CONTROLES (TRATAMIENTO DEL RIESGO Y PLANES ATENUANTES) - SUSTITUCIÓN]]&"Controles de Ingenieria; "&año24[[#This Row],[CONTROLES (TRATAMIENTO DEL RIESGO Y PLANES ATENUANTES) - CONTROLES DE INGENIERIA]]&" Controles administrativos; "&año24[[#This Row],[CONTROLES (TRATAMIENTO DEL RIESGO Y PLANES ATENUANTES) - CONTROLES ADMINISTRATIVOS / SEÑALIZACIÓN]]&"Controles de EPP; "&año24[[#This Row],[CONTROLES (TRATAMIENTO DEL RIESGO Y PLANES ATENUANTES) - ELEMENTOS DE PROTECCIÓN PERSONAL]] -> Eliminación del riesgo:Sustitución del riesgo; Controles de Ingenieria; Controles administrativos; * Programa de Gestión Seguridad Basada en el Comportamiento * Programa de gestión trabajo en alturas * Procedimiento para trabajo en alturas * Procedimiento Sistema Permisos de Trabajo * Anexo HSEQ para contratistas * Plan de emergencias, plan de rescate en alturas * Programa de capacitacionesControles de EPP; Ver matriz de EPP | AH50: HS Parex Contratista | AI50: 2 Moderado | AJ50: Personas | AK50: 2 Improbable | AL50: =INDEX($AS$3:$AV$6,MATCH($AI50,$AR$3:$AR$6,FALSE),MATCH($AK50,$AS$7:$AV$7,FALSE)) -> 4 | AM50: =IF(año24[[#This Row],[VALORACION DEL RIESGO RESULTANTE CON CONTROLES (Riesgo residual) - Nivel de riesgo]]<=3,"Bajo",IF(año24[[#This Row],[VALORACION DEL RIESGO RESULTANTE CON CONTROLES (Riesgo residual) - Nivel de riesgo]]<=6,"Medio",IF(año24[[#This Row],[VALORACION DEL RIESGO RESULTANTE CON CONTROLES (Riesgo residual) - Nivel de riesgo]]<=12,"Alto","Extremo"))) -> Medio | AO50: =IF(AL50<=4,"SI",IF(AL50>=5,"NO")) -> SI | AP50: ="El nivel del riesgo es"&" "&año24[[#This Row],[VALORACION DEL RIESGO RESULTANTE CON CONTROLES (Riesgo residual) - INTERPRETACIÓN DEL RIESGO]]&" siendo las principales consecuencias las siguientes; "&año24[[#This Row],[Consecuencias (AT/EL)]] -> El nivel del riesgo es Medio siendo las principales consecuencias las siguientes; AT | AQ50: =_xlfn.XLOOKUP(año24[[#This Row],[VALORACION DEL RIESGO RESULTANTE CON CONTROLES (Riesgo residual) - INTERPRETACIÓN DEL RIESGO]], Nivel[Calsificación], Nivel[Imagen]) -> #VALUE!
B51: 42 | C51: 2024 | D51: Campos Parex | E51: Rig Up- Rig Down | F51: Rig Up- Rig Down de equipo / campamento Traslado de la mesa, líneas de succión, limpiar filtros de succión, correr y cortar cables de perforación, campamento Stack Out de Equipos en Patios | G51: Locación | H51: Apretones, golpes, proyección de objetos, caídas al vincular/desvincular bombas | I51: Condiciones_de_seguridad | J51: =_xlfn.XLOOKUP(año24[[#This Row],[PELIGRO -Tipo]], Tabla12[Calsificación], Tabla12[Imagen]) -> #VALUE! | K51: 6.1 Mecánico | L51: AT | M51: Rutinaria | N51: Interna | O51: 2 | P51: 53 | Q51: 2 | R51: 8 | S51: Contratistas | U51: Guardas de seguridad | V51: Programa de capacitación (Riesgo Mecánico, cuidado de manos) Procedimiento de permisos de trabajo, ATS Programa de seguridad basada en el comportamiento | W51: 3 Serio | X51: Personas | Y51: 3 Probable | Z51: =INDEX($AS$3:$AV$6,MATCH($W51,$AR$3:$AR$6,FALSE),MATCH($Y51,AS$7:$AV$7,FALSE)) -> 9 | AA51: Si (Ver matriz de requisitos legales) | AB51: Ninguna | AC51: Ninguna | AD51: * Identificar en herramienta puntos de peligro (Pellizco; machucon; agarre) * Instalación de guayas antilatigos | AE51: *Implementar Programa de Gestión del Riesgo Mecánico * Seguimiento Programa de mantenimiento mecánico y eléctrico *Programa DROPS Mantener controles existentes: * Programa de Gestión Seguridad Basada en el Comportamiento * Programa de Gestión Cuidado de Manos * Manual de gestión de proyectos de facilidades * Procedimiento Sistema Permisos de Trabajo * Procedimiento Manejo Seguro de Herramientas Manuales * Procedimiento Levantamiento de Cargas * Anexo HSEQ para contratistas * Plan de Emergencias | AF51: Ver matriz de EPP | AG51: ="Eliminación del riesgo:"&año24[[#This Row],[CONTROLES (TRATAMIENTO DEL RIESGO Y PLANES ATENUANTES) - ELIMINACIÓN]]&"Sustitución del riesgo; "&año24[[#This Row],[CONTROLES (TRATAMIENTO DEL RIESGO Y PLANES ATENUANTES) - SUSTITUCIÓN]]&"Controles de Ingenieria; "&año24[[#This Row],[CONTROLES (TRATAMIENTO DEL RIESGO Y PLANES ATENUANTES) - CONTROLES DE INGENIERIA]]&" Controles administrativos; "&año24[[#This Row],[CONTROLES (TRATAMIENTO DEL RIESGO Y PLANES ATENUANTES) - CONTROLES ADMINISTRATIVOS / SEÑALIZACIÓN]]&"Controles de EPP; "&año24[[#This Row],[CONTROLES (TRATAMIENTO DEL RIESGO Y PLANES ATENUANTES) - ELEMENTOS DE PROTECCIÓN PERSONAL]] -> Eliminación del riesgo:NingunaSustitución del riesgo; NingunaControles de Ingenieria; * Identificar en herramienta puntos de peligro (Pellizco; machucon; agarre) * Instalación de guayas antilatigos Controles administrativos; *Implementar Programa de Gestión del Riesgo Mecánico * Seguimiento Programa de mantenimiento mecánico y eléctrico *Programa DROPS Mantener controles existentes: * Programa de Gestión Seguridad Basada en el Comportamiento * Programa de Gestión Cuidado de Manos * Manual de gestión de proyectos de facilidades * Procedimiento Sistema Permisos de Trabajo * Procedimiento Manejo Seguro de Herramientas Manuales * Procedimiento Levantamiento de Cargas * Anexo HSEQ para contratistas * Plan de EmergenciasControles de EPP; Ver matriz de EPP | AH51: HS Parex Contratista | AI51: 2 Moderado | AJ51: Personas | AK51: 2 Improbable | AL51: =INDEX($AS$3:$AV$6,MATCH($AI51,$AR$3:$AR$6,FALSE),MATCH($AK51,$AS$7:$AV$7,FALSE)) -> 4 | AM51: =IF(año24[[#This Row],[VALORACION DEL RIESGO RESULTANTE CON CONTROLES (Riesgo residual) - Nivel de riesgo]]<=3,"Bajo",IF(año24[[#This Row],[VALORACION DEL RIESGO RESULTANTE CON CONTROLES (Riesgo residual) - Nivel de riesgo]]<=6,"Medio",IF(año24[[#This Row],[VALORACION DEL RIESGO RESULTANTE CON CONTROLES (Riesgo residual) - Nivel de riesgo]]<=12,"Alto","Extremo"))) -> Medio | AO51: =IF(AL51<=4,"SI",IF(AL51>=5,"NO")) -> SI | AP51: ="El nivel del riesgo es"&" "&año24[[#This Row],[VALORACION DEL RIESGO RESULTANTE CON CONTROLES (Riesgo residual) - INTERPRETACIÓN DEL RIESGO]]&" siendo las principales consecuencias las siguientes; "&año24[[#This Row],[Consecuencias (AT/EL)]] -> El nivel del riesgo es Medio siendo las principales consecuencias las siguientes; AT | AQ51: =_xlfn.XLOOKUP(año24[[#This Row],[VALORACION DEL RIESGO RESULTANTE CON CONTROLES (Riesgo residual) - INTERPRETACIÓN DEL RIESGO]], Nivel[Calsificación], Nivel[Imagen]) -> #VALUE!
B52: 43 | C52: 2024 | D52: Campos Parex | E52: Rig Up- Rig Down | F52: Rig Up- Rig Down de equipo / campamento Traslado de la mesa, líneas de succión, limpiar filtros de succión, correr y cortar cables de perforación, campamento Stack Out de Equipos en Patios | G52: Locación | H52: Contacto directo con corriente al conectar/desconectar suministro eléctrico a la torre | I52: Condiciones_de_seguridad | J52: =_xlfn.XLOOKUP(año24[[#This Row],[PELIGRO -Tipo]], Tabla12[Calsificación], Tabla12[Imagen]) -> #VALUE! | K52: 6.2 Eléctrico | L52: AT | M52: Rutinaria | N52: Interna | O52: 2 | P52: 53 | Q52: 2 | R52: 4 | S52: Contratistas | T52: Mantenimientos preventivos y predictivos a los equipos | U52: Sistema puesta a tierra Inspecciones de seguridad Señalización reglamentaria riesgo eléctrico | V52: Certificado de Aislamiento (Bloqueo, candado y Etiquetado). Sistema lock out 5 Reglas de oro aislamiento. Procedimiento Permisos de trabajo, ATS Personal competente para trabajos eléctricos de acuerdo con certificación conte Capacitación riesgo eléctrico | W52: 3 Serio | X52: Personas | Y52: 3 Probable | Z52: =INDEX($AS$3:$AV$6,MATCH($W52,$AR$3:$AR$6,FALSE),MATCH($Y52,AS$7:$AV$7,FALSE)) -> 9 | AA52: Si (Ver matriz de requisitos legales) | AB52: Ninguna | AC52: Ninguna | AD52: Mantener Controles Existentes: Sistema de aterrizaje pararrayos Puesta a tierra de equipos | AE52: Implementar programa de gestión de riesgo eléctrico Mantener controles existentes: *Inspección Vial (Identificación de cuerdas de alta, media, baja) *Uso de pertigueros en puntos identificados *Señalización riesgo eléctrico * Programa de Gestión Seguridad Basada en el Comportamiento * Procedimiento sistemas permiso de trabajo * Procedimiento Aislamiento de Fuentes de Energia * Anexo HSEQ para contratistas * Plan de emergencias | AF52: Ver matriz de EPP | AG52: ="Eliminación del riesgo:"&año24[[#This Row],[CONTROLES (TRATAMIENTO DEL RIESGO Y PLANES ATENUANTES) - ELIMINACIÓN]]&"Sustitución del riesgo; "&año24[[#This Row],[CONTROLES (TRATAMIENTO DEL RIESGO Y PLANES ATENUANTES) - SUSTITUCIÓN]]&"Controles de Ingenieria; "&año24[[#This Row],[CONTROLES (TRATAMIENTO DEL RIESGO Y PLANES ATENUANTES) - CONTROLES DE INGENIERIA]]&" Controles administrativos; "&año24[[#This Row],[CONTROLES (TRATAMIENTO DEL RIESGO Y PLANES ATENUANTES) - CONTROLES ADMINISTRATIVOS / SEÑALIZACIÓN]]&"Controles de EPP; "&año24[[#This Row],[CONTROLES (TRATAMIENTO DEL RIESGO Y PLANES ATENUANTES) - ELEMENTOS DE PROTECCIÓN PERSONAL]] -> Eliminación del riesgo:NingunaSustitución del riesgo; NingunaControles de Ingenieria; Mantener Controles Existentes: Sistema de aterrizaje pararrayos Puesta a tierra de equipos Controles administrativos; Implementar programa de gestión de riesgo eléctrico Mantener controles existentes: *Inspección Vial (Identificación de cuerdas de alta, media, baja) *Uso de pertigueros en puntos identificados *Señalización riesgo eléctrico * Programa de Gestión Seguridad Basada en el Comportamiento * Procedimiento sistemas permiso de trabajo * Procedimiento Aislamiento de Fuentes de Energia * Anexo HSEQ para contratistas * Plan de emergenciasControles de EPP; Ver matriz de EPP | AH52: HS Parex Contratista | AI52: 2 Moderado | AJ52: Personas | AK52: 2 Improbable | AL52: =INDEX($AS$3:$AV$6,MATCH($AI52,$AR$3:$AR$6,FALSE),MATCH($AK52,$AS$7:$AV$7,FALSE)) -> 4 | AM52: =IF(año24[[#This Row],[VALORACION DEL RIESGO RESULTANTE CON CONTROLES (Riesgo residual) - Nivel de riesgo]]<=3,"Bajo",IF(año24[[#This Row],[VALORACION DEL RIESGO RESULTANTE CON CONTROLES (Riesgo residual) - Nivel de riesgo]]<=6,"Medio",IF(año24[[#This Row],[VALORACION DEL RIESGO RESULTANTE CON CONTROLES (Riesgo residual) - Nivel de riesgo]]<=12,"Alto","Extremo"))) -> Medio | AO52: =IF(AL52<=4,"SI",IF(AL52>=5,"NO")) -> SI | AP52: ="El nivel del riesgo es"&" "&año24[[#This Row],[VALORACION DEL RIESGO RESULTANTE CON CONTROLES (Riesgo residual) - INTERPRETACIÓN DEL RIESGO]]&" siendo las principales consecuencias las siguientes; "&año24[[#This Row],[Consecuencias (AT/EL)]] -> El nivel del riesgo es Medio siendo las principales consecuencias las siguientes; AT | AQ52: =_xlfn.XLOOKUP(año24[[#This Row],[VALORACION DEL RIESGO RESULTANTE CON CONTROLES (Riesgo residual) - INTERPRETACIÓN DEL RIESGO]], Nivel[Calsificación], Nivel[Imagen]) -> #VALUE!
B53: 44 | C53: 2024 | D53: Campos Parex | E53: Rig Up- Rig Down | F53: Rig Up- Rig Down de equipo / campamento Traslado de la mesa, líneas de succión, limpiar filtros de succión, correr y cortar cables de perforación, campamento Stack Out de Equipos en Patios | G53: Locación | H53: Contacto dérmico con sustancias químicas al acondicionar tanques y bombas. | I53: Químico | J53: =_xlfn.XLOOKUP(año24[[#This Row],[PELIGRO -Tipo]], Tabla12[Calsificación], Tabla12[Imagen]) -> #VALUE! | K53: 3.4 Líquidos, rocíos | L53: AT/EL | M53: Rutinaria | N53: Interna | O53: 2 | P53: 53 | Q53: 2 | R53: 8 | S53: Contratistas | T53: Identificación de peligrosidad con Sistema Globalmente armonizado | U53: Programa de Higiene Ocupacional (Mediciones de higiene según cronoggrama) | V53: Programa de gestión de riesgo químico EPP Exámenes médicos ocupacionales Capacitación en riesgo químico | W53: 2 Moderado | X53: Personas | Y53: 3 Probable | Z53: =INDEX($AS$3:$AV$6,MATCH($W53,$AR$3:$AR$6,FALSE),MATCH($Y53,AS$7:$AV$7,FALSE)) -> 6 | AA53: Si (Ver matriz de requisitos legales) | AB53: Ninguna | AC53: Ninguna | AD53: Ninguna | AE53: Continuidad a los controles implementados: Seguimiento al programa de gestión del riesgo químico Programa de Seguridad Basada en el Comportamiento | AF53: Ver matriz de EPP | AG53: ="Eliminación del riesgo:"&año24[[#This Row],[CONTROLES (TRATAMIENTO DEL RIESGO Y PLANES ATENUANTES) - ELIMINACIÓN]]&"Sustitución del riesgo; "&año24[[#This Row],[CONTROLES (TRATAMIENTO DEL RIESGO Y PLANES ATENUANTES) - SUSTITUCIÓN]]&"Controles de Ingenieria; "&año24[[#This Row],[CONTROLES (TRATAMIENTO DEL RIESGO Y PLANES ATENUANTES) - CONTROLES DE INGENIERIA]]&" Controles administrativos; "&año24[[#This Row],[CONTROLES (TRATAMIENTO DEL RIESGO Y PLANES ATENUANTES) - CONTROLES ADMINISTRATIVOS / SEÑALIZACIÓN]]&"Controles de EPP; "&año24[[#This Row],[CONTROLES (TRATAMIENTO DEL RIESGO Y PLANES ATENUANTES) - ELEMENTOS DE PROTECCIÓN PERSONAL]] -> Eliminación del riesgo:NingunaSustitución del riesgo; NingunaControles de Ingenieria; Ninguna Controles administrativos; Continuidad a los controles implementados: Seguimiento al programa de gestión del riesgo químico Programa de Seguridad Basada en el ComportamientoControles de EPP; Ver matriz de EPP | AH53: HS Parex Contratista | AI53: 2 Moderado | AJ53: Personas | AK53: 2 Improbable | AL53: =INDEX($AS$3:$AV$6,MATCH($AI53,$AR$3:$AR$6,FALSE),MATCH($AK53,$AS$7:$AV$7,FALSE)) -> 4 | AM53: =IF(año24[[#This Row],[VALORACION DEL RIESGO RESULTANTE CON CONTROLES (Riesgo residual) - Nivel de riesgo]]<=3,"Bajo",IF(año24[[#This Row],[VALORACION DEL RIESGO RESULTANTE CON CONTROLES (Riesgo residual) - Nivel de riesgo]]<=6,"Medio",IF(año24[[#This Row],[VALORACION DEL RIESGO RESULTANTE CON CONTROLES (Riesgo residual) - Nivel de riesgo]]<=12,"Alto","Extremo"))) -> Medio | AO53: =IF(AL53<=4,"SI",IF(AL53>=5,"NO")) -> SI | AP53: ="El nivel del riesgo es"&" "&año24[[#This Row],[VALORACION DEL RIESGO RESULTANTE CON CONTROLES (Riesgo residual) - INTERPRETACIÓN DEL RIESGO]]&" siendo las principales consecuencias las siguientes; "&año24[[#This Row],[Consecuencias (AT/EL)]] -> El nivel del riesgo es Medio siendo las principales consecuencias las siguientes; AT/EL | AQ53: =_xlfn.XLOOKUP(año24[[#This Row],[VALORACION DEL RIESGO RESULTANTE CON CONTROLES (Riesgo residual) - INTERPRETACIÓN DEL RIESGO]], Nivel[Calsificación], Nivel[Imagen]) -> #VALUE!
B54: 45 | C54: 2024 | D54: Campos Parex | E54: Rig Up- Rig Down | F54: Rig Up- Rig Down de equipo / campamento Traslado de la mesa, líneas de succión, limpiar filtros de succión, correr y cortar cables de perforación, campamento Stack Out de Equipos en Patios | G54: Locación | H54: Ruido generado por equipos de perforación | I54: Físico | J54: =_xlfn.XLOOKUP(año24[[#This Row],[PELIGRO -Tipo]], Tabla12[Calsificación], Tabla12[Imagen]) -> #VALUE! | K54: 2.1 Ruido | L54: EL | M54: Rutinaria | N54: Interna | O54: 2 | P54: 53 | Q54: 2 | R54: 8 | S54: Contratistas | T54: Mantenimiento de equipos y maquinaria | U54: Señalización Programa de Higiene Ocupacional | V54: EPP Exámenes médicos ocupacionales | W54: 3 Serio | X54: Personas | Y54: 2 Improbable | Z54: =INDEX($AS$3:$AV$6,MATCH($W54,$AR$3:$AR$6,FALSE),MATCH($Y54,AS$7:$AV$7,FALSE)) -> 6 | AA54: Si (Ver matriz de requisitos legales) | AD54: Programa de mantenimiento de equipos | AE54: * PVE Auditivo *Seguridad Basada en el Comportamiento | AF54: Ver matriz de EPP | AG54: ="Eliminación del riesgo:"&año24[[#This Row],[CONTROLES (TRATAMIENTO DEL RIESGO Y PLANES ATENUANTES) - ELIMINACIÓN]]&"Sustitución del riesgo; "&año24[[#This Row],[CONTROLES (TRATAMIENTO DEL RIESGO Y PLANES ATENUANTES) - SUSTITUCIÓN]]&"Controles de Ingenieria; "&año24[[#This Row],[CONTROLES (TRATAMIENTO DEL RIESGO Y PLANES ATENUANTES) - CONTROLES DE INGENIERIA]]&" Controles administrativos; "&año24[[#This Row],[CONTROLES (TRATAMIENTO DEL RIESGO Y PLANES ATENUANTES) - CONTROLES ADMINISTRATIVOS / SEÑALIZACIÓN]]&"Controles de EPP; "&año24[[#This Row],[CONTROLES (TRATAMIENTO DEL RIESGO Y PLANES ATENUANTES) - ELEMENTOS DE PROTECCIÓN PERSONAL]] -> Eliminación del riesgo:Sustitución del riesgo; Controles de Ingenieria; Programa de mantenimiento de equipos Controles administrativos; * PVE Auditivo *Seguridad Basada en el ComportamientoControles de EPP; Ver matriz de EPP | AH54: HS Parex Contratista | AI54: 2 Moderado | AJ54: Personas | AK54: 2 Improbable | AL54: =INDEX($AS$3:$AV$6,MATCH($AI54,$AR$3:$AR$6,FALSE),MATCH($AK54,$AS$7:$AV$7,FALSE)) -> 4 | AM54: =IF(año24[[#This Row],[VALORACION DEL RIESGO RESULTANTE CON CONTROLES (Riesgo residual) - Nivel de riesgo]]<=3,"Bajo",IF(año24[[#This Row],[VALORACION DEL RIESGO RESULTANTE CON CONTROLES (Riesgo residual) - Nivel de riesgo]]<=6,"Medio",IF(año24[[#This Row],[VALORACION DEL RIESGO RESULTANTE CON CONTROLES (Riesgo residual) - Nivel de riesgo]]<=12,"Alto","Extremo"))) -> Medio | AO54: =IF(AL54<=4,"SI",IF(AL54>=5,"NO")) -> SI | AP54: ="El nivel del riesgo es"&" "&año24[[#This Row],[VALORACION DEL RIESGO RESULTANTE CON CONTROLES (Riesgo residual) - INTERPRETACIÓN DEL RIESGO]]&" siendo las principales consecuencias las siguientes; "&año24[[#This Row],[Consecuencias (AT/EL)]] -> El nivel del riesgo es Medio siendo las principales consecuencias las siguientes; EL | AQ54: =_xlfn.XLOOKUP(año24[[#This Row],[VALORACION DEL RIESGO RESULTANTE CON CONTROLES (Riesgo residual) - INTERPRETACIÓN DEL RIESGO]], Nivel[Calsificación], Nivel[Imagen]) -> #VALUE!
B55: 46 | C55: 2024 | D55: Campos Parex | E55: Rig Up- Rig Down | F55: Rig Up- Rig Down de equipo / campamento Traslado de la mesa, líneas de succión, limpiar filtros de succión, correr y cortar cables de perforación, campamento Stack Out de Equipos en Patios | G55: Locación | H55: Contacto directo o indirecto al conectar/desconectar luminarias y suministro eléctrico de campamento | I55: Condiciones_de_seguridad | J55: =_xlfn.XLOOKUP(año24[[#This Row],[PELIGRO -Tipo]], Tabla12[Calsificación], Tabla12[Imagen]) -> #VALUE! | K55: 6.2 Eléctrico | L55: AT | M55: Rutinaria | N55: Interna | O55: 2 | P55: 53 | Q55: 2 | R55: 8 | S55: Contratistas | T55: Mantenimientos preventivos y predictivos a los equipos | U55: Sistema puesta a tierra Inspecciones de seguridad Señalización reglamentaria riesgo eléctrico | V55: Certificado de Aislamiento (Bloqueo, candado y Etiquetado). Sistema lock out 5 Reglas de oro aislamiento. Procedimiento Permisos de trabajo, ATS Personal competente para trabajos eléctricos de acuerdo con certificación conte Capacitación riesgo eléctrico | W55: 3 Serio | X55: Personas | Y55: 3 Probable | Z55: =INDEX($AS$3:$AV$6,MATCH($W55,$AR$3:$AR$6,FALSE),MATCH($Y55,AS$7:$AV$7,FALSE)) -> 9 | AA55: Si (Ver matriz de requisitos legales) | AB55: Ninguna | AC55: Ninguna | AD55: Mantener Controles Existentes: Sistema de aterrizaje pararrayos Puesta a tierra de equipos | AE55: Implementar programa de gestión de riesgo eléctrico Mantener controles existentes: *Inspección Vial (Identificación de cuerdas de alta, media, baja) *Uso de pertigueros en puntos identificados *Señalización riesgo eléctrico * Programa de Gestión Seguridad Basada en el Comportamiento * Procedimiento sistemas permiso de trabajo * Procedimiento Aislamiento de Fuentes de Energia * Anexo HSEQ para contratistas * Plan de emergencias | AF55: Ver matriz de EPP | AG55: ="Eliminación del riesgo:"&año24[[#This Row],[CONTROLES (TRATAMIENTO DEL RIESGO Y PLANES ATENUANTES) - ELIMINACIÓN]]&"Sustitución del riesgo; "&año24[[#This Row],[CONTROLES (TRATAMIENTO DEL RIESGO Y PLANES ATENUANTES) - SUSTITUCIÓN]]&"Controles de Ingenieria; "&año24[[#This Row],[CONTROLES (TRATAMIENTO DEL RIESGO Y PLANES ATENUANTES) - CONTROLES DE INGENIERIA]]&" Controles administrativos; "&año24[[#This Row],[CONTROLES (TRATAMIENTO DEL RIESGO Y PLANES ATENUANTES) - CONTROLES ADMINISTRATIVOS / SEÑALIZACIÓN]]&"Controles de EPP; "&año24[[#This Row],[CONTROLES (TRATAMIENTO DEL RIESGO Y PLANES ATENUANTES) - ELEMENTOS DE PROTECCIÓN PERSONAL]] -> Eliminación del riesgo:NingunaSustitución del riesgo; NingunaControles de Ingenieria; Mantener Controles Existentes: Sistema de aterrizaje pararrayos Puesta a tierra de equipos Controles administrativos; Implementar programa de gestión de riesgo eléctrico Mantener controles existentes: *Inspección Vial (Identificación de cuerdas de alta, media, baja) *Uso de pertigueros en puntos identificados *Señalización riesgo eléctrico * Programa de Gestión Seguridad Basada en el Comportamiento * Procedimiento sistemas permiso de trabajo * Procedimiento Aislamiento de Fuentes de Energia * Anexo HSEQ para contratistas * Plan de emergenciasControles de EPP; Ver matriz de EPP | AH55: HS Parex Contratista | AI55: 2 Moderado | AJ55: Personas | AK55: 2 Improbable | AL55: =INDEX($AS$3:$AV$6,MATCH($AI55,$AR$3:$AR$6,FALSE),MATCH($AK55,$AS$7:$AV$7,FALSE)) -> 4 | AM55: =IF(año24[[#This Row],[VALORACION DEL RIESGO RESULTANTE CON CONTROLES (Riesgo residual) - Nivel de riesgo]]<=3,"Bajo",IF(año24[[#This Row],[VALORACION DEL RIESGO RESULTANTE CON CONTROLES (Riesgo residual) - Nivel de riesgo]]<=6,"Medio",IF(año24[[#This Row],[VALORACION DEL RIESGO RESULTANTE CON CONTROLES (Riesgo residual) - Nivel de riesgo]]<=12,"Alto","Extremo"))) -> Medio | AO55: =IF(AL55<=4,"SI",IF(AL55>=5,"NO")) -> SI | AP55: ="El nivel del riesgo es"&" "&año24[[#This Row],[VALORACION DEL RIESGO RESULTANTE CON CONTROLES (Riesgo residual) - INTERPRETACIÓN DEL RIESGO]]&" siendo las principales consecuencias las siguientes; "&año24[[#This Row],[Consecuencias (AT/EL)]] -> El nivel del riesgo es Medio siendo las principales consecuencias las siguientes; AT | AQ55: =_xlfn.XLOOKUP(año24[[#This Row],[VALORACION DEL RIESGO RESULTANTE CON CONTROLES (Riesgo residual) - INTERPRETACIÓN DEL RIESGO]], Nivel[Calsificación], Nivel[Imagen]) -> #VALUE!
B56: 47 | C56: 2024 | D56: Campos Parex | E56: Rig Up- Rig Down | F56: Rig Up- Rig Down de equipo / campamento Traslado de la mesa, líneas de succión, limpiar filtros de succión, correr y cortar cables de perforación, campamento Stack Out de Equipos en Patios | G56: Locación | H56: Caída de objetos, al levantar - bajar la torre del equipo | I56: Condiciones_de_seguridad | J56: =_xlfn.XLOOKUP(año24[[#This Row],[PELIGRO -Tipo]], Tabla12[Calsificación], Tabla12[Imagen]) -> #VALUE! | K56: 6.1 Mecánico | L56: AT | M56: Rutinaria | N56: Interna | O56: 2 | P56: 53 | Q56: 2 | R56: 8 | S56: Contratistas | T56: Mantenimientos preventivos y predictivos a los equipos Inspección preoperacional de equipos y herramientas | U56: Inspecciones de seguridad | V56: Programa de capacitación (Riesgo Mecánico, cuidado de manos) Procedimiento de permisos de trabajo, ATS Programa de seguridad basada en el comportamiento | W56: 3 Serio | X56: Personas | Y56: 3 Probable | Z56: =INDEX($AS$3:$AV$6,MATCH($W56,$AR$3:$AR$6,FALSE),MATCH($Y56,AS$7:$AV$7,FALSE)) -> 9 | AA56: Si (Ver matriz de requisitos legales) | AB56: Ninguna | AC56: Ninguna | AD56: * Identificar en herramienta puntos de peligro (Pellizco; machucon; agarre) * Instalación de guayas antilatigos | AE56: *Implementar Programa de Gestión del Riesgo Mecánico * Seguimiento Programa de mantenimiento mecánico y eléctrico *Programa DROPS Mantener controles existentes: * Programa de Gestión Seguridad Basada en el Comportamiento * Programa de Gestión Cuidado de Manos * Manual de gestión de proyectos de facilidades * Procedimiento Sistema Permisos de Trabajo * Procedimiento Manejo Seguro de Herramientas Manuales * Procedimiento Levantamiento de Cargas * Anexo HSEQ para contratistas * Plan de Emergencias | AF56: Ver matriz de EPP | AG56: ="Eliminación del riesgo:"&año24[[#This Row],[CONTROLES (TRATAMIENTO DEL RIESGO Y PLANES ATENUANTES) - ELIMINACIÓN]]&"Sustitución del riesgo; "&año24[[#This Row],[CONTROLES (TRATAMIENTO DEL RIESGO Y PLANES ATENUANTES) - SUSTITUCIÓN]]&"Controles de Ingenieria; "&año24[[#This Row],[CONTROLES (TRATAMIENTO DEL RIESGO Y PLANES ATENUANTES) - CONTROLES DE INGENIERIA]]&" Controles administrativos; "&año24[[#This Row],[CONTROLES (TRATAMIENTO DEL RIESGO Y PLANES ATENUANTES) - CONTROLES ADMINISTRATIVOS / SEÑALIZACIÓN]]&"Controles de EPP; "&año24[[#This Row],[CONTROLES (TRATAMIENTO DEL RIESGO Y PLANES ATENUANTES) - ELEMENTOS DE PROTECCIÓN PERSONAL]] -> Eliminación del riesgo:NingunaSustitución del riesgo; NingunaControles de Ingenieria; * Identificar en herramienta puntos de peligro (Pellizco; machucon; agarre) * Instalación de guayas antilatigos Controles administrativos; *Implementar Programa de Gestión del Riesgo Mecánico * Seguimiento Programa de mantenimiento mecánico y eléctrico *Programa DROPS Mantener controles existentes: * Programa de Gestión Seguridad Basada en el Comportamiento * Programa de Gestión Cuidado de Manos * Manual de gestión de proyectos de facilidades * Procedimiento Sistema Permisos de Trabajo * Procedimiento Manejo Seguro de Herramientas Manuales * Procedimiento Levantamiento de Cargas * Anexo HSEQ para contratistas * Plan de EmergenciasControles de EPP; Ver matriz de EPP | AH56: HS Parex Contratista | AI56: 2 Moderado | AJ56: Personas | AK56: 2 Improbable | AL56: =INDEX($AS$3:$AV$6,MATCH($AI56,$AR$3:$AR$6,FALSE),MATCH($AK56,$AS$7:$AV$7,FALSE)) -> 4 | AM56: =IF(año24[[#This Row],[VALORACION DEL RIESGO RESULTANTE CON CONTROLES (Riesgo residual) - Nivel de riesgo]]<=3,"Bajo",IF(año24[[#This Row],[VALORACION DEL RIESGO RESULTANTE CON CONTROLES (Riesgo residual) - Nivel de riesgo]]<=6,"Medio",IF(año24[[#This Row],[VALORACION DEL RIESGO RESULTANTE CON CONTROLES (Riesgo residual) - Nivel de riesgo]]<=12,"Alto","Extremo"))) -> Medio | AO56: =IF(AL56<=4,"SI",IF(AL56>=5,"NO")) -> SI | AP56: ="El nivel del riesgo es"&" "&año24[[#This Row],[VALORACION DEL RIESGO RESULTANTE CON CONTROLES (Riesgo residual) - INTERPRETACIÓN DEL RIESGO]]&" siendo las principales consecuencias las siguientes; "&año24[[#This Row],[Consecuencias (AT/EL)]] -> El nivel del riesgo es Medio siendo las principales consecuencias las siguientes; AT | AQ56: =_xlfn.XLOOKUP(año24[[#This Row],[VALORACION DEL RIESGO RESULTANTE CON CONTROLES (Riesgo residual) - INTERPRETACIÓN DEL RIESGO]], Nivel[Calsificación], Nivel[Imagen]) -> #VALUE!
B57: 48 | C57: 2024 | D57: Campos Parex | E57: Rig Up- Rig Down | F57: Rig Up- Rig Down de equipo / campamento Traslado de la mesa, líneas de succión, limpiar filtros de succión, correr y cortar cables de perforación, campamento Stack Out de Equipos en Patios | G57: Locación | H57: Esfuerzos excesivos y posturas inadecuadas por el cargue o descargue de pesos superiores a 25 Kg. | I57: Biomecánicas | J57: =_xlfn.XLOOKUP(año24[[#This Row],[PELIGRO -Tipo]], Tabla12[Calsificación], Tabla12[Imagen]) -> #VALUE! | K57: 5.4 Manipulación manual de cargas | L57: EL | M57: Rutinaria | N57: Interna | O57: 2 | P57: 53 | Q57: 2 | R57: 8 | S57: Contratistas | U57: Estudio de puestos de trabajo | V57: Exámen médico ocupacional con enfásis osteomuscular PVE Lesiones osteomusculares Capacitación en Higiene postural y manejo de cargas | W57: 2 Moderado | X57: Personas | Y57: 3 Probable | Z57: =INDEX($AS$3:$AV$6,MATCH($W57,$AR$3:$AR$6,FALSE),MATCH($Y57,AS$7:$AV$7,FALSE)) -> 6 | AA57: Si (Ver matriz de requisitos legales) | AB57: Ninguna | AC57: Ninguna | AD57: Ninguna | AE57: * Programa de Gestión Seguridad Basada en el Comportamiento * Sequimiento Programa de Vigilancia Epidemiológica condiciones ergonómicas inadecuadas y Desórdenes Músculo Esqueléticos * Anexo HSEQ para contratistas | AF57: Ver matriz de EPP | AG57: ="Eliminación del riesgo:"&año24[[#This Row],[CONTROLES (TRATAMIENTO DEL RIESGO Y PLANES ATENUANTES) - ELIMINACIÓN]]&"Sustitución del riesgo; "&año24[[#This Row],[CONTROLES (TRATAMIENTO DEL RIESGO Y PLANES ATENUANTES) - SUSTITUCIÓN]]&"Controles de Ingenieria; "&año24[[#This Row],[CONTROLES (TRATAMIENTO DEL RIESGO Y PLANES ATENUANTES) - CONTROLES DE INGENIERIA]]&" Controles administrativos; "&año24[[#This Row],[CONTROLES (TRATAMIENTO DEL RIESGO Y PLANES ATENUANTES) - CONTROLES ADMINISTRATIVOS / SEÑALIZACIÓN]]&"Controles de EPP; "&año24[[#This Row],[CONTROLES (TRATAMIENTO DEL RIESGO Y PLANES ATENUANTES) - ELEMENTOS DE PROTECCIÓN PERSONAL]] -> Eliminación del riesgo:NingunaSustitución del riesgo; NingunaControles de Ingenieria; Ninguna Controles administrativos; * Programa de Gestión Seguridad Basada en el Comportamiento * Sequimiento Programa de Vigilancia Epidemiológica condiciones ergonómicas inadecuadas y Desórdenes Músculo Esqueléticos * Anexo HSEQ para contratistas Controles de EPP; Ver matriz de EPP | AH57: HS Parex Contratista | AI57: 2 Moderado | AJ57: Personas | AK57: 2 Improbable | AL57: =INDEX($AS$3:$AV$6,MATCH($AI57,$AR$3:$AR$6,FALSE),MATCH($AK57,$AS$7:$AV$7,FALSE)) -> 4 | AM57: =IF(año24[[#This Row],[VALORACION DEL RIESGO RESULTANTE CON CONTROLES (Riesgo residual) - Nivel de riesgo]]<=3,"Bajo",IF(año24[[#This Row],[VALORACION DEL RIESGO RESULTANTE CON CONTROLES (Riesgo residual) - Nivel de riesgo]]<=6,"Medio",IF(año24[[#This Row],[VALORACION DEL RIESGO RESULTANTE CON CONTROLES (Riesgo residual) - Nivel de riesgo]]<=12,"Alto","Extremo"))) -> Medio | AO57: =IF(AL57<=4,"SI",IF(AL57>=5,"NO")) -> SI | AP57: ="El nivel del riesgo es"&" "&año24[[#This Row],[VALORACION DEL RIESGO RESULTANTE CON CONTROLES (Riesgo residual) - INTERPRETACIÓN DEL RIESGO]]&" siendo las principales consecuencias las siguientes; "&año24[[#This Row],[Consecuencias (AT/EL)]] -> El nivel del riesgo es Medio siendo las principales consecuencias las siguientes; EL | AQ57: =_xlfn.XLOOKUP(año24[[#This Row],[VALORACION DEL RIESGO RESULTANTE CON CONTROLES (Riesgo residual) - INTERPRETACIÓN DEL RIESGO]], Nivel[Calsificación], Nivel[Imagen]) -> #VALUE!
B58: 49 | C58: 2024 | D58: Campos Parex | E58: Rig Up- Rig Down | F58: Rig Up- Rig Down de equipo / campamento Traslado de la mesa, líneas de succión, limpiar filtros de succión, correr y cortar cables de perforación, campamento Stack Out de Equipos en Patios | G58: Locación | H58: Radiación no ionizante (Exposición a rayos solares) | I58: Físico | J58: =_xlfn.XLOOKUP(año24[[#This Row],[PELIGRO -Tipo]], Tabla12[Calsificación], Tabla12[Imagen]) -> #VALUE! | K58: 2.7 Radiaciones No ionizantes | L58: EL | M58: Rutinaria | N58: Interna | O58: 2 | P58: 53 | Q58: 2 | R58: 4 | S58: Contratistas | T58: Ninguna | U58: Ninguna | V58: Hidratación. Uso de bloqueador solar Examen Ocupacional con énfasis dermatológico | W58: 2 Moderado | X58: Personas | Y58: 3 Probable | Z58: =INDEX($AS$3:$AV$6,MATCH($W58,$AR$3:$AR$6,FALSE),MATCH($Y58,AS$7:$AV$7,FALSE)) -> 6 | AA58: Si (Ver matriz de requisitos legales) | AB58: Ninguna | AC58: Ninguna | AD58: Ninguna | AE58: Mantener controles existentes: Hidratación. Uso de bloqueador solar Examen Ocupacional con énfasis dermatológico Evitar la exposición directa a la luz solar dos horas antes y dos horas después del medio día. Capacitación en lesiones de piel | AF58: Ver matriz de EPP | AG58: ="Eliminación del riesgo:"&año24[[#This Row],[CONTROLES (TRATAMIENTO DEL RIESGO Y PLANES ATENUANTES) - ELIMINACIÓN]]&"Sustitución del riesgo; "&año24[[#This Row],[CONTROLES (TRATAMIENTO DEL RIESGO Y PLANES ATENUANTES) - SUSTITUCIÓN]]&"Controles de Ingenieria; "&año24[[#This Row],[CONTROLES (TRATAMIENTO DEL RIESGO Y PLANES ATENUANTES) - CONTROLES DE INGENIERIA]]&" Controles administrativos; "&año24[[#This Row],[CONTROLES (TRATAMIENTO DEL RIESGO Y PLANES ATENUANTES) - CONTROLES ADMINISTRATIVOS / SEÑALIZACIÓN]]&"Controles de EPP; "&año24[[#This Row],[CONTROLES (TRATAMIENTO DEL RIESGO Y PLANES ATENUANTES) - ELEMENTOS DE PROTECCIÓN PERSONAL]] -> Eliminación del riesgo:NingunaSustitución del riesgo; NingunaControles de Ingenieria; Ninguna Controles administrativos; Mantener controles existentes: Hidratación. Uso de bloqueador solar Examen Ocupacional con énfasis dermatológico Evitar la exposición directa a la luz solar dos horas antes y dos horas después del medio día. Capacitación en lesiones de piel Controles de EPP; Ver matriz de EPP | AH58: HS Parex Contratista | AI58: 2 Moderado | AJ58: Personas | AK58: 2 Improbable | AL58: =INDEX($AS$3:$AV$6,MATCH($AI58,$AR$3:$AR$6,FALSE),MATCH($AK58,$AS$7:$AV$7,FALSE)) -> 4 | AM58: =IF(año24[[#This Row],[VALORACION DEL RIESGO RESULTANTE CON CONTROLES (Riesgo residual) - Nivel de riesgo]]<=3,"Bajo",IF(año24[[#This Row],[VALORACION DEL RIESGO RESULTANTE CON CONTROLES (Riesgo residual) - Nivel de riesgo]]<=6,"Medio",IF(año24[[#This Row],[VALORACION DEL RIESGO RESULTANTE CON CONTROLES (Riesgo residual) - Nivel de riesgo]]<=12,"Alto","Extremo"))) -> Medio | AO58: =IF(AL58<=4,"SI",IF(AL58>=5,"NO")) -> SI | AP58: ="El nivel del riesgo es"&" "&año24[[#This Row],[VALORACION DEL RIESGO RESULTANTE CON CONTROLES (Riesgo residual) - INTERPRETACIÓN DEL RIESGO]]&" siendo las principales consecuencias las siguientes; "&año24[[#This Row],[Consecuencias (AT/EL)]] -> El nivel del riesgo es Medio siendo las principales consecuencias las siguientes; EL | AQ58: =_xlfn.XLOOKUP(año24[[#This Row],[VALORACION DEL RIESGO RESULTANTE CON CONTROLES (Riesgo residual) - INTERPRETACIÓN DEL RIESGO]], Nivel[Calsificación], Nivel[Imagen]) -> #VALUE!
